Workbook

Sheet Guide
A1: 단계 | B1: 가이드
A2: 1 | B2: Source Check에서 소스 단위로 상태를 체크하세요.
A3: 2 | B3: Item Audit에서 각 항목 바로 옆 체크칸(landing/title/description/thumbnail)을 채우세요.
A4: 3 | B4: source_review_status는 Source Check 상태를 자동 참조합니다.

Sheet Source Check
A1: review_status | B1: source_id | C1: source_name | D1: source_url | E1: source_check | F1: landing_check | G1: thumbnail_check | H1: title_check | I1: description_check | J1: source_issue_notes | K1: source_active | L1: source_level | M1: source_added_at | N1: item_count | O1: exposed_item_count | P1: memo_item_count | Q1: latest_exposed_date
A2: 미확인 | B2: 62 | C2: generalist.com | D2: https://www.generalist.com/ | K2: 1 | L2: core | M2: 2026-04-15 06:31:36 | N2: 21 | O2: 3 | P2: 0 | Q2: 2026-04-19
A3: 미확인 | B3: 63 | C3: bucketplace.com | D3: https://www.bucketplace.com/culture/ | K3: 1 | L3: light | M3: 2026-04-15 06:31:36 | N3: 19 | O3: 1 | P3: 0 | Q3: 2026-04-18
A4: 미확인 | B4: 61 | C4: techblog.gccompany.co.kr | D4: https://techblog.gccompany.co.kr/ | K4: 1 | L4: focus | M4: 2026-04-15 06:31:35 | N4: 11 | O4: 0 | P4: 0
A5: 미확인 | B5: 59 | C5: intercom.com | D5: https://www.intercom.com/blog/ | K5: 1 | L5: focus | M5: 2026-04-15 06:31:34 | N5: 16 | O5: 0 | P5: 0
A6: 미확인 | B6: 58 | C6: uxdesign.cc | D6: https://uxdesign.cc/ | K6: 1 | L6: focus | M6: 2026-04-15 06:31:33 | N6: 11 | O6: 0 | P6: 0
A7: 미확인 | B7: 57 | C7: apple.com | D7: https://www.apple.com/kr/newsroom/ | K7: 1 | L7: focus | M7: 2026-04-15 06:31:33 | N7: 19 | O7: 0 | P7: 0
A8: 미확인 | B8: 56 | C8: newsroom.spotify.com | D8: https://newsroom.spotify.com/ | K8: 1 | L8: focus | M8: 2026-04-15 06:31:32 | N8: 11 | O8: 0 | P8: 0
A9: 미확인 | B9: 55 | C9: figma.com | D9: https://www.figma.com/blog/ | K9: 1 | L9: focus | M9: 2026-04-15 06:31:32 | N9: 19 | O9: 1 | P9: 0 | Q9: 2026-04-18
A10: 미확인 | B10: 54 | C10: thegradient.pub | D10: https://thegradient.pub/ | K10: 1 | L10: focus | M10: 2026-04-15 06:31:31 | N10: 16 | O10: 0 | P10: 0
A11: 미확인 | B11: 53 | C11: stratechery.com | D11: https://stratechery.com/ | K11: 1 | L11: focus | M11: 2026-04-15 06:31:31 | N11: 122 | O11: 10 | P11: 0 | Q11: 2026-04-19
A12: 미확인 | B12: 111 | C12: the-reader.or.kr | D12: https://www.the-reader.or.kr/ | K12: 1 | L12: light | M12: 2026-04-15 06:31:30 | N12: 1 | O12: 0 | P12: 0
A13: 미확인 | B13: 51 | C13: about.daangn.com | D13: https://about.daangn.com/blog/ | K13: 1 | L13: focus | M13: 2026-04-15 06:31:30 | N13: 22 | O13: 0 | P13: 0
A14: 미확인 | B14: 49 | C14: techcrunch.com | D14: https://techcrunch.com/ | K14: 1 | L14: focus | M14: 2026-04-15 06:31:29 | N14: 99 | O14: 10 | P14: 0 | Q14: 2026-04-17
A15: 미확인 | B15: 50 | C15: gcoo.io | D15: https://gcoo.io/en/blog | K15: 1 | L15: focus | M15: 2026-04-15 06:31:29 | N15: 19 | O15: 1 | P15: 0 | Q15: 2026-04-15
A16: 미확인 | B16: 48 | C16: toss.im | D16: https://toss.im/tossfeed | K16: 1 | L16: focus | M16: 2026-04-15 06:31:28 | N16: 52 | O16: 10 | P16: 0 | Q16: 2026-04-18
A17: 미확인 | B17: 47 | C17: medium.com | D17: https://medium.com/29cm | K17: 1 | L17: focus | M17: 2026-04-15 06:31:28 | N17: 11 | O17: 0 | P17: 0
A18: 미확인 | B18: 46 | C18: growth.design | D18: https://growth.design/ | K18: 1 | L18: focus | M18: 2026-04-15 06:31:27 | N18: 1 | O18: 0 | P18: 0
A19: 미확인 | B19: 44 | C19: producthunt.com | D19: https://www.producthunt.com/ | K19: 1 | L19: focus | M19: 2026-04-15 06:31:26 | N19: 110 | O19: 3 | P19: 0 | Q19: 2026-04-12
A20: 미확인 | B20: 45 | C20: jayoung.blog | D20: https://jayoung.blog/about | K20: 1 | L20: focus | M20: 2026-04-15 06:31:26 | N20: 21 | O20: 2 | P20: 1 | Q20: 2026-04-17
A21: 미확인 | B21: 43 | C21: plus.hankyung.com | D21: https://plus.hankyung.com/ | K21: 1 | L21: focus | M21: 2026-04-15 06:31:25 | N21: 39 | O21: 0 | P21: 0
A22: 미확인 | B22: 42 | C22: innoforest.co.kr | D22: https://www.innoforest.co.kr/report | K22: 1 | L22: light | M22: 2026-04-15 06:31:25 | N22: 1 | O22: 0 | P22: 0
A23: 미확인 | B23: 100 | C23: nngroup.com | D23: https://www.nngroup.com/ | K23: 1 | L23: focus | M23: 2026-04-15 06:31:24 | N23: 2 | O23: 2 | P23: 0 | Q23: 2026-04-17
A24: 미확인 | B24: 40 | C24: latpeed.com | D24: https://www.latpeed.com/ | K24: 1 | L24: light | M24: 2026-04-15 06:31:23 | N24: 1 | O24: 0 | P24: 0
A25: 미확인 | B25: 64 | C25: designboom.com | D25: https://www.designboom.com/ | K25: 1 | L25: core | M25: 2026-04-15 06:31:23 | N25: 20 | O25: 0 | P25: 0
A26: 미확인 | B26: 37 | C26: outstanding.kr | D26: https://outstanding.kr/search_detail/Ui%20%EC%A0%80%EC%9E%91%EA%B6%8C | K26: 1 | L26: focus | M26: 2026-04-15 06:31:22 | N26: 30 | O26: 3 | P26: 0 | Q26: 2026-04-12
A27: 미확인 | B27: 38 | C27: newneek.co | D27: https://newneek.co/ | K27: 1 | L27: core | M27: 2026-04-15 06:31:22 | N27: 62 | O27: 1 | P27: 0 | Q27: 2026-04-19
A28: 미확인 | B28: 36 | C28: longblack.co | D28: https://longblack.co/ | K28: 1 | L28: focus | M28: 2026-04-15 06:31:21 | N28: 45 | O28: 4 | P28: 0 | Q28: 2026-04-15

Sheet Item Audit
A1: review_status | B1: source_review_status | C1: source_id | D1: source_name | E1: source_url | F1: source_check | G1: item_id | H1: item_url | I1: landing_check | J1: title | K1: title_check | L1: summary | M1: description_check | N1: thumbnail_url | O1: thumbnail_check | P1: issue_category | Q1: fix_priority | R1: issue_notes | S1: source_active | T1: source_level | U1: source_added_at | V1: item_status | W1: exposure_count | X1: first_exposed_date | Y1: last_exposed_date | Z1: seen_since_2026_04_01 | AA1: has_note | AB1: note_updated_at | AC1: split_items | AD1: extraction_mode | AE1: landing_suspect | AF1: thumb_suspect | AG1: title_suspect | AH1: summary_suspect
A2: 미확인 | B2: =IFERROR(INDEX('Source Check'!$A:$A, MATCH(C2, 'Source Check'!$B:$B, 0)), "미등록") | C2: 62 | D2: generalist.com | E2: https://www.generalist.com/ | F2: =IFERROR(INDEX('Source Check'!$E:$E, MATCH(C2, 'Source Check'!$B:$B, 0)), "") | G2: 7907 | H2: https://www.generalist.com/ | J2: generalist.com | S2: 1 | T2: core | U2: 2026-04-15 06:31:36 | V2: active | W2: 0 | Z2: 0 | AA2: 0 | AC2: 0 | AE2: 0 | AF2: 1 | AG2: 1 | AH2: 1
A3: 미확인 | B3: =IFERROR(INDEX('Source Check'!$A:$A, MATCH(C3, 'Source Check'!$B:$B, 0)), "미등록") | C3: 62 | D3: generalist.com | E3: https://www.generalist.com/ | F3: =IFERROR(INDEX('Source Check'!$E:$E, MATCH(C3, 'Source Check'!$B:$B, 0)), "") | G3: 7714 | H3: https://www.generalist.com/p/54-books-to-read-in-2026 | J3: 54 books to read in 2026 | L3: Essential recommendations from some of the world's most interesting and accomplished people. | N3: https://substackcdn.com/image/fetch/$s_!OT6u!,f_auto,q_auto:good,fl_progressive:steep/https%3A%2F%2Fsubstack-post-media.s3.amazonaws.com%2Fpublic%2Fimages%2F4261ef09-5730-411d-8e39-ba88e4309d17_3200x1792.jpeg | S3: 1 | T3: core | U3: 2026-04-15 06:31:36 | V3: active | W3: 1 | X3: 2026-04-14 | Y3: 2026-04-14 | Z3: 1 | AA3: 0 | AC3: 0 | AE3: 0 | AF3: 0 | AG3: 0 | AH3: 0
A4: 미확인 | B4: =IFERROR(INDEX('Source Check'!$A:$A, MATCH(C4, 'Source Check'!$B:$B, 0)), "미등록") | C4: 62 | D4: generalist.com | E4: https://www.generalist.com/ | F4: =IFERROR(INDEX('Source Check'!$E:$E, MATCH(C4, 'Source Check'!$B:$B, 0)), "") | G4: 7695 | H4: https://www.generalist.com/p/how-a-20-person-startup-won-gold | J4: how a 20 person startup won gold | L4: Listen now | Tudor Achim explains how Harmonic built the world's first AI that produces formally verified outputs, why hallucinations drive creativity, and what happens when AI surpasses human mathematicians. | N4: https://substackcdn.com/image/fetch/$s_!S8uR!,w_1456,c_limit,f_auto,q_auto:good,fl_progressive:steep/https%3A%2F%2Fsubstack-post-media.s3.amazonaws.com%2Fpublic%2Fimages%2Fc3eb8b6f-d22b-42b4-8778-e726fbba7e39_1600x128.png | S4: 1 | T4: core | U4: 2026-04-15 06:31:36 | V4: active | W4: 1 | X4: 2026-04-13 | Y4: 2026-04-13 | Z4: 1 | AA4: 0 | AC4: 0 | AE4: 0 | AF4: 0 | AG4: 0 | AH4: 0
A5: 미확인 | B5: =IFERROR(INDEX('Source Check'!$A:$A, MATCH(C5, 'Source Check'!$B:$B, 0)), "미등록") | C5: 62 | D5: generalist.com | E5: https://www.generalist.com/ | F5: =IFERROR(INDEX('Source Check'!$E:$E, MATCH(C5, 'Source Check'!$B:$B, 0)), "") | G5: 360 | H5: https://www.generalist.com/p/why-being-a-generalist-vc-is-a-competitive-advantage | J5: Why Being a Generalist VC Is a Competitive Advantage | Aydin Senkut (Founder and Managing Partner at Felicis Ventures) | L5: Listen now | Felicis Ventures founder Aydin Senkut on how he built a top VC firm, his 10x decision framework, and why he's bullish on AI and automation. | N5: https://substackcdn.com/image/fetch/$s_!MFXo!,w_1456,c_limit,f_auto,q_auto:good,fl_progressive:steep/https%3A%2F%2Fsubstack-post-media.s3.amazonaws.com%2Fpublic%2Fimages%2F4d31932a-59f3-4e45-b41d-3c9b962b58b5_475x151.png | S5: 1 | T5: core | U5: 2026-04-15 06:31:36 | V5: active | W5: 0 | Z5: 0 | AA5: 0 | AC5: 0 | AE5: 0 | AF5: 0 | AG5: 0 | AH5: 0
A6: 미확인 | B6: =IFERROR(INDEX('Source Check'!$A:$A, MATCH(C6, 'Source Check'!$B:$B, 0)), "미등록") | C6: 62 | D6: generalist.com | E6: https://www.generalist.com/ | F6: =IFERROR(INDEX('Source Check'!$E:$E, MATCH(C6, 'Source Check'!$B:$B, 0)), "") | G6: 359 | H6: https://www.generalist.com/p/steve-case | J6: steve case | L6: Illustration by Eleanor Taylor Friends, Perhaps no one experienced the dotcom boom and bust quite as viscerally as Steve Case. The founder of Revolution began the decade as an executive at a small software company called Quantum Link, and ended it as the CEO of a behemoth: AOL. It is hard to overstate just how important a company AOL was at the start of the millennium. Unless you were already of working age and minded towards tech and business, there's a good chance you haven't calibrated its size appropriately. AOL was a giant. Between its IPO in 1992 and the start of the new millennium, its stock appreciated approximately 80,000% , reaching a peak of $222 billion in December 1999. By that point, it had eclipsed many of the business world's biggest companies, surpassing Disney, IBM, McDonald's, and Berkshire Hathaway. At the time, AOL was larger than Boeing and General Motors combined . It was also wildly significant and influential, responsible for opening the internet up to a new generation of users and making it fun to use. The AOL of that era pioneered many of the user experiences and behaviors that make up the modern web, from screen names to instant messaging. In January 2000, AOL looked set for another decade of dominance. On the tenth of that month, it announced a planned merger with Time Warner. Remarkably, AOL was the senior partner, receiving 55% of the combined $350 billion entity. Again, the scale of the deal is hard to comprehend unless you lived it. At the headline valuation, AOL Time Warner became the fourth largest company on the planet - a figure greater than "the output of Russia or the Netherlands." What came after is the subject of much study and coverage. The market crashed, the merger failed, and not long after, Case stepped down as AOL CEO. By 2005, Case publicly argued in favor of the two companies splitting, and at the end of the decade, that came to fruition. Though there were strong strategic merits to an AOL-Time Warner union, it proved to be a marriage that suited neither party. It seems as if we are in yet another torrid cycle and potentially one of greater magnitude than that which Case surfed. A recent analyst report argued that the current AI bubble is 17x greater than its dotcom corollary, and 4x larger than the 2008 financial crisis. (We can hope it will be more productive than the financial crash, at least.) A bubble is a strange environment in which to live. It is an even stranger one in which to build a business. How do you keep your feet on the ground when the world beneath is rushing past at a thousand miles an hour? How can you hold fast to reality when wide-eyed investors, gasping for breath, paint ever more fantastical futures in front of you and shove your pockets full of cash? Where is the boundary? Is there really such a thing as a horizon? We believe that "this time is different," and there is truth in that. We do not live in a perfectly iterated game. The board has changed, fresh players have stepped onto it, and new moves are always being invented. But it is more naive to pretend the past has nothing to teach us. In fundamental ways, today's founders face the same set of challenges as their late 90s forerunners. How do you build a team at warp speed? Is it possible to scale a culture when you're growing exponentially? How can you make smart acquisitions and avoid the most common missteps? What role should partnerships and business development play when you're forging a new category? As I thought about these questions, I realized that perhaps no one is better suited to speak from experience than Steve Case himself. And so, I asked him to reflect on his journey at AOL, the similarities and differences between that era and ours, and the lessons founders should heed. We also discuss what it was like to compete head-to-head against Bill Gates, the strategic necessity that drove the Time Warner deal, and the similarities between Jeff Bezos and Steve Jobs. Subscribe now Brought to you by Mercury What gets measured gets managed. And when you're juggling multiple portfolio companies, having a crystal clear measure of cash burn is invaluable. That's why you'll want to keep Mercury's cash burn rate calculator in your toolkit - and pass it along to the founders you're backing. In seconds, you can see how many months of runway remain at a startup's current burn. That kind of clarity can help guide make-or-break decisions around spend, headcount, and future funding rounds. Mercury does banking* differently. They don't stop at banking and financial software to help businesses move money. They help businesses stay two steps ahead with the help of free tools and resources like this . Use the free cash burn rate calculator *Mercury is a financial technology company, not a bank. Banking services provided through Choice Financial Group, Column N.A., and Evolve Bank & Trust; Members FDIC. An Interview with Steve Case To start, I'd love to connect the two eras we're talking about and the lessons we might take from them. How much does the current AI wave remind you of the dotcom bubble? It has some similarities, but some differences, too. Like the internet, AI has been many years in the making. When you look at AI, some of the core technologies can be traced back to something like 70 years ago. This is not a new idea. It just took that time for it to become a mainstream consumer phenomenon. Obviously, over the last ten to twenty years, a lot of companies have integrated AI. Most of the apps we use on our phones rely on AI to some extent. The difference is that nobody called it AI. But it was driving recommendation engines and so on; it was just more of a back-end, invisible thing. It only became an in-your-face visible technology with the success of ChatGPT. That timing dynamic reminds me of the dotcom era. The gold rush mentality does too. People feel that this is the next big thing, and they don't want to miss out, which leads to investors pouring a lot of money into companies. A few of those will be wildly successful, many will be OK, and a good number will also probably end up hitting the wall and going out of business, which is what happened with the internet. Clearly, AI as a core technology and platform is going to have a comparable or greater impact to the internet. It has the ability to transform industries and society in very fundamental ways, but there will be a mix of successes and failures. A final point I'd make is about government and policy. What most people don't appreciate about the internet is that the United States wouldn't have been the leader it was with respect to that technology were it not for a series of government decisions: first, you have the government's decision to fund the Defense Department's ARPANET, which basically became the internet. Next, there was the Justice Department's decision in 1984 to break up AT&T into seven regional operating companies, which drove communication costs down and made the internet much more affordable. Third, there was the decision by the FCC to mandate open access for the telephone networks so that they had to let AOL and others plug into them. And, finally, in the early 90s, Congress passed a law opening up the internet to consumers and businesses. Up until that point, it had been restricted to government agencies and educational institutions. It's easy to forget these things, but if they hadn't happened, the internet would not have evolved the way it did. In the case of AI, it's really important that we figure out what that policy overlay should be. How do you make sure that while the technology is being developed, you don't over-regulate and stifle innovation? Europe has historically made the mistake of focusing too much on what might go wrong and, as a result, stifles what might go right. At the same time, though, because AI is so ubiquitous already (versus the internet, which grew slowly before mass adoption), some engagement, some policy guardrails are necessary now. What might some common-sense guidelines look like? One of the lessons from the internet is that you need to mandate open access. When it comes to AI, I think we need to make sure the big platform companies are essentially required to have open access. We don't want to create a system that just allows the big companies to dominate; we have to force them to open their networks and keep them open for new companies to participate and innovate. You had the rare experience of building what was considered the most significant company of its time during a historic bull market. It remains to be seen to what extent AI is a bubble, but I suspect the lessons you learned building AOL during the dotcom boom are deeply relevant for today's founders. As a jumping-off point, how did you manage your mental game during that period? AOL went from a relatively small company to one of the most important on the planet in a short period of time. The company must have been changing noticeably almost every day. Part of my job was to be a shock absorber for the rest of the company. As the CEO, you have to even out the highs and lows for people. When things are going great, remind them about the risk. I used to call that "delegating paranoia." When things are down in the dumps, remind them of why you have a bright future. There were plenty of moments like that at AOL - we'd be on the cover of a magazine with the headline saying "AOL is going to go under for XYZ reason." It's your role to provide that balance so that people can focus on the overall mission. It probably helped that it took more than a decade for us to get real traction. I joke that AOL was a ten-year-in-the-making overnight success. The time it took us probably gave all of us, including me, more perspective and humility when all of a sudden it was this go-go-go momentum. It helped me not buy into all the positives or all the negatives. Beyond that, you have to surround yourself with good advisors, including board members. They were helpful in making sure we were taking a step back at the right times and not just focusing on the day-to-day so much that we missed something. You have to learn to look at the company not just as a snapshot but as a movie that's playing out. I imagine that one of the biggest challenges of scaling that fast is finding enough great people who understand what you're building, and creating the right structure to get the best out of them. Although AI founders today can probably get more leverage on people than during the 1990s, great talent is still essential. What was your approach to recruiting and organizing talent, and how did it evolve with the business? Well, it definitely evolved. In the early days, when we were just a couple dozen people, it was about surrounding ourselves with true believers. This was before people knew what the internet was, so there weren't that many people interested in it. We were looking for people who wanted to be a part of the journey and could add value to it. When headcount got into the hundreds, we started to be a bit more precise in terms of the roles we needed. You start to run searches for roles and look in a more structured, disciplined way. When we got into the thousands, and things really started accelerating, I realized that as the CEO, I couldn't be involved in everything. And so I needed to shift my mindset to spend the majority of my time on recruiting. It might not have been 50% of my actual hours, but it was more than 50% of my attention . A lot of my job in those days was not just promoting AOL but evangelizing the internet. I'd travel a lot and speak at a lot of conferences - Allen&Co in Sun Valley and others. I always had my radar on: Who's going to be there? Are there people who might be partners in a way that works for us and works for them? Is there anyone I'm really impressed with that I can convince to leave what they're doing and join us? Every meeting I was in, every conference I was attending - whatever it was that I was doing - looking for great people was always on my agenda. With the right people and the right focus, anything is possible. You mentioned that as the company scaled, you felt you couldn't do everything anymore. The pendulum in tech seems to have swung towards CEOs feeling like they should micro-manage more and have their hands on every part of the business. Why did that feel like the wrong fit for you? Read more | N6: https://substackcdn.com/image/fetch/$s_!u9G8!,f_auto,q_auto:good,fl_progressive:steep/https%3A%2F%2Fsubstack-post-media.s3.amazonaws.com%2Fpublic%2Fimages%2F2d820b70-d9eb-4eb1-bf85-7955d4408b07_3742x2839.jpeg | S6: 1 | T6: core | U6: 2026-04-15 06:31:36 | V6: active | W6: 0 | Z6: 0 | AA6: 0 | AC6: 0 | AE6: 0 | AF6: 0 | AG6: 0 | AH6: 0
A7: 미확인 | B7: =IFERROR(INDEX('Source Check'!$A:$A, MATCH(C7, 'Source Check'!$B:$B, 0)), "미등록") | C7: 62 | D7: generalist.com | E7: https://www.generalist.com/ | F7: =IFERROR(INDEX('Source Check'!$E:$E, MATCH(C7, 'Source Check'!$B:$B, 0)), "") | G7: 358 | H7: https://www.generalist.com/p/modern-meditations-immad-akhund | J7: modern meditations immad akhund | L7: Illustration by Eleanor Taylor Friends, How often do you think about the Mongolian Empire? For Mercury CEO, Immad Akhund, the answer seems to be "surprisingly often." For our final interview of the year, I asked the founder of one of my very favorite products to share his latest obsessions, contrarian opinions, and favorite reads. As well as outlining the h… Read more | N7: https://substackcdn.com/image/fetch/$s_!7vOy!,f_auto,q_auto:good,fl_progressive:steep/https%3A%2F%2Fsubstack-post-media.s3.amazonaws.com%2Fpublic%2Fimages%2F788cafb3-056b-46eb-a300-bc7e9ab40996_3857x3000.jpeg | S7: 1 | T7: core | U7: 2026-04-15 06:31:36 | V7: active | W7: 1 | X7: 2026-04-19 | Y7: 2026-04-19 | Z7: 1 | AA7: 0 | AC7: 0 | AE7: 0 | AF7: 0 | AG7: 0 | AH7: 0
A8: 미확인 | B8: =IFERROR(INDEX('Source Check'!$A:$A, MATCH(C8, 'Source Check'!$B:$B, 0)), "미등록") | C8: 62 | D8: generalist.com | E8: https://www.generalist.com/ | F8: =IFERROR(INDEX('Source Check'!$E:$E, MATCH(C8, 'Source Check'!$B:$B, 0)), "") | G8: 357 | H8: https://www.generalist.com/p/what-to-watch-in-2026 | J8: what to watch in 2026 | L8: 🌟 Happy 2026! There's never been a better time to join our premium newsletter and invest in yourself. It's designed to make you a better founder, investor, and technologist. Members get access to the strategies, tactics, and wisdom of exceptional investors and founders. Today's piece is a subscriber-only edition. Friends, The world is not waiting to start the year. In just over a week, we have seen that the world of 2026 will not be the same as that of 2025. Trump's actions in Venezuela are the most naked illustration of this fact, revealing the changing nature of power and shifts in spheres of relative influence. Technology is not immune to such developments, and, indeed, is a key input. Even with January just getting its footing, our sector is in motion: in a span of just a few weeks, Jensen Huang struck a $20 billion deal for Groq's talent and IP, revealed Nvidia's upcoming Rubin architecture, and saw China order its domestic companies to pause purchases of H200 chips. Meanwhile, DeepSeek released research rethinking AI training, ChatGPT launched a dedicated health product, Meta is attempting to purchase Chinese-founded startup Manus, and Anthropic is raising $10 billion at a $350 billion valuation. All of this is happening against the backdrop of growing unease about AI valuations and the possibility that we are in the midst of a rapidly inflating bubble primed to burst. As a reminder: it is January 9th. To try and grasp what (else) 2026 might have in store, particularly with regard to tech and venture capital, I reached out to a collection of more than 45 elite investors and thinkers. I asked each of these people to answer the question: What company, market, or trend do you think is most worth paying attention to in 2026? Below, you will find their answers, organized into seven themes. It includes entries from legends like Reid Hoffman, Kirsten Green, Gili Raanan, and Aydin Senkut, as well as those I consider the sharpest thinkers from the next generation. It is, in a sense, a collection of futures. A cadre of possible paths that may or may not unfurl. In big and little ways, I hope that they make you a little more aware of what may happen and where opportunities might lie. As was the case with last year's edition , I compiled this piece with the express goal of creating something that more than justifies the cost of The Generalist's premium subscription on its basis alone. Given the insights I've gleaned from it already, I believe we've achieved that for anyone who works in venture capital, actively angel invests, or is considering starting a company. I suspect it will also be of great use to operators who want to understand how their respective industries could develop. Here's what to expect: The robotics company helping with data center buildouts A voice AI company poised to come out of stealth The African fintech following Nubank's trajectory Where China is poised to outcompete America A potential landmark in nuclear energy An AI myth gets exposed The startups poised to win in Latin America The under-the-radar search startup used by Cursor To set yourself up for the best possible 2026, join our premium subscription for just $22/month today . It's designed to make you a radically better investor for a teeny fraction of the cost of a traditional investing intelligence service. Subscribe now Again, my hope and goal is that this piece alone repays the cost of a year's subscription. PS. You know this already, but for the avoidance of doubt: this is not investment advice . This is intended to surface new ideas and guide you toward interesting topics. Most submissions focus on private companies, but please heed this, particularly for those that highlight a crypto project with a public token. These tend to be hyper-volatile assets. You should always make investment decisions based on your own research. I. The physical world wakes up AI's most impressive feats have typically occurred on screens. That may be changing. Robots are learning by watching humans, excavators are moving dirt without drivers, and the robotics sector is splitting into two worlds: one of hype, another of quiet deployment. Read more | N8: https://substackcdn.com/image/fetch/$s_!_tEY!,f_auto,q_auto:good,fl_progressive:steep/https%3A%2F%2Fsubstack-post-media.s3.amazonaws.com%2Fpublic%2Fimages%2F1386660d-ee2b-45ca-8daa-9c5c71fbd0f0_2912x1632.png | S8: 1 | T8: core | U8: 2026-04-15 06:31:36 | V8: active | W8: 0 | Z8: 0 | AA8: 0 | AC8: 0 | AE8: 0 | AF8: 0 | AG8: 0 | AH8: 0
A9: 미확인 | B9: =IFERROR(INDEX('Source Check'!$A:$A, MATCH(C9, 'Source Check'!$B:$B, 0)), "미등록") | C9: 62 | D9: generalist.com | E9: https://www.generalist.com/ | F9: =IFERROR(INDEX('Source Check'!$E:$E, MATCH(C9, 'Source Check'!$B:$B, 0)), "") | G9: 356 | H9: https://www.generalist.com/p/nothings-carl-pei-on-building-a-1b-smartphone-company | J9: nothings carl pei on building a 1b smartphone company | L9: "As humans, one of our superpowers is creativity. Both on an individual level, but also on a species level. And by creativity, I mean the ability to solve problems." -Carl Pei Listen or watch now on YouTube , Spotify , or Apple Podcasts Carl Pei is the founder of Nothing, the consumer electronics company known for its distinctive transparent design language across smartphones and audio products. Before launching Nothing in 2020, Carl co-founded OnePlus, where he spent seven years helping build it into a major smartphone brand. But Carl's instincts as a builder showed up much earlier. As a teenager, he taught himself to code by building Pokémon fan sites, all while moving between China, the U.S., and Sweden. That combination of early creation and constant change shaped a founder comfortable with uncertainty-and deeply motivated by questions bigger than products. Carl thinks often about time and mortality, is skeptical of early retirement, and believes creativity is humanity's real advantage. In an industry obsessed with optimization, he's focused on making technology feel meaningful again. In our conversation, we explore: The origins of Nothing's transparent design language and how it helps differentiate the brand in a mature, competitive market Carl's childhood fascination with mortality and how it continues to drive his ambition today Nothing's multiple near-death experiences, from 80% defect rates on first products to fundraising struggles Why India has become a crucial market for Nothing's smartphone business How Nothing approaches community involvement, including letting users invest alongside VCs The company's approach to integrating AI features without overhyping the technology Carl's admiration for Genghis Khan's management style and talent acquisition approach The future of consumer electronics beyond smartphones Thank you to our sponsor, Guru - The AI source of truth for work Explore the episode Timestamps ( 00:00 ) Introduction to Carl Pei and Nothing ( 02:44 ) Nothing's long-term vision ( 06:33 ) How existential thinking shapes Carl's motivation ( 10:12 ) Why Carl's planned sabbatical ended after ten days ( 12:35 ) Carl's international upbringing ( 16:02 ) Entrepreneurial experiments in China ( 19:10 ) Carl's competitive nature and attitude toward school ( 25:30 ) Lessons from seven years at OnePlus ( 28:07 ) Taking a break at age 31 ( 30:50 ) Carl's fundraising strategy ( 33:26 ) Why Carl chose London for Nothing's HQ ( 35:12 ) Lessons from Genghis Khan ( 38:38 ) Nothing's first near-death moment ( 42:56 ) Nothing's product evolution and breakout hits ( 45:24 ) Partnering with Teenage Engineering ( 49:28 ) Design inspirations ( 51:36 ) How Nothing recruits talent ( 53:42 ) Nothing's approach to marketing ( 56:51 ) How India became a key market ( 59:48 ) Why Nothing created CMF ( 1:02:12 ) Why Carl is bullish on India ( 1:03:32 ) How Carl thinks about AI ( 1:07:05 ) Rethinking ads based on community feedback ( 1:09:05 ) How Nothing leverages community ( 1:11:23 ) Why AI hardware is struggling ( 1:13:37 ) Carl's thoughts on the future of consumer electronics ( 1:15:10 ) Philosophies that shape Carl's worldview ( 1:16:45 ) Final meditations Follow Carl Pei LinkedIn: X: Resources and episode mentions Books Apple in China: The Capture of the World's Greatest Company : Conqueror (5 book series): Zen Mind, Beginner's Mind: Informal Talks on Zen Meditation and Practice : People Genghis Khan: Elon Musk on X: Jesper Kouthoofd on LinkedIn: Charlie Smith on LinkedIn: Other resources Nothing: Carl's AMA thread on X: Steve Jobs' 2005 Stanford Commencement Address: Naruto: League of Legends : OnePlus: King: Klarna: Ear (1): Teenage Engineering: Dior: Gucci: Ipren the Intelligent Painkiller: Get to Know Creative Museum Tokyo ‐ Experience the Creativity of Diverse Works and Creators in an Expansive Space Presented by Sony: 2001: A Space Odyssey : HAL 9000: Loewe: 4K Restoration: 1984 Super Bowl APPLE MACINTOSH Ad by Ridley Scott: CMF: Essential apps: Porsche: Humane: Limitless: Rabbit: Friend: Subscribe to the show I'd love it if you'd subscribe and share the show. Your support makes all the difference as we try to bring more curious minds into the conversation. YouTube Spotify Apple Production and marketing by penname.co . For inquiries about sponsoring the podcast, email jordan@penname.co. | N9: https://substackcdn.com/image/fetch/$s_!uKI7!,w_1456,c_limit,f_auto,q_auto:good,fl_progressive:steep/https%3A%2F%2Fsubstack-post-media.s3.amazonaws.com%2Fpublic%2Fimages%2F1200e4c5-5be5-451c-a20e-657f4e576886_475x151.png | S9: 1 | T9: core | U9: 2026-04-15 06:31:36 | V9: active | W9: 0 | Z9: 0 | AA9: 0 | AC9: 0 | AE9: 0 | AF9: 0 | AG9: 0 | AH9: 0
A10: 미확인 | B10: =IFERROR(INDEX('Source Check'!$A:$A, MATCH(C10, 'Source Check'!$B:$B, 0)), "미등록") | C10: 62 | D10: generalist.com | E10: https://www.generalist.com/ | F10: =IFERROR(INDEX('Source Check'!$E:$E, MATCH(C10, 'Source Check'!$B:$B, 0)), "") | G10: 355 | H10: https://www.generalist.com/p/programming-sunlight-ben-nowack | J10: programming sunlight ben nowack | L10: "It's either sunny or it's not sunny, and there's not much you can do about that-but we're trying to change that for the first time ever." -Ben Nowack Listen or watch now on YouTube , Spotify , or Apple Podcasts Most energy conversations start with scarcity. This one starts with abundance. Sunlight powers nearly everything on Earth, directly or indirectly. And yet we have almost no control over when or where we get it. Ben Nowack thinks that's a solvable problem. Ben is the founder and CEO of Reflect Orbital, a company building satellites designed to redirect sunlight from space-not as a thought experiment, but as a product. The company nearly died before it worked. Eight months in, Ben had $300 left and was living in a garage. He made a deliberate decision to go $50,000 into credit card debt to finish critical tests. At one point, he was down to $21 of available credit. A month later, Reflect raised its first round. Today, the company is preparing to launch its first revenue-generating satellites. This is a conversation about building conviction, finding the real market, and what changes when a fundamental resource becomes programmable. In our conversation, we explore: How Reflect's satellites work The surprising pivot from energy to lighting applications that made the business immediately viable Ben's remarkable journey from building RC planes and X-ray machines in high school to founding Reflect Why previous attempts at space mirrors failed and what's changed to make this possible now The near-death moment when Ben went $50,000 into credit card debt to keep his vision alive How Reflect plans to scale from moonlight-level brightness to potentially powering solar farms The company's first satellite launches planned for this year, and their path to a full constellation The wide range of applications, from emergency response to municipal lighting to agriculture Explore the episode Timestamps ( 00:00 ) Introduction to Ben Nowack ( 02:26 ) What Reflect Orbital is building ( 05:07 ) How the satellite constellation works ( 08:00 ) What Reflect is launching this year ( 10:35 ) Finding early markets ( 13:43 ) Ben's childhood and early building experiences ( 22:04 ) What Ben learned working for startups ( 28:03 ) High school projects: X-ray machines, rocket engines, and fusion reactors ( 33:14 ) The eureka moment that led to Reflect ( 35:24 ) Early validation of the idea ( 38:35 ) The Russian space mirror experiments of the 1990s and what's changed ( 42:31 ) Partnering with Tristan Similac as co-founder ( 45:05 ) Baiju Bhatt's involvement ( 47:04 ) Why Reflect isn't pivoting to space-based data centers ( 50:54 ) Common misconceptions about Reflect's technology ( 55:11 ) Why programmable light is valuable ( 1:01:28 ) Initial target markets ( 1:03:42 ) The future markets for Reflect ( 1:07:33 ) Reflect's company culture and operational philosophy ( 1:12:05 ) Surprises and struggles in building Reflect ( 1:14:56 ) Putting the idea to the test Follow Ben Nowack LinkedIn: X: Resources and episode mentions People Vladimir Syromyatnikov: Tristan Semmelhack on LinkedIn: Baiju Bhatt on LinkedIn: Marc Andreessen on X: J.P. Morgan: Ric Burton on LinkedIn: Other resources Reflect Orbital: Zipline: Cassegrain: Advanced Composite Solar Sail System (ACS3): Znamya: Aetherflux: Elon Musk's post on X about building a sentient sun: Denali: Subscribe to the show I'd love it if you'd subscribe and share the show. Your support makes all the difference as we try to bring more curious minds into the conversation. YouTube Spotify Apple Production and marketing by penname.co . For inquiries about sponsoring the podcast, email jordan@penname.co. | N10: https://substackcdn.com/image/fetch/$s_!WSAh!,w_1200,h_600,c_fill,f_jpg,q_auto:good,fl_progressive:steep,g_auto/https%3A%2F%2Fsubstack-post-media.s3.amazonaws.com%2Fpublic%2Fimages%2F6029b0cd-09a3-40cb-a969-8ffe50a1acd8_1456x1048.png | S10: 1 | T10: core | U10: 2026-04-15 06:31:36 | V10: active | W10: 0 | Z10: 0 | AA10: 0 | AC10: 0 | AE10: 0 | AF10: 0 | AG10: 0 | AH10: 0
A11: 미확인 | B11: =IFERROR(INDEX('Source Check'!$A:$A, MATCH(C11, 'Source Check'!$B:$B, 0)), "미등록") | C11: 62 | D11: generalist.com | E11: https://www.generalist.com/ | F11: =IFERROR(INDEX('Source Check'!$E:$E, MATCH(C11, 'Source Check'!$B:$B, 0)), "") | G11: 354 | H11: https://www.generalist.com/p/productivity-stack-2026 | J11: productivity stack 2026 | L11: Friends, Last January, on a whim, I shared a few of the productivity methods I've found effective in maximizing my output while building The Generalist. It was driven by a geekish obsession with tiny optimizations, a love for adopting niche tools, and a real belief that the environment you make for yourself impacts the work you are capable of. To my surprise, it became one of The Generalist's most popular pieces. With January in full swing and the year still stretching in front of us, I decided to sit down and outline the new tools and methods I've found effective over the past year. It turned into quite a collection. You'll find 26 tools I recommend (both digital and analog) and 8 practices I've found invaluable. I've avoided repeating last year's recommendations (though I still use them), so if you're as into these kinds of hacks and optimizations as I am, you may want to read that piece, too. Tools An exhaustive list of the programs, apps, extensions, and physical objects I recommend. Read more | N11: https://substackcdn.com/image/fetch/$s_!JaEN!,f_auto,q_auto:good,fl_progressive:steep/https%3A%2F%2Fsubstack-post-media.s3.amazonaws.com%2Fpublic%2Fimages%2Fcc7ae492-fcba-4478-8503-59caaf59f5b1_2912x1632.png | S11: 1 | T11: core | U11: 2026-04-15 06:31:36 | V11: active | W11: 0 | Z11: 0 | AA11: 0 | AC11: 0 | AE11: 0 | AF11: 0 | AG11: 0 | AH11: 0
A12: 미확인 | B12: =IFERROR(INDEX('Source Check'!$A:$A, MATCH(C12, 'Source Check'!$B:$B, 0)), "미등록") | C12: 62 | D12: generalist.com | E12: https://www.generalist.com/ | F12: =IFERROR(INDEX('Source Check'!$E:$E, MATCH(C12, 'Source Check'!$B:$B, 0)), "") | G12: 353 | H12: https://www.generalist.com/p/the-private-company-bringing-nuclear | J12: the private company bringing nuclear | L12: "We [the U.S.] went from controlling something like 86% of global enrichment capacity to effectively last place." Listen or watch now on YouTube , Spotify , or Apple Podcasts Roughly 20% of the U.S. power grid runs on nuclear energy. A quarter of the fuel behind it is headed toward a hard stop. In this episode, I sit down with Scott Nolan , founder and CEO of General Matter, to unpack why uranium enrichment has quietly become one of the most consequential industrial bottlenecks of the 21st century. While at Founders Fund, Scott spent over a year searching for an American enrichment company to back. When he couldn't find one, he decided to build it himself. Less than a year after emerging from stealth, General Matter secured a historic enrichment site in Paducah, Kentucky, and was awarded a $900 million Department of Energy contract-marking one of the first serious efforts to rebuild domestic enrichment capacity ahead of the 2028 ban on Russian supply. In this episode, we discuss: Why enrichment is the missing link in America's nuclear supply chain How the U.S. went from controlling 86% of global enrichment capacity to effectively none at commercial scale The science behind uranium enrichment and why it matters for next-generation reactors Why Scott applied the SpaceX playbook to nuclear after more than a decade in venture capital How General Matter is revitalizing the historic Paducah, Kentucky enrichment site The significance of General Matter's $900 million Department of Energy contract The bipartisan political support for expanding nuclear energy Why Scott believes nuclear energy could grow 3-4x by 2050 The parallels between America's space and nuclear industries Thank you to our sponsor, Persona : Trusted identity verification for any use case. Explore the episode Timestamps ( 00:00 ) Introduction to Scott Nolan ( 02:24 ) General Matter's mission to rebuild U.S. enrichment ( 05:08 ) How the U.S. lost its edge ( 06:24 ) The nuclear fuel cycle explained-and where enrichment fits ( 08:31 ) Scott's background: From SpaceX and Founders Fund to General Matter ( 13:56 ) Lessons from SpaceX ( 17:50 ) How Scott's focus evolved over 13 years at Founders Fund ( 21:00 ) How Scott landed on nuclear enrichment ( 25:58 ) Why nuclear energy was off the radar-until recently ( 30:10 ) Finding the right partner: Scott and Lee's collaboration ( 32:04 ) What downblending means and why it matters ( 33:30 ) How U.S. uranium enrichment quietly came to an end ( 38:34 ) The Russian uranium ban and the 2028 supply cliff ( 40:38 ) How General Matter plans to compete ( 43:09 ) Building a world-class team ( 46:03 ) The market for enriched uranium ( 49:30 ) Future bottlenecks ( 50:56 ) What the U.S. needs to actually scale nuclear energy ( 51:32 ) Uranium supply constraints ( 54:16 ) LEU vs. HALEU: the fuels powering old and new reactors ( 57:49 ) Why 20% enrichment is a critical threshold ( 59:30 ) Why General Matter chose Paducah, Kentucky ( 01:04:35 ) Legislation and executive orders easing nuclear friction ( 01:07:06 ) The $900 million Department of Energy award ( 01:11:08 ) Why mission matters most ( 01:14:12 ) Final meditations Follow Scott Nolan X: Resources and episode mentions Books Zero to One: Notes on Startups, or How to Build the Future : People Peter Thiel on X: Lee Robinson on LinkedIn; Other resources No Rivals: The Prophet (Part I): General Matter: Founders Fund: SpaceX: How Anduril Is Reimagining the Defense Industry: Faster Tech, Ethical AI, and a New Kind of Deterrence (Trae Stephens, Co-Founder & Executive Chairman at Anduril): The Boring Company: Neuralink: Nubank: Radiant: Megatons to Megawatts Program: S.1111 - ADVANCE Act of 2023: Subscribe to the show I'd love it if you'd subscribe and share the show. Your support makes all the difference as we try to bring more curious minds into the conversation. YouTube Spotify Apple Production and marketing by penname.co . For inquiries about sponsoring the podcast, email jordan@penname.co. | N12: https://substackcdn.com/image/fetch/$s_!lmo-!,w_1456,c_limit,f_auto,q_auto:good,fl_progressive:steep/https%3A%2F%2Fsubstack-post-media.s3.amazonaws.com%2Fpublic%2Fimages%2F6902c32a-356e-4652-bb15-25b769f0fa80_451x127.png | S12: 1 | T12: core | U12: 2026-04-15 06:31:36 | V12: active | W12: 0 | Z12: 0 | AA12: 0 | AC12: 0 | AE12: 0 | AF12: 0 | AG12: 0 | AH12: 0
A13: 미확인 | B13: =IFERROR(INDEX('Source Check'!$A:$A, MATCH(C13, 'Source Check'!$B:$B, 0)), "미등록") | C13: 62 | D13: generalist.com | E13: https://www.generalist.com/ | F13: =IFERROR(INDEX('Source Check'!$E:$E, MATCH(C13, 'Source Check'!$B:$B, 0)), "") | G13: 352 | H13: https://www.generalist.com/p/lessons-of-a-first-time-fund-manager | J13: lessons of a first time fund manager | L13: Friends, Four years ago, I set out to raise my first venture fund. The result was Generalist Capital, a $15 million vehicle to invest in a small collection of (hopefully) legendary companies. The beginning of this year marks something of a turning point. After closing on a few investments, Generalist Capital officially moved from the deployment phase to management and harvesting. That makes it a fitting moment to share the lessons learned along the way. Though venture capital is awash in content, in my view, there's too little introspective writing on the mental game of fund management. Below, you'll find my attempt to distill the most important lessons I've learned so far. To that end, these are best seen as the lessons of a first-time fund manager, relating primarily to the challenges of starting a fund and establishing an initial viable strategy. Naturally, the gravity of these lessons will depend on information I cannot give you: my long-term performance as an investor. It will likely take another six to ten years to discover how promising a portfolio I have built with Generalist Capital, and even longer to know definitively if I am any good. As of our last update to LPs, Generalist Capital was performing in the top 10-15% in its vintage, but the data suggests that it takes about six years for a fund to settle into its terminal quartile. There's still a long way left to run and too much uncertainty to read much into this. I am afraid that this is the best I can offer you. Let this serve as a reminder, then, if any were needed, that you should take my lessons with a grain of salt. I have achieved little, and every investor must learn to play their own game. Though I hope they spark new ideas for you, these are just the observations of one manager at the beginning of what I hope proves to be a long career. If this is your first time managing a fund, be extremely skeptical of your early investment urges. You're probably overly keen to validate your existence to your LPs. The best companies can go under the radar for a long time. When other VCs asked which of my investments I was most bullish about, I told them freely. It still took several years for a Tier 1 firm to lead a round into the company. You do not have to wait for a round. If you have enough to offer a company, they'll find a way to bring you aboard ahead of a formal raise. When you see a startup you love, try to make something happen. Don't assume you know your level. New managers often think they can't get access to rounds led by Tier 1 VCs. With the right pitch, you may be closer than you think. It's very rare you see everything you want in a startup: founder, market, traction, and so on. When you do, write a much bigger check than you ordinarily would. The first investor has a unique relationship with a founder. You can build good relationships no matter when you invest, but the first check in earns a special level of trust. Contrary to what you might expect, the best companies are not easier to access as round sizes grow. Competition escalates as they succeed, often through late growth. The best investors often need little more than a sentence to explain why they've invested in a company. The longer and more convoluted your investment rationale is, the more skeptical you should be of it. Find your pace. A generation of managers has been conditioned to deploy vintages in 18-24 months. There is nothing wrong with taking twice as long, or more. Just because a deal is hot does not mean it is good. Don't let other people's urgency influence your desire. Remind yourself: the best venture firms in the world make a majority of bad investments. Don't index on a buzzy name. Conversely, if some of the best investors in the world are backing a startup you don't consider promising, look again, extremely closely. There's a good chance you're missing something important. Remember, the best investors in the world ≠ the best known investors. Calibrate accordingly. Don't assume the best opportunities will land in your lap. Outbound sourcing is a necessity. Progress is never linear. A company that you had more or less written off can suddenly catch light, and one that was on a breakout trajectory can easily stall or stumble. Don't push your anxiety onto your founders. It's not your job to let them know of every new company that pops up in their space. If you're asked for advice, give it honestly, but recognize that you have 0.01% of the context a founder has. Fight for every dollar. Getting an extra $10K into a breakout company can make a huge difference for a small fund. Founders respond to conviction. Earnestly explaining to an entrepreneur why you're excited about their business and showing a desire to move quickly can overcome any number of natural disadvantages. Be skeptical of a pitch that looks too rational. Great companies often have something paradoxical about them. If something doesn't quite make sense, that's a good indication you should lean in, not out. Be careful you don't get stuck correcting your last mistake. If you invested too little in a startup that has just started to break out, don't triple the size of your next check to compensate. Consider each opportunity anew. If you're not positioned to catch a wave, don't chase it. You could burn an entire vintage on second-and third-rate AI companies. Read more | N13: https://substackcdn.com/image/fetch/$s_!MTsx!,f_auto,q_auto:good,fl_progressive:steep/https%3A%2F%2Fsubstack-post-media.s3.amazonaws.com%2Fpublic%2Fimages%2F2994d4f1-bacf-44ba-987b-61056318dd88_2688x1792.jpeg | S13: 1 | T13: core | U13: 2026-04-15 06:31:36 | V13: active | W13: 0 | Z13: 0 | AA13: 0 | AC13: 0 | AE13: 0 | AF13: 0 | AG13: 0 | AH13: 0
A14: 미확인 | B14: =IFERROR(INDEX('Source Check'!$A:$A, MATCH(C14, 'Source Check'!$B:$B, 0)), "미등록") | C14: 62 | D14: generalist.com | E14: https://www.generalist.com/ | F14: =IFERROR(INDEX('Source Check'!$E:$E, MATCH(C14, 'Source Check'!$B:$B, 0)), "") | G14: 351 | H14: https://www.generalist.com/p/how-bolt-survived-an-85-revenue-crash | J14: how bolt survived an 85 revenue crash | L14: "We don't care that we're from a small country. We've always had the view that if we work harder and [make] smarter decisions, we can beat [any] company in the world, regardless of how big they are." Listen or watch now on YouTube , Spotify , or Apple Podcasts In 2013, on an Estonian island of just 10,000 residents, a teenager borrowed €5,000 from his parents and decided to take on Uber. Twelve years later, Markus Villig leads Bolt , a company operating in 50+ countries, generating nearly €3 billion in revenue, and standing as one of the only European tech companies competing at true global scale. Rather than going head-to-head with incumbents in their strongest markets, Bolt expanded through underserved cities, emerging economies, and overlooked segments of urban transport. When COVID erased 85% of its revenue in weeks, the company didn't retreat; it staged a kind of corporate "eucatastrophe," pivoting into food delivery across nearly 20 countries in what became a company-wide sprint. That same bias toward action now shapes Markus's broader agenda: investing in defense tech for Estonia and Ukraine, pushing for capital markets reform, and advancing a contrarian thesis on autonomous vehicles. In this conversation, we discuss: How growing up in Soviet-occupied Estonia shaped Markus's ambition and moral clarity How Bolt's European ethos and long-term focus on driver retention became a structural advantage The marketplace models and capital discipline that allowed Bolt to outmaneuver better-funded rivals Why Bolt found breakout success in African markets after failing in 12 Western countries The 85% revenue collapse during COVID and the rapid food delivery pivot that reshaped the company Bolt's partnerships with Stellantis and Pony.ai and its long-term bet on autonomous vehicles Why Ukrainian and Eastern European startups are often outperforming their Western peers Markus's blueprint for closing Europe's tech deficit and building globally competitive companies Thank you to the partners who make this possible Granola : The app that might actually make you love meetings Brex : The intelligent finance platform. Persona : Trusted identity verification for any use case. Explore the episode Timestamps ( 00:00 ) Intro ( 03:32 ) How The Lord of the Rings shaped Markus's worldview ( 05:52 ) Bolt's underdog story and its existential turning point ( 10:22 ) Estonia's startup DNA and its imprint on Bolt ( 13:38 ) Europe's ambition problem ( 17:23 ) Europe's defense tech gap ( 23:09 ) The need for capital market reform in Europe ( 25:13 ) Bolt's origin story ( 36:35 ) Frugality as strategy ( 38:24 ) What running Bolt actually demands ( 41:27 ) The hidden costs of being too lean ( 42:50 ) Bolt's shift to experimentation ( 44:10 ) Bolt's micromobility strategy ( 45:50 ) How Bolt found the right markets ( 50:44 ) The Serbian mob story ( 54:00 ) Markus on venture capital and lessons from Klarna's board ( 55:40 ) Why Bolt never sold ( 57:08 ) Bolt's autonomous vehicle (AV) strategy and key partnerships ( 1:05:50 ) The concept of culture-market fit ( 1:07:48 ) How Bolt operates: writing, hiring, reading, and more ( 1:13:15 ) Markus's personal strengths ( 1:14:15 ) What people get wrong about business ( 1:16:27 ) Final meditations Follow Markus Villig X: LinkedIn: Resources and episode mentions Books The Lord of the Rings : High Output Management : The Precipice: Existential Risk and the Future of Humanity : People Martin Villig on LinkedIn: Oliver Leisalu on LinkedIn: Jeff Bezos on X: Jensen Huang on LinkedIn: Andy Grove: Other resources Bolt: Palmer Luckey's post on X about Lord of the Rings : Skype: Markus's post on X about Europe lagging in tech: Revolut: Wise: Klarna: Sequoia: Daimler: Stellantis: Pony AI: Waymo: TSMC: Existential Risk and the Future of Humanity: Lessons from AI, Pandemics, and Nuclear Threats (Toby Ord, Author of "The Precipice"): Subscribe to the show I'd love it if you'd subscribe and share the show. Your support makes all the difference as we try to bring more curious minds into the conversation. YouTube Spotify Apple Production and marketing by penname.co . For inquiries about sponsoring the podcast, email jordan@penname.co. | N14: https://substackcdn.com/image/fetch/$s_!pAew!,w_1456,c_limit,f_auto,q_auto:good,fl_progressive:steep/https%3A%2F%2Fsubstack-post-media.s3.amazonaws.com%2Fpublic%2Fimages%2F81215a3c-be4c-42ec-bfe9-8d4c14f50935_1600x128.png | S14: 1 | T14: core | U14: 2026-04-15 06:31:36 | V14: active | W14: 0 | Z14: 0 | AA14: 0 | AC14: 0 | AE14: 0 | AF14: 0 | AG14: 0 | AH14: 0
A15: 미확인 | B15: =IFERROR(INDEX('Source Check'!$A:$A, MATCH(C15, 'Source Check'!$B:$B, 0)), "미등록") | C15: 62 | D15: generalist.com | E15: https://www.generalist.com/ | F15: =IFERROR(INDEX('Source Check'!$E:$E, MATCH(C15, 'Source Check'!$B:$B, 0)), "") | G15: 350 | H15: https://www.generalist.com/p/everyone-is-betting-on-bigger-llms | J15: everyone is betting on bigger llms | L15: "AGI should be just like natural intelligence. Something which plans, something which is able to predict, produce new knowledge, be cheap and efficient, and be adaptive to the environment. It should reason, it should not mimic." - Eve Bodnia, Founder & CEO, Logical Intelligence Listen or watch now on YouTube , Spotify , or Apple Podcasts Eve Bodnia is the co-founder and CEO of Logical Intelligence, which is developing energy-based reasoning models (EBMs) as an alternative to large language models. She argues that LLMs, which operate by recognizing and recombining patterns within language space, are structurally incapable of genuine reasoning. Eve's alternative: Kona-an EBM that reasons in abstract latent space, learns rules about the world rather than surface patterns, and can interface with language models as one output channel among many. Eve traces the core ideas behind her architecture to decades of work in symmetry groups, condensed matter physics, and brain science-fields that share, as she explains, the same underlying mathematics. In a public demo, Kona solved a complex reasoning task for roughly $4 in compute, compared to an estimated $15,000 using frontier LLMs. With Yann LeCun serving as founding chair of its technical board, Logical Intelligence sits at the center of a small but growing effort to rethink AI beyond language-based models. In our conversation, we explore: Why Eve believes LLMs can't truly extrapolate knowledge, even at larger scale What energy-based reasoning models are-and where the "energy" concept comes from The $4 vs. $15,000 benchmark, and what it tells us about the cost of guessing vs. knowing How Logical Intelligence showed spontaneous knowledge transfer at just 16M parameters Why systems like chip design, surgical robotics, and power grids need more than probabilistic AI What formally verified code generation means for the future of programming Why the math behind particle physics also explains how the brain filters signal from noise How meeting Grigori Perelman as a teenager shaped Eve's views on ego and ownership in science Why Eve believes humans must remain the constraint-setters in advanced AI How meditation, piano, and Eastern philosophy support her creative process Thank you to the partners who make this possible Granola : The app that might actually make you love meetings. Persona : Trusted identity verification for any use case. Explore the episode Timestamps ( 00:00 ) Introduction ( 03:03 ) Eve's encounter with Grigori Perelman ( 05:38 ) Why bizarre people are Eve's favorite people ( 06:56 ) Her early obsession with math and physics ( 09:02 ) The manifold hypothesis and language ( 11:54 ) The Kekulé Problem ( 14:05 ) Eve's upbringing and her CERN research in high school ( 17:40 ) Eve's academic path ( 20:36 ) Symmetry in nature ( 22:58 ) Spirituality and creativity ( 27:00 ) Theory vs. experiment ( 29:03 ) Uncovering a critical gap in AI models ( 33:45 ) What Logical Intelligence is building ( 35:50 ) Logical Intelligence's use cases ( 42:08 ) Energy-based models explained ( 45:06 ) LLMs vs. EBMs ( 48:01 ) AGI defined ( 51:22 ) Kona's knowledge extrapolation ( 53:20 ) The team behind Logical Intelligence ( 58:09 ) Early investors in Logical Intelligence ( 58:50 ) Feynman's influence on Eve's work ( 1:01:15 ) How Eve sustains her creativity ( 1:03:42 ) Final meditations Follow Eve Bodnia LinkedIn: X: Website: Resources and episode mentions Books The Creative Act: A Way of Being : Impro: Improvisation and the Theatre : Perfectly Reasonable Deviations from the Beaten Track : Letting Go: The Pathway of Surrender : People Grigori Perelman: Cormac McCarthy: Rick Rubin on X: David Krakauer's website: Yann LeCun on LinkedIn: Michael Freedman: Vladislav Isenbaev on LinkedIn: Other resources Fields Medal: Manifold hypothesis: The Kekulé Problem: CERN: Can Humans Stay Smart in the Age of AI? (David Krakauer, President of the Santa Fe Institute): Kona: ICPC global: Eve's post on X about Feynman's writings: Mahayana Buddhism: Subscribe to the show I'd love it if you'd subscribe and share the show. Your support makes all the difference as we try to bring more curious minds into the conversation. YouTube Spotify Apple Production and marketing by penname.co . For inquiries about sponsoring the podcast, email jordan@penname.co. | N15: https://substackcdn.com/image/fetch/$s_!unuq!,w_1456,c_limit,f_auto,q_auto:good,fl_progressive:steep/https%3A%2F%2Fsubstack-post-media.s3.amazonaws.com%2Fpublic%2Fimages%2Fc92c1444-b5dc-415e-8ff1-d3218a02f26d_936x128.png | S15: 1 | T15: core | U15: 2026-04-15 06:31:36 | V15: active | W15: 0 | Z15: 0 | AA15: 0 | AC15: 0 | AE15: 0 | AF15: 0 | AG15: 0 | AH15: 0
A16: 미확인 | B16: =IFERROR(INDEX('Source Check'!$A:$A, MATCH(C16, 'Source Check'!$B:$B, 0)), "미등록") | C16: 62 | D16: generalist.com | E16: https://www.generalist.com/ | F16: =IFERROR(INDEX('Source Check'!$E:$E, MATCH(C16, 'Source Check'!$B:$B, 0)), "") | G16: 349 | H16: https://www.generalist.com/p/infinite-games | J16: infinite games | L16: "To be prepared against surprise is to be trained. To be prepared for surprise is to be educated." - James Carse, Finite and Infinite Games Friends, Evolutionary biology has the concept of "allopatric speciation," the process that occurs when a species develops separately from those on the mainland. Saved from some evolutionary pressures and exposed to oth… Read more | N16: https://substackcdn.com/image/fetch/$s_!grav!,f_auto,q_auto:good,fl_progressive:steep/https%3A%2F%2Fsubstack-post-media.s3.amazonaws.com%2Fpublic%2Fimages%2F804e34cc-6fb2-40ba-9a9b-e95131e4acc6_2912x1632.png | S16: 1 | T16: core | U16: 2026-04-15 06:31:36 | V16: active | W16: 0 | Z16: 0 | AA16: 0 | AC16: 0 | AE16: 0 | AF16: 0 | AG16: 0 | AH16: 0
A17: 미확인 | B17: =IFERROR(INDEX('Source Check'!$A:$A, MATCH(C17, 'Source Check'!$B:$B, 0)), "미등록") | C17: 62 | D17: generalist.com | E17: https://www.generalist.com/ | F17: =IFERROR(INDEX('Source Check'!$E:$E, MATCH(C17, 'Source Check'!$B:$B, 0)), "") | G17: 348 | H17: https://www.generalist.com/p/americas-electric-power-grid-is-broken | J17: americas electric power grid is broken | L17: "You must get comfortable with the notion that a lot of really smart people you respect are going to explain to you in excruciating detail why this is not going to work...You have to be able to see through that and have a clear vision in your mind for why it is going to work." - Zach Dell, co-founder and CEO of Base Listen or watch now on YouTube , Spotify , or Apple Podcasts For decades, America's electrical system has rewarded utilities for building more infrastructure, not for lowering costs. The result is a grid that expanded but rarely improved. Zach Dell , co-founder and CEO of Base, is building a different kind of power company. In under three years, Base has grown into a vertically integrated business valued in the billions. It combines home batteries and software to store electricity when it is cheap and deliver it when demand spikes. Dell's interest in energy began long before Base. In college, he tried to lease a Hawaiian lava field for a solar project. He also experimented with anaerobic digestion systems in India and worked at Blackstone and Thrive Capital, where he met his co-founder. His bet is simple but ambitious: the next phase of the grid will come from increasing utilization rather than constantly building new infrastructure. In our conversation, we explore: How a failed college solar project and early energy experiments in India pulled Zach into the power industry The lessons he absorbed from his parents, including truth-seeking, reinvention, and competitive endurance How the U.S. grid's regulatory structure discourages innovation and why Texas's deregulated market creates space for new power companies Why batteries are best understood as a time-shifting technology that increases grid utilization and reduces total system costs, not simply as energy generators Base's "make, move, store, sell" framework for thinking about the full power stack How Base aims to become the first beloved energy company How Zach identified Justin as a world-class operator and built the trust needed to go all-in together on a non-obvious idea How aggressive AI adoption is compressing cycle times and why slow adopters risk falling behind Thank you to the partners who make this possible Granola : The app that might actually make you love meetings Brex : The intelligent finance platform. Explore the episode Timestamps ( 00:00 ) Introduction to Zach Dell and Base ( 03:06 ) The Hawaiian lava field solar project and early energy curiosity ( 07:58 ) Investing vs. operating ( 09:31 ) Lessons from Phil Jackson on aligning talented teams ( 15:24 ) Lessons from his parents ( 19:19 ) The loneliness of solo founding and the value of co-founders ( 21:49 ) Justin's strengths as a co-founder and how their partnership formed ( 30:55 ) Why Base became the obvious focus ( 32:21 ) The original vision and the three reversals ( 35:49 ) The American power grid and what makes Texas different ( 40:39 ) Why batteries matter and what Base is building ( 41:44 ) How Base works in two market types ( 45:59 ) Base's core product ( 47:43 ) The software behind Base's battery network ( 49:14 ) Base's partnerships with battery cell makers ( 50:43 ) The Gen 2 hardware mistake and the lesson in risk management ( 52:00 ) Dino's strengths as Head of Hardware ( 53:20 ) Base's positioning as grid infrastructure ( 55:39 ) Building a beloved energy brand ( 58:45 ) How hiring at Base has evolved ( 1:01:54 ) AI workflows at Base ( 1:03:44 ) Zach's dedicated deep work time ( 1:06:29 ) Final meditations Follow Zach Dell LinkedIn: X: Resources and episode mentions Books Factfulness: Ten Reasons We're Wrong About the World--and Why Things Are Better Than You Think : Robert Greene's books on Amazon: People Bill Walton: John Wooden's website: Phil Jackson on X: Michael Jordan: Scottie Pippen: Kobe Bryant: Shaquille O'Neal: Dennis Rodman: Justin Lopas on LinkedIn: Jared Greene on LinkedIn: Cole Jones on LinkedIn: Dana Paz on LinkedIn: Michael Scaria on LinkedIn: Dino Sasaridis on LinkedIn: Michael Dell: Susan Dell: Packy McCormick's blog: Other resources Base: Blackstone: Childhoods of exceptional people: Feynman Technique: The Ultimate Guide to Learning Anything Faster: Anduril: Base Power Company: Base Power Company: Chapter 2: Enron: Austin Energy: CPS: GVEC: Bandera Electric: Farmers Electric: NRG: Vista Energy: Costco: Southwest Airlines: HEB: Subscribe to the show I'd love it if you'd subscribe and share the show. Your support makes all the difference as we try to bring more curious minds into the conversation. YouTube Spotify Apple Production and marketing by penname.co . For inquiries about sponsoring the podcast, email jordan@penname.co. | N17: https://substackcdn.com/image/fetch/$s_!YsmO!,w_1456,c_limit,f_auto,q_auto:good,fl_progressive:steep/https%3A%2F%2Fsubstack-post-media.s3.amazonaws.com%2Fpublic%2Fimages%2F9ba9cafe-f944-4dac-bd9c-8452debd0241_1600x128.png | S17: 1 | T17: core | U17: 2026-04-15 06:31:36 | V17: active | W17: 0 | Z17: 0 | AA17: 0 | AC17: 0 | AE17: 0 | AF17: 0 | AG17: 0 | AH17: 0
A18: 미확인 | B18: =IFERROR(INDEX('Source Check'!$A:$A, MATCH(C18, 'Source Check'!$B:$B, 0)), "미등록") | C18: 62 | D18: generalist.com | E18: https://www.generalist.com/ | F18: =IFERROR(INDEX('Source Check'!$E:$E, MATCH(C18, 'Source Check'!$B:$B, 0)), "") | G18: 347 | H18: https://www.generalist.com/p/karol-hausman-physical-intelligence | J18: karol hausman physical intelligence | L18: Listen or watch now on YouTube , Spotify , or Apple Podcasts Karol Hausman is the co-founder and CEO of Physical Intelligence , a robotics company building a general-purpose "AI brain for the physical world." The company has raised more than $1 billion in funding to develop foundation models that allow robots to operate across many machines, environments, and tasks rather than being programmed for a single purpose. The core thesis: the same scaling dynamics that transformed language models may also unlock robotic intelligence. But only if you resist every commercial pressure pushing you toward specialization. The central challenge isn't mechanical design. It's intelligence: how robots learn, generalize, and interact with a physical world that is far harder to simulate than it is to describe. Before launching Physical Intelligence, Karol worked at Google Brain and Stanford University, studying robot learning alongside researchers Sergey Levine and Chelsea Finn , who later became his co-founders. In our conversation, we explore: How growing up in a small town in Poland and watching Star Wars sparked Karol's fascination with robots The moment a lecture from Sergey Levine convinced him to abandon his PhD research direction and pivot fully to deep learning Why robotics has historically lagged behind breakthroughs in language models The case for building a general "AI brain" for the physical world rather than a single specialized robot The role of real-world data in training robots, the limits of simulation, and how deployment could create a powerful data flywheel The return of reinforcement learning and the parallels between human learning and robot training The unique challenges of physical intelligence and why robots must operate with far higher reliability than language models Thank you to the partners who make this possible Brex : The intelligent finance platform. Granola : The app that might actually make you love meetings. Explore the episode Timestamps ( 00:00 ) Intro ( 04:05 ) Karol's early fascination with robots ( 07:38 ) How Karol relates to Fei-Fei Li's biography ( 08:52 ) What inspired Karol to build better robots ( 11:19 ) Philosophical influences ( 15:33 ) Parallels between The Inner Game of Tennis and robotics ( 18:21 ) Karol's entry point to robotics and PhD program ( 25:49 ) Combining robotics with LLMs: The Taylor Swift demo ( 30:48 ) The 1970s SHRDLU AI experiment ( 32:33 ) Founding Physical Intelligence ( 35:13 ) How Lachy Groom got involved ( 39:40 ) How research shapes what Physical Intelligence builds ( 45:22 ) The importance of real-world data ( 49:07 ) The return of reinforcement learning in robotics ( 53:31 ) The risk of commercializing too early ( 55:47 ) Finding the right partners for the business ( 57:13 ) Open research questions ( 1:00:00 ) NVIDIA's simulation engines ( 1:01:57 ) The surprising speed of progress ( 1:04:16 ) Reliability in robotics ( 1:07:31 ) Compensating for missing senses ( 1:12:28 ) Book recommendation Follow Karol Hausman LinkedIn: X: Resources and episode mentions Books Worlds I See : The Inner Game of Tennis: The Classic Guide to the Mental Side of Peak : On the Move : Why Greatness Cannot Be Planned : The Myth of the Objective : People Fei-Fei Li on X: Plato: Baruch Spinoza: Sergey Levine on X: Brian Ichter on LinkedIn: Lachy Groom on LinkedIn: Chelsea Finn on LinkedIn: Lee Sedol: Other resources Physical Intelligence: Karol's post on X about Worlds I See : Ontology: The History of AI in 7 Experiments: NVIDIA: AlphaGo: Proprioception: Subscribe to the show I'd love it if you'd subscribe and share the show. Your support makes all the difference as we try to bring more curious minds into the conversation. YouTube Spotify Apple Production and marketing by penname.co . For inquiries about sponsoring the podcast, email jordan@penname.co. | N18: https://substackcdn.com/image/fetch/$s_!VFuL!,w_1456,c_limit,f_auto,q_auto:good,fl_progressive:steep/https%3A%2F%2Fsubstack-post-media.s3.amazonaws.com%2Fpublic%2Fimages%2F7e7d0e56-c3f4-4b0f-b30f-24d2d76b7d72_1600x128.png | S18: 1 | T18: core | U18: 2026-04-15 06:31:36 | V18: active | W18: 0 | Z18: 0 | AA18: 0 | AC18: 0 | AE18: 0 | AF18: 0 | AG18: 0 | AH18: 0
A19: 미확인 | B19: =IFERROR(INDEX('Source Check'!$A:$A, MATCH(C19, 'Source Check'!$B:$B, 0)), "미등록") | C19: 62 | D19: generalist.com | E19: https://www.generalist.com/ | F19: =IFERROR(INDEX('Source Check'!$E:$E, MATCH(C19, 'Source Check'!$B:$B, 0)), "") | G19: 346 | H19: https://www.generalist.com/p/why-one-superintelligence-is-more | J19: why one superintelligence is more | L19: "I would argue the biggest risk is actually locking in a very narrow monoculture for superintelligence. One superintelligence is much less safe than infinite superintelligence." - Vincent Weisser Listen or watch now on YouTube , Spotify , or Apple Podcasts Much of the fear around AI centers on misalignment - the idea that powerful systems might act against human interests. Vincent Weisser worries about something different: what happens if advanced AI systems are perfectly aligned with the interests of a small group of institutions? That concern led him to co-found Prime Intellect, a startup building open infrastructure for training and deploying advanced AI models. Before Prime Intellect, Weisser helped organize Vitalik Buterin's Zuzalu experiment and worked in decentralized science, where he helped unlock roughly $40 million in funding for unconventional research. Today, he's applying that same open ethos to AI, working to ensure the tools that shape superintelligence remain broadly accessible rather than concentrated in the hands of a few. In our conversation, we explore: Why Vincent believes multiple superintelligences are safer than one The intellectual influences that shaped Vincent's thinking about intelligence and progress, including David Deutsch and Nick Bostrom Prime Intellect's evolution from distributed compute infrastructure to frontier model training and reinforcement learning tools Why Vincent believes open and decentralized science could accelerate discovery The Zuzalu experiment and what it suggests about the future of scientific communities The role of aesthetics and craft in building technology Why Europe might have a cultural advantage in a post-superintelligence world Vincent's predictions for the next five years of AI Thank you to the partners who make this possible Granola : The app that might actually make you love meetings. Brex : The intelligent finance platform. Rippling : Stop wasting time on admin tasks, build your startup faster. Explore the episode Timestamps ( 00:00 ) Introduction to Vincent Weisser ( 03:28 ) The book behind Prime Intellect's name ( 07:35 ) The case for suffering ( 09:35 ) An overview of Prime Intellect ( 13:03 ) Why open source models matter ( 21:18 ) Vincent's intellectual influences ( 25:17 ) Early years in the startup scene ( 31:48 ) Funding science outside traditional institutions ( 41:22 ) The past 6 months of AI progress ( 43:45 ) Deciding to build Prime Intellect ( 46:55 ) Why GPUs were the right starting point ( 51:39 ) Training models on Prime Intellect ( 59:48 ) Why beauty matters ( 1:03:48 ) The Zuzalu experiment ( 1:06:27 ) Prime Intellect's AGI Easter egg ( 1:11:13 ) Predictions for the next five years ( 1:15:09 ) Final meditations Follow Vincent Weisser LinkedIn: X: Goodreads: Website: Resources and episode mentions Books The Metamorphosis of Prime Intellect : The Beginning of Infinity: Explanations That Transform the World : Superintelligence: Paths, Dangers, Strategies : Steve Jobs : The Singularity Is Near: When Humans Transcend Biology : Physics of the Future: How Science Will Shape Human Destiny and Our Daily Lives by the Year 2100 : A Pattern Language: Towns, Buildings, Construction (Center for Environmental Structure Series) : People George Hotz on X: Andrej Karpathy on X: Benjamin Bratton's website: David Deutsch's website: Albert Einstein: Vitalik Buterin's website: Celine Halioua's website: Other resources Prime Intellect: Anthropic: OpenAI: DeepSeek: Google DeepMind: Are We Alone In The Universe? Sara Seager on Exoplanets, Venus, and the Hunt for Alien Life (Astrophysicist and Planetary Scientist at MIT): Y Combinator: Loyal: Cursor: Zuzalu: Why I Built Zuzalu: Dyson sphere: Subscribe to the show I'd love it if you'd subscribe and share the show. Your support makes all the difference as we try to bring more curious minds into the conversation. YouTube Spotify Apple Production and marketing by penname.co . For inquiries about sponsoring the podcast, email jordan@penname.co. | N19: https://substackcdn.com/image/fetch/$s_!De62!,w_1456,c_limit,f_auto,q_auto:good,fl_progressive:steep/https%3A%2F%2Fsubstack-post-media.s3.amazonaws.com%2Fpublic%2Fimages%2Fe021990f-d0f8-43c8-b746-6873cf58fbce_1600x128.png | S19: 1 | T19: core | U19: 2026-04-15 06:31:36 | V19: active | W19: 0 | Z19: 0 | AA19: 0 | AC19: 0 | AE19: 0 | AF19: 0 | AG19: 0 | AH19: 0
... A22: 미확인 | B22: =IFERROR(INDEX('Source Check'!$A:$A, MATCH(C22, 'Source Check'!$B:$B, 0)), "미등록") | C22: 62 | D22: generalist.com | E22: https://www.generalist.com/ | F22: =IFERROR(INDEX('Source Check'!$E:$E, MATCH(C22, 'Source Check'!$B:$B, 0)), "") | G22: 343 | H22: https://www.generalist.com/p/confidential | J22: confidential | L22: Friends, You didn't mind speaking with Hanns Scharff. No, it was better than that - you liked it. He spoke English well, for one thing, the product of years spent in South Africa and a wife from London. But that didn't fully explain it either. He spoke softly (unlike the others), was good for a joke or a story, and when he directed his dark, thoughtful eyes in your direction, you didn't feel fearful, but at ease. You could almost forget that he was the Luftwaffe's most effective interrogator. And you, his prisoner. While the Nazi Party's other torturers and wheedlers relied on threats and violence, Scharff found success with a more genteel approach, taking downed pilots on long walks in the Taunus hills northwest of Frankfurt, during which he seemed to avoid discussing military matters. Only later, in some cases much later, would prisoners realize what had happened. One American pilot recalled such a stroll. Only after he and Scharff had wandered and chatted for a while did the German mention, almost in passing, that a chemical shortage seemed to have impacted American munitions: their tracer bullets now trailed white smoke rather than their usual red. No, no, the American told him. That wasn't caused by a chemical shortage; it was a matter of design. American tracer bullets shifted from red to white when a pilot was running low on ammunition. It was a kind of warning system. There it was. By purposefully saying the wrong thing, Scharff prompted the pilot to correct him, all without asking a question. A pocket had been picked without the wallet's owner even registering a rustle. The pilot would not realize what had happened until it was much too late. This technique, and others like it, are the topic of Confidential by John Nolan, a 1999 book that is as fascinating as it is difficult to obtain. Though prized by intelligence officials and professional "elicitors," Confidential is no longer in print and only available to buy second-hand. To grab my copy, I spent a few hundred dollars on eBay and waited weeks for it to arrive. All of which only adds to its strange allure, as if someone decided Nolan's work was too useful to simply leave lying around. Confidential is a wildly entertaining and impressively insightful book. In studying it closely these last few months, I've also come to believe it's an important one. Though Nolan is ostensibly writing for the professional intelligence gatherer, his conversational techniques are useful to anyone, in any context. They are liable to make you more engaging and persuasive, as well as a better conversationalist. It is also worth knowing when someone else is using them. Why did that salesperson seem to purposefully misspeak? Was I imagining it, or did that headhunter seem to disbelieve everything I said? What is it about this person that makes me want to open up so much? For founders working in sectors of national interest, Confidential will help you protect what you know. If you are building almost anything of note, there is a good chance that someone out there - whether in a bland concrete building, a glassy office tower, or a grassy tech campus - would love to understand it better than you'd like them to. This is the second piece in an occasional series about books that change how you see everyday interactions. The first, on Keith Johnstone's Impro , explored the invisible power dynamics in every conversation. Confidential picks up the other side of that coin: how information actually moves between people, and what a former spy figured out about making it move faster. If you'd like to read more work like this - pieces that dig into overlooked ideas and the people behind them - a premium membership is $22/month or $220/year . Subscribe now. Subscribe now Lessons from Confidential Like a character in Atlas Shrugged, the natural question when beginning Confidential is, "Who is John Nolan?" The first thing to say is that this is the name you would want for a spy - a vaguely heroic sound being stirred into a bowl of porridge. There are, fittingly, few details online, so we must rely on Nolan's own telling. For twenty-two years, he worked as a spy. From the sparse available details, it seems Nolan spent time in some of the intelligence community's more controversial programs, a background that lends Confidential both its authority and occasional chill. After his time working for the government, Nolan founded a corporate espionage consultancy that advised business clients and gathered intel on their behalf. (One of the only articles I can find that mentions Nolan outside of Confidential covers an espionage campaign conducted by P&G against Unilever in 2000 to obtain the "secrets of shampoo." Nolan's firm was ostensibly the orchestrator.) As part of his work, Nolan's team relied on the psychological tools he outlines to extract sensitive information - all while being perfectly explicit about who they were. Beyond his team, Nolan also trained executives to use his techniques and protect themselves against him. Nolan's own "call to adventure" is a memorable starting point for the book. In 1960s New Jersey, Nolan started work as a typewriter salesman for a small local outfit, competing with a rep from IBM. Despite offering a superior product, Nolan struggled to shift them. While he flailed around trying to convince companies to have him in for an appointment, his rival was having companies call him - everyone knew that if you needed a typewriter, you went to "Big Blue." Sitting in a coffee shop one day, Nolan watched as the IBM salesman loaded typewriters into his station wagon. "In a brief moment of clarity," Nolan came to a realization. Why bother to hunt and scrabble for customers when he could simply follow his rival and figure out who was in the market for typewriters? For the rest of the day, he tailed the station wagon, watching it go from office to office. The next morning, he set out and visited every company, one after another, showcasing what his product could do. That week, he sold twelve typewriters. Over the following months, he repeated the trick, shadowing the IBM rep a few days each week. He grew cocky enough to wait outside an office building and follow him an hour later. Without meaning to, Nolan stumbled into the world of intelligence gathering and had seen what it could yield. This is the first of Nolan's rollicking stories, but it would be wrong to classify this as a collection of yarns. Across Confidential's 350 pages, Nolan outlines techniques of striking psychological acuity, interleaved with lessons from the history of espionage, and detailed examples. On a given page, you're just as likely to learn about the subterfuges Johnson & Johnson deployed to defend the Tylenol market as to analyze the brilliant sinuousness of Sherlock Holmes's questioning style. For this piece, we'll focus mainly on Part I: "Eliciting the Information You Want and Need." Though the latter two parts offer interesting details, they primarily address how organizations can collect intelligence more effectively or protect against spies. As the title of Part I suggests, it covers the art of "elicitation." Even if you are familiar with this word, its place in the Nolan lexicon is particular and benefits from definition. When the author writes about elicitation techniques, he explicitly means the following: Elicitation…is defined as that process which avoids direct questions and employs a conversational style to help reduce concerns and suspicions-both during the contact and in the days and weeks to follow-in the interest of maximizing the flow of information. As Nolan explains, elicitation is expressly distinct from interrogation and interviewing. "Interrogation [is] obtaining what you want from someone who possibly has it, who has not admitted to having it, and who knows who you are and why you want it," he writes. Meanwhile, "interviewing is the process of obtaining information from someone who probably has it, who has more or less admitted to having it, and who knows who you are and why you want it." Interrogation is, by definition, adversarial, while interviewing tends not to be. As you'll see, elicitation is a subtler dance. The worst way to get an answer might be a question Read more | N22: https://substackcdn.com/image/fetch/$s_!yWnR!,f_auto,q_auto:good,fl_progressive:steep/https%3A%2F%2Fsubstack-post-media.s3.amazonaws.com%2Fpublic%2Fimages%2F0dc7c606-ccf1-4e11-9832-1f178c3c45fe_1376x768.jpeg | S22: 1 | T22: core | U22: 2026-04-15 06:31:36 | V22: active | W22: 0 | Z22: 0 | AA22: 0 | AC22: 0 | AE22: 0 | AF22: 0 | AG22: 0 | AH22: 0
A23: 미확인 | B23: =IFERROR(INDEX('Source Check'!$A:$A, MATCH(C23, 'Source Check'!$B:$B, 0)), "미등록") | C23: 63 | D23: bucketplace.com | E23: https://www.bucketplace.com/culture/ | F23: =IFERROR(INDEX('Source Check'!$E:$E, MATCH(C23, 'Source Check'!$B:$B, 0)), "") | G23: 8108 | H23: https://www.bucketplace.com/culture/ | J23: bucketplace.com | S23: 1 | T23: light | U23: 2026-04-15 06:31:36 | V23: active | W23: 0 | Z23: 0 | AA23: 0 | AC23: 0 | AE23: 0 | AF23: 1 | AG23: 1 | AH23: 1
A24: 미확인 | B24: =IFERROR(INDEX('Source Check'!$A:$A, MATCH(C24, 'Source Check'!$B:$B, 0)), "미등록") | C24: 63 | D24: bucketplace.com | E24: https://www.bucketplace.com/culture/ | F24: =IFERROR(INDEX('Source Check'!$E:$E, MATCH(C24, 'Source Check'!$B:$B, 0)), "") | G24: 750 | H24: https://www.bucketplace.com/post/2022-11-23-tech-company%EB%A5%BC-%EC%A7%80%ED%96%A5%ED%95%98%EB%8A%94-%EB%B2%84%ED%82%B7%ED%94%8C%EB%A0%88%EC%9D%B4%EC%8A%A4-%EA%B0%9C%EB%B0%9C-%EB%AC%B8%ED%99%94-ver-2022_01/ | J24: 2022 11 23 tech company를 지향하는 버킷플레이스 개발 문화 ver 2022 01 | L24: 엔지니어링팀의 다양한 변화와 새로운 시도 | N24: https://res.cloudinary.com/bucketplace-co-kr/image/upload/v1669177348/20221121__%EA%B0%9C%EB%B0%9C%EB%AC%B8%ED%99%94__%EC%8D%B8%EB%84%A4%EC%9D%BC_01.png | S24: 1 | T24: light | U24: 2026-04-15 06:31:36 | V24: active | W24: 0 | Z24: 0 | AA24: 0 | AC24: 0 | AE24: 0 | AF24: 0 | AG24: 0 | AH24: 0
A25: 미확인 | B25: =IFERROR(INDEX('Source Check'!$A:$A, MATCH(C25, 'Source Check'!$B:$B, 0)), "미등록") | C25: 63 | D25: bucketplace.com | E25: https://www.bucketplace.com/culture/ | F25: =IFERROR(INDEX('Source Check'!$E:$E, MATCH(C25, 'Source Check'!$B:$B, 0)), "") | G25: 748 | H25: https://www.bucketplace.com/post/2023-05-22-%EC%9C%A0%EC%82%AC-%EC%9D%B4%EB%AF%B8%EC%A7%80-%EC%B6%94%EC%B2%9C-%EA%B0%9C%EB%B0%9C-1-%EB%B9%84%EC%8A%B7%ED%95%9C-%EA%B3%B5%EA%B0%84/ | J25: 2023 05 22 유사 이미지 추천 개발 1 비슷한 공간 | L25: 콘텐츠 추천을 위한 이미지 유사도 모델 개발 과정 | N25: https://res.cloudinary.com/bucketplace-co-kr/image/upload/v1684725576/%EC%9C%A0%EC%82%AC_%EC%9D%B4%EB%AF%B8%EC%A7%80_%EC%8D%B8%EB%84%A4%EC%9D%BC.jpg | S25: 1 | T25: light | U25: 2026-04-15 06:31:36 | V25: active | W25: 0 | Z25: 0 | AA25: 0 | AC25: 0 | AE25: 0 | AF25: 0 | AG25: 0 | AH25: 0
A26: 미확인 | B26: =IFERROR(INDEX('Source Check'!$A:$A, MATCH(C26, 'Source Check'!$B:$B, 0)), "미등록") | C26: 63 | D26: bucketplace.com | E26: https://www.bucketplace.com/culture/ | F26: =IFERROR(INDEX('Source Check'!$E:$E, MATCH(C26, 'Source Check'!$B:$B, 0)), "") | G26: 746 | H26: https://www.bucketplace.com/post/2021-11-19-%EC%98%A4%EB%8A%98%EC%9D%98%EC%A7%91-msa-%EC%97%AC%EC%A0%95-part-1-%EC%8B%9C%EC%9E%91/ | J26: 2021 11 19 오늘의집 msa 여정 part 1 시작 | L26: 오늘의집이 MSA를 채택하고 나아가는 과정을 공유합니다. | N26: https://res.cloudinary.com/bucketplace-co-kr/image/upload/v1637808736/%EB%AF%B8%EB%A6%AC%EB%B3%B4%EA%B8%B0.png | S26: 1 | T26: light | U26: 2026-04-15 06:31:36 | V26: active | W26: 0 | Z26: 0 | AA26: 0 | AC26: 0 | AE26: 0 | AF26: 0 | AG26: 0 | AH26: 0
A27: 미확인 | B27: =IFERROR(INDEX('Source Check'!$A:$A, MATCH(C27, 'Source Check'!$B:$B, 0)), "미등록") | C27: 63 | D27: bucketplace.com | E27: https://www.bucketplace.com/culture/ | F27: =IFERROR(INDEX('Source Check'!$E:$E, MATCH(C27, 'Source Check'!$B:$B, 0)), "") | G27: 744 | H27: https://www.bucketplace.com/post/2022-05-20-%EA%B4%91%EA%B3%A0-%EC%A0%95%EC%82%B0-%EC%8B%9C%EC%8A%A4%ED%85%9C%EC%97%90-kafka-streams-%EB%8F%84%EC%9E%85%ED%95%98%EA%B8%B0/ | J27: 2022 05 20 광고 정산 시스템에 kafka streams 도입하기 | L27: Kafka를 통한 정산시스템 구축 | N27: https://res.cloudinary.com/bucketplace-co-kr/image/upload/v1653458979/Kafak_%EC%8D%B8%EB%84%A4%EC%9D%BC_%EC%88%98%EC%A0%95.jpg | S27: 1 | T27: light | U27: 2026-04-15 06:31:36 | V27: active | W27: 0 | Z27: 0 | AA27: 0 | AC27: 0 | AE27: 0 | AF27: 0 | AG27: 0 | AH27: 0
A28: 미확인 | B28: =IFERROR(INDEX('Source Check'!$A:$A, MATCH(C28, 'Source Check'!$B:$B, 0)), "미등록") | C28: 63 | D28: bucketplace.com | E28: https://www.bucketplace.com/culture/ | F28: =IFERROR(INDEX('Source Check'!$E:$E, MATCH(C28, 'Source Check'!$B:$B, 0)), "") | G28: 742 | H28: https://www.bucketplace.com/post/2023-07-13-%EC%9C%A0%EC%82%AC-%EC%9D%B4%EB%AF%B8%EC%A7%80-%EC%B6%94%EC%B2%9C-%EA%B0%9C%EB%B0%9C-2-%EB%B9%84%EC%8A%B7%ED%95%9C-%EC%83%81%ED%92%88/ | J28: 2023 07 13 유사 이미지 추천 개발 2 비슷한 상품 | L28: 커머스 상품 추천을 위한 유사도 모델 개발 과정 | N28: https://res.cloudinary.com/bucketplace-co-kr/image/upload/v1689225724/%ED%85%8C%ED%81%AC%EB%B8%94%EB%A1%9C%EA%B7%B8_%EC%9C%A0%EC%82%BC%EB%8F%84%EB%8D%B8_%EB%A9%94%EC%9D%B8.jpg | S28: 1 | T28: light | U28: 2026-04-15 06:31:36 | V28: active | W28: 0 | Z28: 0 | AA28: 0 | AC28: 0 | AE28: 0 | AF28: 0 | AG28: 0 | AH28: 0
A29: 미확인 | B29: =IFERROR(INDEX('Source Check'!$A:$A, MATCH(C29, 'Source Check'!$B:$B, 0)), "미등록") | C29: 63 | D29: bucketplace.com | E29: https://www.bucketplace.com/culture/ | F29: =IFERROR(INDEX('Source Check'!$E:$E, MATCH(C29, 'Source Check'!$B:$B, 0)), "") | G29: 740 | H29: https://www.bucketplace.com/post/2021-12-03-%EC%98%A4%EB%8A%98%EC%9D%98%EC%A7%91-msa-phase-1-%ED%94%84%EB%A1%A0%ED%8A%B8%EC%97%94%EB%93%9C-%EB%B6%84%EB%A6%AC%EC%9E%91%EC%97%85/ | J29: 2021 12 03 오늘의집 msa phase 1 프론트엔드 분리작업 | L29: MSA 전환의 첫 관문, 프론트엔드 분리작업 과정 | N29: https://res.cloudinary.com/bucketplace-co-kr/image/upload/v1638490703/14_%EC%8D%B8%EB%84%A4%EC%9D%BC_%EC%9D%B4%EB%AF%B8%EC%A7%80.jpg | S29: 1 | T29: light | U29: 2026-04-15 06:31:36 | V29: active | W29: 0 | Z29: 0 | AA29: 0 | AC29: 0 | AE29: 0 | AF29: 0 | AG29: 0 | AH29: 0
A30: 미확인 | B30: =IFERROR(INDEX('Source Check'!$A:$A, MATCH(C30, 'Source Check'!$B:$B, 0)), "미등록") | C30: 63 | D30: bucketplace.com | E30: https://www.bucketplace.com/culture/ | F30: =IFERROR(INDEX('Source Check'!$E:$E, MATCH(C30, 'Source Check'!$B:$B, 0)), "") | G30: 738 | H30: https://www.bucketplace.com/post/2023-02-27-%EC%BB%A4%EB%A8%B8%EC%8A%A4%ED%94%8C%EB%9E%AB%ED%8F%BC%ED%8C%80%EC%9D%98-%EC%98%A8%EB%B3%B4%EB%94%A9-%ED%94%84%EB%A1%9C%EC%A0%9D%ED%8A%B8/ | J30: 2023 02 27 커머스플랫폼팀의 온보딩 프로젝트 | L30: 온보딩 프로젝트 기간 동안의 경험과 느낀 점 | N30: https://res.cloudinary.com/bucketplace-co-kr/image/upload/v1677464378/%EC%98%A8%EB%B3%B4%EB%94%A9_%EC%9B%90%EB%B3%B8.jpg | S30: 1 | T30: light | U30: 2026-04-15 06:31:36 | V30: active | W30: 0 | Z30: 0 | AA30: 0 | AC30: 0 | AE30: 0 | AF30: 0 | AG30: 0 | AH30: 0
A31: 미확인 | B31: =IFERROR(INDEX('Source Check'!$A:$A, MATCH(C31, 'Source Check'!$B:$B, 0)), "미등록") | C31: 63 | D31: bucketplace.com | E31: https://www.bucketplace.com/culture/ | F31: =IFERROR(INDEX('Source Check'!$E:$E, MATCH(C31, 'Source Check'!$B:$B, 0)), "") | G31: 737 | H31: https://www.bucketplace.com/post/2021-12-17-msa-phase-1-%EC%84%9C%EB%B9%84%EC%8A%A4-%EA%B5%AC%EC%B6%95%EA%B3%BC-%EB%B0%B0%ED%8F%AC-with-mortar/ | J31: 2021 12 17 msa phase 1 서비스 구축과 배포 with mortar | L31: MSA 구축 및 배포 관리 플랫폼의 설계부터 구현까지 | N31: https://res.cloudinary.com/bucketplace-co-kr/image/upload/v1647507366/Mortar_%EC%8D%B8%EB%84%A4%EC%9D%BC.jpg | S31: 1 | T31: light | U31: 2026-04-15 06:31:36 | V31: active | W31: 0 | Z31: 0 | AA31: 0 | AC31: 0 | AE31: 0 | AF31: 0 | AG31: 0 | AH31: 0
A32: 미확인 | B32: =IFERROR(INDEX('Source Check'!$A:$A, MATCH(C32, 'Source Check'!$B:$B, 0)), "미등록") | C32: 63 | D32: bucketplace.com | E32: https://www.bucketplace.com/culture/ | F32: =IFERROR(INDEX('Source Check'!$E:$E, MATCH(C32, 'Source Check'!$B:$B, 0)), "") | G32: 735 | H32: https://www.bucketplace.com/post/2022-02-03-%EC%98%A4%EB%8A%98%EC%9D%98%EC%A7%91-msa-phase-1-devops/ | J32: 2022 02 03 오늘의집 msa phase 1 devops | L32: MSA 환경에 맞는 DevOps의 구축 | N32: https://res.cloudinary.com/bucketplace-co-kr/image/upload/v1647427808/DevOps_%EC%8D%B8%EB%84%A4%EC%9D%BC.jpg | S32: 1 | T32: light | U32: 2026-04-15 06:31:36 | V32: active | W32: 0 | Z32: 0 | AA32: 0 | AC32: 0 | AE32: 0 | AF32: 0 | AG32: 0 | AH32: 0
A33: 미확인 | B33: =IFERROR(INDEX('Source Check'!$A:$A, MATCH(C33, 'Source Check'!$B:$B, 0)), "미등록") | C33: 63 | D33: bucketplace.com | E33: https://www.bucketplace.com/culture/ | F33: =IFERROR(INDEX('Source Check'!$E:$E, MATCH(C33, 'Source Check'!$B:$B, 0)), "") | G33: 734 | H33: https://www.bucketplace.com/post/2020-10-27-%EC%98%A4%EB%8A%98%EC%9D%98%EC%A7%91%EC%9D%80-%ED%9A%8C%EC%82%AC-%ED%99%88%ED%8E%98%EC%9D%B4%EC%A7%80%EB%A5%BC-%EC%9D%B4%EB%A0%87%EA%B2%8C-%EA%B0%9C%EC%84%A0%ED%96%88%EC%96%B4%EC%9A%94/ | J33: 2020 10 27 오늘의집은 회사 홈페이지를 이렇게 개선했어요 | L33: 오늘의집에서 바텀업(Bottom-up)으로 일하는 방법 | N33: https://res.cloudinary.com/bucketplace-co-kr/image/upload/cover_1.png | S33: 1 | T33: light | U33: 2026-04-15 06:31:36 | V33: active | W33: 0 | Z33: 0 | AA33: 0 | AC33: 0 | AE33: 0 | AF33: 0 | AG33: 0 | AH33: 0
A34: 미확인 | B34: =IFERROR(INDEX('Source Check'!$A:$A, MATCH(C34, 'Source Check'!$B:$B, 0)), "미등록") | C34: 63 | D34: bucketplace.com | E34: https://www.bucketplace.com/culture/ | F34: =IFERROR(INDEX('Source Check'!$E:$E, MATCH(C34, 'Source Check'!$B:$B, 0)), "") | G34: 732 | H34: https://www.bucketplace.com/post/2020-10-22-%EC%98%A4%EB%8A%98%EC%9D%98%EC%A7%91%EC%97%90%EC%84%9C-sns-%EC%B1%84%EB%84%90%EC%9D%84-%ED%82%A4%EC%9A%B0%EB%8A%94-%EC%BB%A8%ED%85%90%EC%B8%A0-%EB%A7%88%EC%BC%80%ED%8C%85-%EC%A0%84%EB%9E%B5/ | J34: 2020 10 22 오늘의집에서 sns 채널을 키우는 컨텐츠 마케팅 전략 | L34: 각 SNS 채널별 고객 속성과 니즈, 소비 행태 파악을 통한 오늘의집만의 콘텐츠 발행 방법 | N34: https://res.cloudinary.com/bucketplace-co-kr/image/upload/claire_thumbnail3.jpg | S34: 1 | T34: light | U34: 2026-04-15 06:31:36 | V34: active | W34: 0 | Z34: 0 | AA34: 0 | AC34: 0 | AE34: 0 | AF34: 0 | AG34: 0 | AH34: 0
A35: 미확인 | B35: =IFERROR(INDEX('Source Check'!$A:$A, MATCH(C35, 'Source Check'!$B:$B, 0)), "미등록") | C35: 63 | D35: bucketplace.com | E35: https://www.bucketplace.com/culture/ | F35: =IFERROR(INDEX('Source Check'!$E:$E, MATCH(C35, 'Source Check'!$B:$B, 0)), "") | G35: 731 | H35: https://www.bucketplace.com/post/2023-10-25-%EC%98%A4%EB%8A%98%EC%9D%98%EC%A7%91-uxr%ED%8C%80%EC%9D%80-%EC%96%B4%EB%96%BB%EA%B2%8C-%EC%9D%BC%ED%95%A0%EA%B9%8C/ | J35: 2023 10 25 오늘의집 uxr팀은 어떻게 일할까 | L35: 최고의 의사결정을 돕는 방법 | N35: https://res.cloudinary.com/bucketplace-co-kr/image/upload/v1698197046/UXR%ED%8C%80.png | S35: 1 | T35: light | U35: 2026-04-15 06:31:36 | V35: active | W35: 0 | Z35: 0 | AA35: 0 | AC35: 0 | AE35: 0 | AF35: 0 | AG35: 0 | AH35: 0
... A40: 미확인 | B40: =IFERROR(INDEX('Source Check'!$A:$A, MATCH(C40, 'Source Check'!$B:$B, 0)), "미등록") | C40: 63 | D40: bucketplace.com | E40: https://www.bucketplace.com/culture/ | F40: =IFERROR(INDEX('Source Check'!$E:$E, MATCH(C40, 'Source Check'!$B:$B, 0)), "") | G40: 722 | H40: https://www.bucketplace.com/ko/post/2020-12-28-%EC%98%A4%EB%8A%98%EC%9D%98%EC%A7%91-%EC%82%AC%EB%AC%B4%EC%8B%A4%EC%97%90%EB%8A%94-11%EA%B0%9C%EC%9D%98-%EC%A7%91%EC%9D%B4-%EC%9E%88%EB%8B%A4%EA%B5%AC%EC%9A%94-%EB%9E%9C%EC%84%A0%EC%A7%91%EB%93%A4%EC%9D%B4-%EB%B3%B4%EB%9F%AC-%EC%98%A4%EC%84%B8%EC%9A%94-%F0%9F%99%8C/ | J40: 2020 12 28 오늘의집 사무실에는 11개의 집이 있다구요 랜선집들이 보러 오세요 🙌 | L40: 1000만 유저의 인테리어 플랫폼을 만드는 200명의 사무실은 어떤 모습일까요? | N40: https://res.cloudinary.com/bucketplace-co-kr/image/upload/1_3_%ED%83%80%EC%9A%B4%ED%99%80.jpg | S40: 1 | T40: light | U40: 2026-04-15 06:31:36 | V40: active | W40: 0 | Z40: 0 | AA40: 0 | AC40: 0 | AE40: 0 | AF40: 0 | AG40: 0 | AH40: 0
A41: 미확인 | B41: =IFERROR(INDEX('Source Check'!$A:$A, MATCH(C41, 'Source Check'!$B:$B, 0)), "미등록") | C41: 63 | D41: bucketplace.com | E41: https://www.bucketplace.com/culture/ | F41: =IFERROR(INDEX('Source Check'!$E:$E, MATCH(C41, 'Source Check'!$B:$B, 0)), "") | G41: 721 | H41: https://www.bucketplace.com/ko/post/2022-08-10-%EC%98%A4%EB%8A%98%EC%9D%98%EC%A7%91-%EA%B0%9C%EB%B0%9C%ED%8C%80%EC%9D%98-%E2%80%98engineering-awards%E2%80%99%F0%9F%8E%89/ | J41: 2022 08 10 오늘의집 개발팀의 'engineering awards'🎉 | L41: 오늘의집 개발팀의 첫 번째 Eng Awards | N41: https://res.cloudinary.com/bucketplace-co-kr/image/upload/v1660111830/Thumbnail.png | S41: 1 | T41: light | U41: 2026-04-15 06:31:36 | V41: active | W41: 1 | X41: 2026-04-18 | Y41: 2026-04-18 | Z41: 1 | AA41: 0 | AC41: 0 | AE41: 0 | AF41: 0 | AG41: 0 | AH41: 0
A42: 미확인 | B42: =IFERROR(INDEX('Source Check'!$A:$A, MATCH(C42, 'Source Check'!$B:$B, 0)), "미등록") | C42: 61 | D42: techblog.gccompany.co.kr | E42: https://techblog.gccompany.co.kr/ | F42: =IFERROR(INDEX('Source Check'!$E:$E, MATCH(C42, 'Source Check'!$B:$B, 0)), "") | G42: 6780 | H42: https://techblog.gccompany.co.kr/ | J42: techblog.gccompany.co.kr | S42: 1 | T42: focus | U42: 2026-04-15 06:31:35 | V42: active | W42: 0 | Z42: 0 | AA42: 0 | AC42: 0 | AE42: 0 | AF42: 1 | AG42: 1 | AH42: 1
A43: 미확인 | B43: =IFERROR(INDEX('Source Check'!$A:$A, MATCH(C43, 'Source Check'!$B:$B, 0)), "미등록") | C43: 61 | D43: techblog.gccompany.co.kr | E43: https://techblog.gccompany.co.kr/ | F43: =IFERROR(INDEX('Source Check'!$E:$E, MATCH(C43, 'Source Check'!$B:$B, 0)), "") | G43: 424 | H43: https://techblog.gccompany.co.kr/%EC%97%AC%EA%B8%B0%EC%96%B4%EB%95%8C-secret-%ED%94%8C%EB%9E%AB%ED%8F%BC-%EA%B5%AC%EC%B6%95%EA%B8%B0-part-2-%EC%8B%9C%ED%81%AC%EB%A6%BF-%EC%A0%80%EC%9E%A5%EC%86%8C%EB%A5%BC-%EC%A0%84%EC%B2%B4-%EC%84%9C%EB%B9%84%EC%8A%A4%EC%97%90-%EC%A0%81%EC%9A%A9%ED%95%98%EA%B8%B0%EA%B9%8C%EC%A7%80-4219207675b3?source=rss----18356045d353---4 | J43: 여기어때 secret 플랫폼 구축기 part 2 시크릿 저장소를 전체 서비스에 적용하기까지 | L43: 안녕하세요, 여기어때컴퍼니 DevOps팀 셀린입니다. 지난 글에서는 Secrethub를 왜 도입하게 되었는지 이야기했습니다. 이번 글에서는 그 다음 단계, "그래서 어떻게 적용했는가!" 에 대해 이야기해보려고 합니다. 결과부터 말씀드리면, Secrethub는 여기어때 EKS 환경에서 운영 중이던 모든 애플리케이션 에 적용되었습니다. 🎊 이 글에서는 그 결과에 도달하기까지 어떤 선택을 했고, 어떤 기준으로 설계했는지를 차근히 풀어보겠습니다. 🧑‍💻 3줄 요약 CI/CD 표준화가 잘 적용되어 있는 EKS 환경 부터 적용해, 전사 확산의 속도를 높였습니다. 민감 정보 변경이 자동으로 반영되도록 ESO 기반 동기화 구조 를 만들었습니다. Spring Boot 프로젝트에는 공통 Loader를 제공 하고, Shadow 방식 으로 충돌 걱정 없이 적용할 수 있도록 했습니다. 어디부터 적용할 것인가 저희 여기어때 서비스의 배포 환경은 크게 두 가지 였습니다. EKS 환경은 이미 표준화된 CI/CD Pipeline 위에서 운영되고 있었습니다. 반면 EC2 환경은 아직 표준화 이전이라 CI/CD 구조가 팀마다 상이했고, profile 사용 방식도 다양했습니다. 저희의 1차 목표는 빠르게 모든 서비스에 적용하는 것 이었기 때문에, 더 많은 프로젝트에 적용할 수 있고 구조가 정리되어 있는 EKS 환경 에서 먼저 안정성을 확보하고자 했습니다. EKS 환경에서는 어떻게 적용할 것인가 EKS 환경에서 애플리케이션이 Secret을 사용하는 방식은 정해져 있습니다. Kubernetes에서는 민감 정보를 Kubernetes Secret 이라는 형식으로 보관하고, Pod 생성 시 이를 환경변수나 파일 형태로 전달합니다. 그럼 자연스럽게 이런 질문이 생겼습니다. 🧐 Secrethub에 저장된 값을 어떻게 Kubernetes Secret으로 가져올까? 🧐 그리고 그 값이 바뀌면 Kubernetes는 어떻게 감지할까? 🧐 민감 정보가 변경될 때마다 직접 배포해야 하나? 민감 정보는 변경될 수 있는 값이기 때문에 수동 배포로 문제를 해결하는 순간 운영 부담이 커지게 됩니다. 그래서 저희가 내린 결론은 "자동 동기화" 였습니다. Secrethub에서 값이 바뀌면 Kubernetes에서도 자동으로 반영되도록 만들고 싶었습니다. 이에 따라 Webhook 기반 구조 를 고민하게 되었습니다. 그래서 선택한 구조 - External Secrets Operator(ESO) 여기서 등장한 것이 External Secrets Operator , 줄여서 ESO 입니다. ESO가 무엇인지 생소하실 텐데요, ESO는 외부 저장소에 있는 Secret을 가져와, Kubernetes가 이해하는 Secret으로 자동 동기화 해주는 컨트롤러입니다. AI 생성 이미지 (자체 제작) 쉽게 말해, Secrethub는 금고이고 ESO는 그 금고에서 값을 꺼내 Kubernetes에 배달해주는 배달원입니다. 이 구조의 장점은 명확합니다. 애플리케이션이 Secrethub를 직접 호출하지 않아도 됩니다. 애플리케이션은 기존처럼 Kubernetes Secret 만 사용하면 됩니다. 전체 구조 한눈에 정리 ☝️ 로컬과 서버는 시크릿을 가져오는 방식이 다릅니다. 여기서 한 번 정리를 하고 가면 이해가 쉬워집니다. 로컬 환경 로컬에서는 애플리케이션이 직접 Secrethub를 호출 합니다. CLI 로그인 후 생성된 accessToken을 기반으로 Loader 라이브러리가 API를 호출하고, 값을 Spring Environment에 주입합니다. EKS 환경 EKS 환경에서는 애플리케이션이 Secrethub를 호출하지 않습니다. ESO가 대신 Secrethub를 조회하고, 그 결과를 Kubernetes Secret으로 변환해 Pod에 전달합니다. 아래에서 구체적으로 동작 과정을 설명드리겠습니다. External Secret Operator 적용 구조 위의 그림은 EKS 환경에서 Secrethub가 동작하는 전체 흐름입니다. 먼저, Secrethub에 접근하기 위한 API Key는 AWS Secret Manager에 저장했습니다.(①) Secrethub 접근 키를 Secrethub 내부에 저장하면 접근하려면 키가 필요하고, 키를 얻으려면 접근해야 하는 순환 참조 문제 가 발생하기 때문입니다. 따라서 다음과 같이 역할을 분리했습니다. Secrethub → 실제 서비스에서 사용하는 Secret을 저장 AWS Secret Manager → Secrethub 접근용 인증키 저장 ClusterSecretStore는 AWS Secret Manager에 대한 접근 방식을 정의하고, ESO가 이를 기반으로 API Key를 조회합니다.(②) 이후 ESO가 Secrethub를 호출해 값을 가져오고, 이를 Kubernetes Secret으로 변환합니다.( ③ ) Pod는 기존 방식대로 Kubernetes Secret을 마운트해 사용합니다.(④) 실제로 아래와 같이 파일이 생성되게 됩니다. { "db/username": "celine", "db/password": "1234", "apiKey": "abcde" } 애플리케이션은 이 과정을 전혀 알지 못하고 단순히 읽기만 하면 됩니다. External Secret Operator 도입을 위한 실패 시나리오 조사 ESO는 Secrethub에 새롭게 도입하는 구조였습니다. 따라서 단순히 동작만 확인하는 것이 아니라, 실패했을 때 시스템이 어떻게 반응해야 하는지 를 먼저 정의해야 한다고 생각했습니다. 따라서 실제 적용 전에 발생 가능한 모든 실패 케이스를 정리하고 각 케이스별로 다음을 확인했습니다. Kubernetes Secret이 생성되는가? 기존 Secret이 업데이트되는가? 아무 변화 없이 유지되는가? 테스트한 주요 케이스 실제 Kubernetes 반응 확인 각 케이스별로 실제 ExternalSecret 리소스의 상태가 어떻게 변하는지도 확인했습니다. 사용자 요청 오류에 따른 ExternalSecret 응답 이러한 상황을 명확히 정의함으로써, 실제 운영 중 관련 오류가 발생했을 때 원인을 즉시 분류할 수 있도록 하고자 했습니다. 이를 통해 운영 중 장애가 발생했을 때, "ESO 문제인지, Secrethub 문제인지, 사용자 요청 문제인지" 근거를 가지고 설명할 수 있는 상태 가 되었습니다. Secret 저장 방식 선택 - 단일 JSON 파일 전략 Secret을 Kubernetes에 저장하는 방식도 여러 가지가 있었습니다. 가능한 저장 방식을 모두 시도해보면서 실제로 Pod에 어떻게 저장이 되는지를 확인해봤습니다. 결과적으로, 저희는 단일 JSON 파일 제공 방식 을 선택했습니다. 왜 단일 JSON 파일인가? 이 방식의 장점은 명확합니다. 1. Secret 구조를 그대로 유지할 수 있다. Secrethub에 저장된 JSON 구조를 그대로 Pod에 전달할 수 있습니다. 2. 애플리케이션은 파일 하나만 읽으면 된다. key별로 파일이 분리되는 방식의 경우 /etc/secrets/db-user /etc/secrets/db-password 처럼 여러 파일이 생성됩니다. 이 경우 애플리케이션은 여러 파일을 각각 읽어야 합니다. 반면 단일 JSON 파일 방식은, 파일 하나 만 읽으면 모든 값을 사용할 수 있습니다. 3. GitOps 관리 비용이 줄어든다. key를 개별로 매핑하는 방식은 Secret key가 하나 추가될 때마다 values.yaml에 다음과 같은 설정을 계속 추가해야 합니다. spec: data: - secretKey: db-user remoteRef: key: db property: user 서비스마다 key가 늘어날수록 values.yaml은 점점 복잡해집니다. 반면, 단일 JSON 파일 전략은 Secret 전체를 하나의 값으로 전달 하기 때문에 key가 추가되어도, values.yaml을 수정할 필요가 없습니다. 전사 적용이라는 목표를 고려했을 때, 이 단순함이 가장 큰 장점이었습니다. Secrethub Loader 라이브러리 적용 AI 생성 이미지 (자체 제작) EKS에서는 ESO가 Secret을 Kubernetes Secret으로 변환해주었습니다. 하지만, 또 하나의 과제 가 남아 있었습니다. Pod에 Secret이 들어왔다는 것은 알겠으나, Spring Boot는 그 값을 어떻게 인식할 것인가? 팀마다 Spring 설정 방식이 달라서 Secret을 언제, 어떻게 불러오는지 기준이 없었습니다. 그래서, 공통 라이브러리 를 제공하여 이를 해결하고자 했습니다. Secrethub Loader는 순수 Java 로 구현했습니다. 이렇게 한 이유는 단순합니다. Spring Boot 2.x / 3.x 모두 대응 가능 특정 Spring 내부 구현에 강하게 의존하지 않도록 설계 프레임워크 버전에 영향을 받지 않는 구조 유지 플랫폼 라이브러리는 "특정 팀의 기술 스택에 종속되지 않는 것" 이 중요하다고 생각했습니다. EnvironmentPostProcessor를 활용한 자동 주입 Secrethub Loader는 Spring Boot의 EnvironmentPostProcessor를 활용해 애플리케이션 시작 시점에 Secret을 자동으로 주입하도록 설계했습니다. Spring은 시작 시 application.yml과 환경 변수 등을 모아 설정을 구성합니다. EnvironmentPostProcessor는 이 과정에서 설정값을 하나 더 추가할 수 있는 확장 지점입니다. 이 시점에 Secret을 등록하면, @Value나 @ConfigurationProperties에서 기존 설정과 동일하게 사용할 수 있습니다. 이를 통해 다음이 가능해졌습니다. 애플리케이션 코드 수정 없이 Secret 자동 인식 @Value("${db.password}") 그대로 사용 가능 로컬 / EC2 / EKS 환경 모두 동일한 방식 으로 동작 공통 라이브러리의 가장 큰 고민: 의존성 충돌 Secrethub Loader는 여기어때 모든 프로젝트에 공통 라이브러리 로 제공되는 모듈입니다. 이때 제가 가장 고민한 부분은, 공통 라이브러리의 의존성 충돌 가능성 이었습니다. Secrethub Loader에서는 JSON / YAML 파싱 라이브러리가 필요했습니다. 처음에는 다음과 같은 방법도 고려했습니다. 목표는 명확했습니다. "공통 라이브러리가 각 프로젝트의 Classpath를 오염시키면 안 된다." 그래서 선택한 방법 - Shadow Jar 결론적으로 Shadow 방식(Shaded Jar) 을 선택했습니다. Shadow 는 라이브러리 내부 의존성을 외부에 노출하지 않도록 패키지 경로를 재작성하는 방식입니다. com.fasterxml.jackson → com.secrethub.shaded.jackson 이렇게 내부에서만 사용하는 독립 네임스페이스 로 변경합니다. 그 결과, Spring Boot 내부 Jackson과 무관 Classpath 오염 없음 공통 라이브러리로 안전하게 배포 가능 즉, 플랫폼 라이브러리가 기존 애플리케이션을 침범하지 않도록 설계했습니다. 마무리하며, 본 글에서는 Secrethub를 EKS 환경에 적용하며, External Secrets Operator 기반의 자동 동기화 구조를 설계하고, Spring Boot 공통 라이브러리를 통해 환경에 관계없이 일관된 Secret 주입 방식을 마련한 과정을 공유드렸습니다. 이번 적용을 통해 단순히 민감 정보를 중앙화한 것이 아니라, 실패 상황을 예측 가능한 상태로 정리하고, 팀마다 다른 설정 방식을 존중하면서도 일관된 동작을 보장하는 기준을 만들어갈 수 있었습니다. 특히 공통 라이브러리를 직접 설계하며 의존성 충돌을 방지하기 위한 Shadow 전략을 적용하고, PropertySource 우선순위를 검증하며 Secret이 기존 설정에 안전하게 주입되도록 구조를 다듬은 과정은 개인적으로도 큰 도전이었습니다. 전사 적용이라는 목표 아래, 단순히 "동작하는 구조"를 만드는 것이 아니라 운영 중 발생할 수 있는 실패 상황까지 정의 하고, 문제가 발생했을 때 설명 가능한 구조 를 만드는 데에 집중했습니다. Secrethub는 단순한 Secret 저장소가 아니라, 플랫폼 차원에서 기준을 만드는 작업 이었다고 생각합니다. 앞으로도 운영 환경에서 기준을 세우고, 반복 가능한 구조를 설계하는 DevOps 엔지니어로 성장해 나가겠습니다. 읽어주셔서 감사합니다. 🤗 여기어때 Secret 플랫폼 구축기 Part 2: 시크릿 저장소를 전체 서비스에 적용하기까지 was originally published in 여기어때 기술블로그 on Medium, where people are continuing the conversation by highlighting and responding to this story. | N43: https://cdn-images-1.medium.com/max/1024/1*FyBhIgutWmqZ4BhY03FPhQ.png | S43: 1 | T43: focus | U43: 2026-04-15 06:31:35 | V43: active | W43: 0 | Z43: 0 | AA43: 0 | AC43: 0 | AE43: 0 | AF43: 0 | AG43: 0 | AH43: 0
A44: 미확인 | B44: =IFERROR(INDEX('Source Check'!$A:$A, MATCH(C44, 'Source Check'!$B:$B, 0)), "미등록") | C44: 61 | D44: techblog.gccompany.co.kr | E44: https://techblog.gccompany.co.kr/ | F44: =IFERROR(INDEX('Source Check'!$E:$E, MATCH(C44, 'Source Check'!$B:$B, 0)), "") | G44: 422 | H44: https://techblog.gccompany.co.kr/%EC%97%AC%EA%B8%B0%EC%96%B4%EB%95%8C-secret-%ED%94%8C%EB%9E%AB%ED%8F%BC-%EA%B5%AC%EC%B6%95%EA%B8%B0-part-3-%EC%8B%9C%ED%81%AC%EB%A6%BF-%EC%A0%80%EC%9E%A5%EC%86%8C%EB%A5%BC-%EC%9A%B4%EC%98%81-%EA%B0%80%EB%8A%A5%ED%95%9C-%EC%83%81%ED%83%9C%EB%A1%9C-%EB%A7%8C%EB%93%A4%EA%B8%B0-%EC%BB%A8%ED%85%8C%EC%9D%B4%EB%84%88%ED%99%94%EB%B6%80%ED%84%B0-ci-cd-%EB%A1%9C%EA%B7%B8-%EC%88%98%EC%A7%91%EA%B9%8C%EC%A7%80-70d98127bd35?source=rss----18356045d353---4 | J44: 여기어때 secret 플랫폼 구축기 part 3 시크릿 저장소를 운영 가능한 상태로 만들기 컨테이너화부터 ci cd 로그 수집까지 | L44: 안녕하세요 여기어때컴퍼니 DevOps팀 다나입니다. 앞선 두 편에서 Secrethub가 무엇인지, 어떻게 설계했는지를 다뤘습니다. 이번 글에서는 설계한 서비스를 실제로 운영 가능한 상태로 만드는 과정을 이야기하려고 합니다. 컨테이너 이미지 빌드부터 CI/CD, 그리고 Observability까지 단순히 "배포가 되는 파이프라인"이 아니라 DevOps 관점에서 관리 가능한 구조를 만들고 싶었습니다. 그 고민이 이 글의 시작입니다. Bun 런타임 위에 구현한 Secrethub를 컨테이너로 배포하기 Secrethub는 Bun 기반으로 개발 되었습니다. Bun은 빠른 실행 속도와 번들러·패키지 매니저를 내장한 JavaScript/TypeScript 런타임으로, TypeScript를 별도 컴파일 없이 바로 실행할 수 있어 개발 생산성이 높습니다. 애플리케이션을 컨테이너로 패키징 하는 과정 뿐만아니라 Bun의 빌드 방식과 의존성 관리 전략 까지 함께 고민했습니다. isolated linker - node_modules를 심볼릭 링크 없이 구성하기 bunfig.toml에는 다음 설정을 사용하고 있습니다. [install] linker = "isolated" Bun의 기본 링커는 node_modules를 심볼릭 링크 방식으로 구성하는데, isolated 모드는 각 패키지를 독립적인 디렉토리에 복사하는 방식 으로 설치합니다. 심볼릭 링크로 인한 경로 해석 문제를 방지하고, 컨테이너 환경에서 파일 시스템을 더 예측 가능하게 만들어줍니다. Bun build: 빌드 결과물을 단일 파일로 AI Generated with ChatGPT 기존 Node.js 빌드 방식에서는 컴파일된 파일들이 여러 개로 나뉘고 node_modules 전체를 함께 가져가야 했습니다. 반면 Bun의 bun build는 TypeScript 소스와 모든 의존성을 정적으로 번들링해 단일 파일로 생성 합니다. 즉, 컨테이너 안에는 dist/index.js 파일만 존재합니다. node_modules도, 소스 코드도 없이 번들 파일만으로 서버가 구동됩니다. Dockerfile 멀티 스테이지 빌드 # ------- build stage ------ FROM oven/bun:1.3-slim AS build WORKDIR /app COPY package.json bun.lock bunfig.toml ./ COPY scripts ./scripts RUN bun install --frozen-lockfile COPY . . RUN bun run build # ------- run stage ------ FROM oven/bun:1.3-slim WORKDIR /app COPY --from=build /app/dist ./dist ENV PORT=3000 EXPOSE ${PORT} CMD ["bun", "./dist/index.js"] 빌드 스테이지 와 실행 스테이지 를 분리한 멀티 스테이지 빌드 구조입니다. 빌드 스테이지에서는 의존성 설치와 번들링을 수행하고, 실행 스테이지에는 dist/ 결과물만 복사합니다. 덕분에 최종 이미지에 소스 코드, node_modules, 빌드 도구가 포함되지 않아 이미지 크기를 크게 줄일 수 있습니다. Secrethub CI/CD 파이프라인 구성 Secrethub의 CI/CD 파이프라인은 다음과 같은 흐름으로 구성됩니다. GitLab Push → GitLab Runner: Lint / Build / Test → 컨테이너 이미지 빌드 & ECR Push → 배포 스크립트 S3 업로드 → CodeDeploy 트리거 → EC2: docker compose pull & up AI Generated with ChatGPT 기존 EC2 CI/CD 구조 (AS-IS) 여기어때의 EC2 프로젝트들은 Jenkins를 중심으로 CI/CD를 운영하고 있었고, 각 팀이 배포 스크립트를 서비스에 맞게 수정해 사용하는 방식이였습니다. 이 구조는 각 서비스의 특성에 맞게 유연하게 운영할 수 있다는 장점이 있지만, 파이프라인 개선도 서비스마다 해야한다는 의미이기도 합니다. 어떤 서비스가 어떤 방식으로 배포되고 있는지 파악하려면 직접 들어가서 확인하는 방법 밖에 없다보니 전체 배포 현환을 한눈에 파악하는데 어려움이 있습니다. 즉, CI/CD는 잘 동작하고 있었지만, 중앙에서 관리하고 개선 하기에는 구조적으로 확장성이 제한적인 구조였습니다. Gitlab CI 기반 중앙 관리 구조 Secrethub 프로젝트를 진행하면서, 단순히 하나의 서비스 CI/CD를 만드는 데 그치지 않고 DevOps에서 관리 가능한 확장성있는 CI/CD 구조를 만들고자 했습니다. DevOps팀에서는 이미 EKS 환경에서 Gitlab CI 기반의 공통 CI 템플릿 을 운영하고 있습니다. Secrethub은 EC2프로젝트이지만 컨테이너 기반으로 운영될 예정이었기 때문에, 이 공통 템플릿을 EC2에도 녹여내는 것이 가능하였습니다. 배포 대상만 다를 뿐, CI 흐름 자체는 EKS와 동일하게 가져갈 수 있었습니다. 핵심 설계 방향은 다음과 같았습니다. CI 로직은 DevOps팀에서 관리 서비스 설정만 선언적으로 정의 - 프로젝트 명, ECR 이미지명 등 최소한의 값만 명시합니다. 배포대상 구분없이 동일한 CI 흐름을 유지 - EC2든 EKS든 파이프라인 구조는 동일합니다. CD: CodeDeploy + Docker Compose CD 과정은 CodeDeploy를 통해 EC2에 배포 스크립트를 전달하고, docker compose up & down 방식으로 컨테이너를 갱신하는 구조입니다. CodeDeploy는 AWS에서 제공하는 배포 자동화 서비스로, appspec.yml에 정의된 순서에 따라 배포를 단계적으로 실행합니다. 각 단계마다 실행할 스크립트를 지정할 수 있는 데 이를 훅(hooks) 이라고 합니다. 대표적으로 ApplicationStop → BeforeInstall → AfterInstall → ApplicationStart 순서로 진행되며, 각 훅에서 컨테이너 중지, 파일 정리, 서비스 시작 등의 작업을 수행합니다. aws 공식 페이지 기존 배포 스크립트들을 살펴보니 컨테이너 중지 로직이 BeforeInstall 훅에 들어가 있었습니다. 배포 스크립트를 조금씩 수정해가며 쓰다 보니 적절한 훅이 있음에도 관행적으로 굳어진 것으로 보였습니다. 공식 문서에 따르면 실행 중인 애플리케이션을 종료하는 작업은 ApplicationStop 훅에서, 설치 전 준비 작업은 BeforeInstall 훅에서 처리하는 것이 더 적절하다고 판단하여 해당 방식으로 수정하였습니다. 배포 스크립트 설계에서 특히 신경 쓴 부분은 운영환경에서의 독립성이였습니다. 서버가 재부팅되거나 새로운 EC2 인스턴스로 교체되는 상황에서도, 배포 스크립트 하나만으로 전체 CI/CD 프로세스가 완료될 수 있도록 하는 것을 주안점으로 뒀습니다. 파이프라인이 완성된 후, Secrethub에 적용한 구조를 기반으로 DevOps 팀내에서 운영 중인 다른 EC2 서비스들에도 동일한 파이프라인을 순차적으로 적용하였습니다. Observability 서비스가 안정적으로 운영되기 위해서는 빌드와 배포뿐만 아니라, 관측(Observability) 역시 중요한 요소입니다. LGTM 연동을 진행하면서 가장 먼저 고민한 질문은 이것이었습니다. "로그 수집 책임을 어디에 둘 것인가?" 우리 환경은 하나의 EC2 서버에 여러 컨테이너(여러 서비스)를 실행 하는 구조였습니다. 이 환경에서 각 서비스마다 winston이나 pino 같은 로깅 라이브러리를 추가하고 OTEL 설정을 개별적으로 적용하는 방식이 과연 적절한 선택일지 고민하게 되었습니다. Docker 레벨 로그 수집 그래서 선택한 방식은 Docker log를 Loki Driver Client를 통해 직접 LGTM으로 전송하는 구조 였습니다. Container → Docker Log → Loki Driver → LGTM (Loki) 이 방식은 애플리케이션 코드 변경 없이 컨테이너 레벨에서 로그 수집을 처리 할 수 있다는 장점이 있습니다. Loki Docker Driver란? Grafana에서 공식 제공하는 Docker 로깅 드라이버 플러그인으로, 컨테이너의 stdout/stderr 로그를 Loki로 직접 전송할 수 있습니다. 왜 Docker 레벨 수집을 선택했는가 1️⃣ 컨테이너 레벨에서 일관된 수집 로그 수집 책임을 애플리케이션이 아닌 플랫폼(Docker 레벨) 으로 이동시켰습니다. → 여러 컨테이너가 동작하는 환경에서는 각 서비스 별 로깅 설정이 아닌, Docker 레벨에서 일괄 처리하는 방식을 택했습니다. 2️⃣ 언어/프레임워크 독립적 Node.js, Java, Python 등 어떤 스택이든 동일한 방식으로 로그 수집이 가능합니다. 3️⃣ 설정 표준화 가능 Docker Compose 템플릿을 통해 로그 수집 설정을 재사용 가능한 구조로 만들 수 있습니다. # logging.yml services: lgtm: logging: driver: loki options: loki-url: ${LOKI_URL} mode: "non-blocking" loki-batch-size: "400" loki-external-labels: > job=docker, environment=${PROFILE}, namespace=${PROFILE}-${ROOT_PROJECT_NAME}, service=${PROJECT_NAME} # docker-compose.yml services: secrethub: extends: file: ../logging.yml service: lgtm 앞으로의 방향: EC2 → EKS 현재 여기어때 서비스의 약 40%는 EC2 기반으로 운영되고 있습니다. EKS 전환을 장기적으로 진행 중이지만, 여러 이유로 당장 전환이 쉽지 않은 서비스들이 많습니다. 이런 상황에서 선택한 전략은 CI를 먼저 표준화하는 것 이었습니다. EKS 전환 시 바꿔야 할 것이 CD뿐이 되기 때문에 전환 범위가 줄어들고, GitLab CI로 통일되면 전사 배포 현황을 일관된 방식으로 파악하는 것도 가능해집니다. Secrethub 또한, 현재는 Docker Compose 기반 EC2 환경에서 운영하고 있지만, 안정성과 확장성을 고려해 공통 EKS 클러스터로 전환할 예정입니다. 마치며 Secrethub를 Cloud Native하게 운영하기 위해 고민한 것들을 정리해보면, 결국 하나의 방향으로 수렴됩니다. 로그 수집도, CI/CD 구조도, 빌드 방식도 - 서비스 단위가 아니라 플랫폼 레벨에서 관리 가능한 구조 를 만드는 것입니다. 그 방향이 앞으로의 EKS 전환과 운영 확장에도 자연스럽게 이어질 것이라 생각합니다. 끝까지 읽어주셔서 감사합니다😊 여기어때 Secret 플랫폼 구축기 Part 3: 시크릿 저장소를 운영 가능한 상태로 만들기 - 컨테이너화부터 CI/CD, 로그 수집까지 was originally published in 여기어때 기술블로그 on Medium, where people are continuing the conversation by highlighting and responding to this story. | N44: https://cdn-images-1.medium.com/max/1024/0*KaO0phMWhUAVbz9B.png | S44: 1 | T44: focus | U44: 2026-04-15 06:31:35 | V44: active | W44: 0 | Z44: 0 | AA44: 0 | AC44: 0 | AE44: 0 | AF44: 0 | AG44: 0 | AH44: 0
A45: 미확인 | B45: =IFERROR(INDEX('Source Check'!$A:$A, MATCH(C45, 'Source Check'!$B:$B, 0)), "미등록") | C45: 61 | D45: techblog.gccompany.co.kr | E45: https://techblog.gccompany.co.kr/ | F45: =IFERROR(INDEX('Source Check'!$E:$E, MATCH(C45, 'Source Check'!$B:$B, 0)), "") | G45: 420 | H45: https://techblog.gccompany.co.kr/%EC%97%AC%EA%B8%B0%EC%96%B4%EB%95%8C-%ED%98%84%EC%9E%A5%EC%8B%A4%EC%8A%B5%EC%83%9D%EC%9D%84-%EC%86%8C%EA%B0%9C%ED%95%B4%EC%9A%94-25b454ed29f2?source=rss----18356045d353---4 | J45: 여기어때 현장실습생을 소개해요 | L45: 여기어때에서는 1년에 두 번, 현장실습생을 채용하고 있어요. 2025년 하반기에는 총 16명의 실습생이 함께해 주셨는데요. 기술·영업·인사 등 다양한 직무 속 각자의 자리에서 멋지게 활약해 주셨답니다! 오늘은 각 직무에서 경험한 생생한 현장실습 후기를 들려드리려고 해요. 함께 만나보실까요? 💛 🗯️"담당 업무 및 소속 팀에 대해 소개해 주세요." 가브리엘 : 저는 DNA센터 MLOps팀에서 AgentOps와 DataOps쪽 업무를 맡은 안태영(가브리엘)입니다. 입사 초반에는 AWS Redshift에서 GCP 빅쿼리로 데이터를 이관 하는 업무를 담당했습니다. 후반에는 현재 사내 에이전트인 YAPP 개발과 YAPP을 활용한 사내 여러가지 태스크 자동화 작업을 진행했습니다. 팀장님의 젊은 리더십을 바탕으로 수평적이고 에너지가 넘치는 분위기 속에서, 인턴도 자유롭게 의견을 나누며 함께 성장하는 원팀 문화를 경험할 수 있었습니다. 윤: ES영업팀에서 6개월 동안 현장실습생으로 근무했던 함윤종(윤)입니다. 영업 전반을 지원하는 역할부터 직접적인 영업 활동까지 폭넓게 담당했습니다. 신규 고객 발굴을 위한 타겟 기업 선정과 고객 데이터 조사, 콜드 메일 발송과 아웃바운드 콜을 통한 초기 접촉, 이후 고객사와의 커뮤니케이션을 거쳐 제휴를 성사시키는 과정까지 영업 사이클 전반에 참여했습니다. 우리 팀은 밝고 웃음이 많은 분위기로 회사를 한층 부드럽게 만들고, 인턴들이 편안하게 적응할 수 있도록 업무와 회사 생활 전반을 세심히 챙겨주는 점이 가장 큰 장점이라고 생각합니다. 루카: 저는 현재 여기어때 DNA센터 Business Insight팀에서 데이터 분석가로서, 데이터 마트 설계부터 태블로(Tableau)를 활용한 시각화, 그리고 비즈니스 인사이트 도출을 위한 심층 분석 업무를 담당하고 있습니다. BI팀의 가장 큰 장점은 실습생을 실무자로 존중하는 유연하고 수평적인 문화로, 단순히 업무를 수행하는 데 그치지 않고 분석의 목적을 함께 고민하며 의견이 실제 데이터와 대시보드에 반영될 기회를 준다는 점입니다. 혀니: 안녕하세요, 인재영입팀에서 Talent Acquisition Assistant로 6개월간 현장실습을 진행한 이가현(혀니)입니다. 저는 인재영입팀에서 채용 오퍼레이션을 중심으로 채용 데이터 분석, 브랜딩 지원, Long List 구축, 그리고 여러 프로젝트성 업무까지 폭넓게 경험했습니다. 인재영입팀은 현업 부서와 후보자를 가장 가까이에서 만나는 팀인 만큼, 밝고 에너지 넘치는 구성원들로 이루어져 있습니다. AI 도입 등 빠르게 변화하는 채용 환경에 맞춰 트렌드를 꾸준히 학습하고 공유하며 더 나은 프로세스를 고민하는 팀으로, 새로운 아이디어 역시 열린 마음으로 검토하고 실행까지 적극 지원해주는 점이 특히 인상 깊었습니다. 🗯️️"나의 직무를 잘 수행하기 위해 가장 중요한 역량을 꼽아본다면?" 윤: 영업 직무에서는 다양한 이해관계자에게 자신의 의견을 논리적으로 전달하고, 상대의 니즈에 맞춰 설득력 있게 소통하는 커뮤니케이션 능력이 중요하다고 생각합니다. 또한 예상치 못한 이슈 속에서도 다양한 가능성을 열어두고 최적의 해결책을 찾는 문제 해결 중심의 사고가 필요합니다. 더불어 주어진 업무에 그치지 않고 개선점을 고민하며 새로운 기회를 만들어가는 능동적인 자세 역시 중요한 역량이라고 느꼈습니다. 루카: BI 직무에서 가장 중요한 것은 데이터를 다루는 기술적 역량과 비즈니스 도메인 이해도의 균형이라고 생각합니다. SQL을 활용해 방대한 로그 데이터에서 필요한 값을 정확하고 효율적으로 추출하는 능력이 필요하며, 나아가 지표 변화를 두고 가설을 세워 데이터로 검증하는 논리적 사고와 끈기도 중요합니다. 또한 분석 결과가 실제 의사결정으로 이어지기 위해서는 복잡한 내용을 이해하기 쉬운 비즈니스 언어로 전달하는 커뮤니케이션 역량 역시 필수적입니다. 가브리엘: MLOps 직무는 모델링 능력만큼이나 민첩한 대응력과 실행력이 중요합니다. 모니터링 중 발생하는 이슈를 즉각적으로 감지하고 해결할 수 있는 순발력이 필수적이며 빠르게 변하는 AI 트렌드에 맞춰 새로운 기술을 검증하는 PoC(Proof of Concept) 능력이 요구됩니다. PoC를 하며 즉각적으로 우리 회사의 기술에 맡게 시도 해보고 개선해 나가는 유연한 사고방식을 가진 분에게 적합합니다. 혀니 : 채용 오퍼레이션 업무를 맡으며 가장 중요하다고 느낀 역량은 꼼꼼함입니다. 일정 안내와 후보자 커뮤니케이션 등 작은 과정 하나하나가 곧 회사의 인상으로 이어지기 때문에, 세심하게 챙기는 태도가 후보자 경험을 좌우한다고 느꼈습니다. 또한 후보자와 현업 부서 사이에서 원활히 조율할 수 있는 유연한 커뮤니케이션 능력도 중요합니다. 더불어 아이디어와 개선점을 능동적으로 제안하고 실행하려는 적극성이 있다면 더욱 빠르게 성장할 수 있다고 생각합니다. 🗯️"실습 기간 동안 가장 인상 깊었던 프로젝트를 소개해 주세요." 루카: 전사 KPI인 Net GMV를 보다 정교하게 관리하기 위해, 단순 취소율이 아닌 취소 사유와 취소 이후 고객 행동을 연계해 분석했습니다. 특히 '순수 취소'와 '재예약'을 구분해 매출 손실을 줄이고 재예약을 유도할 전략을 도출하는 것을 목표로 삼았습니다. 25년 8월 숙소 주문 데이터를 분석한 결과, 재예약의 80%가 취소 후 24시간 이내 발생하는 '골든타임'이 존재함을 확인했고, 취소 사유와 실제 행동의 일치율은 51%에 그쳤습니다. 또한 순수 취소자의 절반이 취소 후에도 상품 상세 페이지를 탐색한다는 인사이트를 바탕으로, 취소 전·중·후 단계별 재예약 유도 전략을 설계했습니다. 그 결과 전체 취소 GMV의 41%가 재예약임을 데이터로 증명했으며, 재예약 비중을 5%p 개선할 경우 Net GMV가 약 1.7% 상승할 수 있다는 재무적 기대효과를 산출해 C레벨 전략 회의에서 공유했습니다. 가브리엘 : 가장 기억에 남는 과제는 '전사 뉴스 리포팅 자동화 프로젝트'입니다. 매일 아침 전사 공유를 위해 수작업으로 진행하던 뉴스 수집 프로세스를 개선하고자, 사내 AI 에이전트와 n8n을 활용해 크롤링부터 데이터 시각화, 메일 발송까지 전 과정을 자동화했습니다. 이를 통해 반복 업무에 소요되던 운영 리소스를 크게 절감할 수 있었습니다. 또 하나는 'GCP 이관 프로세스 자동화 구축'입니다. AWS Redshift에서 GCP BigQuery로 데이터와 프로시저를 이관하는 과정에서, LLM을 활용해 테이블 의존성 체크, 문법 변환, 데이터 적합성 검증까지 자동화했습니다. 두 프로젝트 모두 자동화를 통해 업무 효율과 비용 절감 효과를 직접 확인할 수 있어 더욱 의미 있는 경험이었습니다. 윤: 실습 당시 ES사업부는 기업체 중심 영업을 진행하고 있었고, 대학교 고객군의 GMV 비중은 낮아 우선순위가 높지 않은 상황이었습니다. 이에 현장실습생으로서 직접 기업 영업에는 제약이 있었지만, 회사 정책을 준수하면서도 주도적으로 기여할 수 있는 영역을 고민해 대학교 대상 제휴 활성화를 목표로 설정했습니다. 임직원 제휴를 우선 체결해 B2B 구조를 확보한 뒤, 해당 학교에 한해 학생 대상 프로모션을 진행하는 2단계 전략을 설계했습니다. 이후 신규 및 재활성화 가능 대학교를 선별해 순차적으로 컨택하고, 학생회와의 협상 과정에서는 개인 지원이 아닌 학교 전체 혜택 중심으로 구조를 전환했습니다. 그 결과 신규 대학교 제휴를 성사시키고, 대학생 전용 프로모션 기획까지 마무리할 수 있었습니다. 혀니: 현장실습 프로그램 개선을 목표로 만족도 서베이를 기획·분석하고, 이를 실제 프로그램 운영으로 연결했던 경험이 가장 기억에 남습니다. 일부 의견에 그치던 개선 요청을 객관적인 데이터로 확인하기 위해 실습생 전원을 대상으로 만족도 조사를 실시했고, 업무 수행·팀 지원·전반적 만족도 등 다양한 영역의 서베이 결과를 분석해 개선 과제를 도출했습니다. 멘토 지정 및 피드백 체계 보완이 필요하다는 점을 확인해 관련 프로세스를 정비했으며, 실습생 간 교류와 직무 멘토링에 대한 수요를 반영해 '직무 토크 세션'을 기획·운영했습니다. 해당 세션은 10개 직무로 확대되었고, 진로 설정에 실질적인 도움이 되었다는 긍정적인 피드백을 받았습니다. 데이터를 기반으로 문제를 정의하고 실행까지 주도했다는 점에서 특히 의미 있는 경험이었습니다. 🗯️"실습 전과 후를 비교했을 때, 가장 크게 달라졌다고 느끼는 부분은 무엇인가요?" 혀니: 실습을 하면서 채용이 단순한 충원을 넘어, 데이터 분석과 브랜딩, 캠퍼스 리크루팅 등 다양한 영역과 유기적으로 연결된 일이라는 것을 직접 체감하게 되었습니다. 특히 AI 도입 등 빠르게 변화하는 환경 속에서 트렌드를 읽고 이를 실무에 적용하는 것 역시 중요한 역할임을 배울 수 있었습니다. 현업 구성원들과 가까이에서 협업하며 채용 전반의 업무를 직접 경험한 것도 큰 자산이 되었습니다. 입사자 데이터 분석, 전형별 리드타임 관리, 지원 경로 분석, 만족도 서베이 해석 등을 수행하며 데이터를 기반으로 인사이트를 도출하고 개선 아이디어를 제안하는 역량을 기를 수 있었습니다. 또한 이번 경험을 통해 제 강점과 흥미를 더 깊이 이해하게 되었고, 앞으로의 커리어 방향을 구체화하는 계기를 마련할 수 있었습니다. 가브리엘: 처음에는 Docker가 무엇인지도 몰랐지만, 이제는 팀에서 사용하는 기술 스택을 이해하고 직접 활용할 수 있을 만큼 성장했습니다. 모르는 부분이 있을 때마다 아낌없이 도와주신 팀원분들 덕분에 기술적인 역량뿐 아니라, 현업에서 협업하고 소통하는 방식도 배울 수 있었습니다. 무엇보다 가장 큰 수확은 '사람'이라고 생각합니다. 6개월은 짧을 것이라 여겼지만, 어느새 헤어짐이 아쉬울 만큼 깊은 유대감을 쌓게 되었습니다. 이곳에서 얻은 실무 경험과 따뜻한 인연은 앞으로의 개발자 커리어에 든든한 밑거름이 되어줄 것이라 믿습니다. 윤: 고객을 직접 만나기 전, 데이터 분석을 통해 타겟을 정교화하고 효과적인 메시지와 접근 방식을 설계하는 전 과정을 경험했습니다. 이를 통해 영업은 단순한 말솜씨가 아니라, 데이터와 전략을 기반으로 철저히 준비하고 결과에 책임지는 직무임을 깨달았습니다. 또한 타겟 고객 발굴부터 초기 접촉, 제휴 협상까지 영업 전반을 직접 경험하며 실무에 대한 이해도를 높일 수 있었습니다. 이 과정에서 성과를 내기까지 필요한 준비와 의사결정의 무게를 배웠고, 향후 영업 커리어를 이어가는 데 있어 보다 현실적인 기준을 세울 수 있었습니다. 루카 : 입사 전에는 단순한 데이터 추출 지원 업무를 주로 맡게 될 것이라 예상했지만, 실제로는 프로젝트의 기획부터 실행까지 직접 주도하는 Hands-on 경험을 많이 할 수 있었습니다. 특히 'YAPP(Yeogi AI Platform & Portal)' 등 최신 에이전트 기술을 활용해 KPI 이상치 모니터링 파이프라인을 구축하며, 실습생에게도 도전적인 기회가 열려 있다는 점을 체감했습니다. 또한 BigQuery와 Redshift 기반의 대용량 데이터 처리, Tableau를 활용한 시각화 역량을 실무 수준으로 끌어올릴 수 있었습니다. '숙소 카테고리 장기 이용 분석'을 통해 모텔 카테고리의 유료 멤버십 도입 타당성을 데이터로 검증한 경험은, 단순 분석을 넘어 비즈니스 가치를 판단하는 데이터 분석가로 성장하는 데 중요한 전환점이 되었습니다. 🗯️"마지막으로 다음 현장실습생분들께 전하고 싶은 말을 남겨주세요." 가브리엘: 제 실습 생활을 이끌어준 한마디는 'Why not? Try it'이었습니다. "못할 게 뭐 있어?"라는 생각으로 부딪혔기에 어려운 프로젝트를 맡게 되어도 잘 마무리할 수 있었습니다. 새로 오실 분들도 미리 겁먹고 움츠러들지 않으셨으면 좋겠습니다. 여기어때는 새로운 도전과 눈에 보이는 발전 가능성이 있으면 팍팍 지원해주기 때문에 "이 정도는 나도 할 수 있어"라는 당당한 마음가짐만 있다면 무엇이든 해내실 수 있을 겁니다. 윤: 다음 학기 현장실습생분들께는 학교에서는 쉽게 경험할 수 없는 실제 현업을 직접 체험할 수 있는 소중한 기회라고 말씀드리고 싶습니다. 막연하게만 느껴졌던 영업 직무를 보다 구체적으로 이해할 수 있었고, 업무를 수행하며 현직자들의 시선과 사고방식을 배울 수 있는 시간이었습니다. 함께하게 될 팀원분들 역시 실습생의 의견을 열린 자세로 받아들여 주시기 때문에, 수동적으로 주어진 업무만 수행하기보다 스스로 해보고 싶은 일을 제안하고 주도적으로 움직일수록 더 많은 경험을 쌓을 수 있을 것이라고 생각합니다. 특히 사람과의 소통을 즐기고, 새로운 시도에 두려움이 없으며, 끈기 있게 도전하는 분들께 이 직무를 추천드리고 싶습니다. 루카: 여기어때는 실습생을 '잠시 머물다 가는 사람'이 아니라 '함께 일하는 미래의 동료'로 대해주는 곳입니다. 협업 툴 사용은 물론, 구글 빅쿼리 워크샵과 같은 사내 세미나, 스터디 등 활발하게 인사이트를 공유할 수 있어요. 기술적으로는 SQL 기본기가 가장 중요하지만, Antigravity나 Claude와 같은 AI 툴을 활용해 부족한 부분을 빠르게 보완하는 역량도 큰 도움이 됩니다. 평소 '여기어때' 앱을 사용하며 유저 관점에서 어떤 지표를 개선하면 좋을지 고민해보는 것도 좋은 준비가 될 것 같아요. 무엇보다 수동적으로 주어진 일을 하기보다, 스스로 문제를 정의하고 데이터로 답을 찾아가는 과정을 즐기는 분이라면 꼭 도전해보셨으면 합니다. 내 분석이 실제 비즈니스에 영향을 주는 경험은 생각보다 더 짜릿합니다! 혀니: 인재영입팀에서 근무하며 채용뿐 아니라 브랜딩, 데이터 분석 등 인하우스 채용팀의 다양한 업무를 폭넓게 경험할 수 있었습니다. 특히 이미 맡은 일 속에서도 개선 포인트를 찾고, 더 나은 방향을 고민해보고 싶은 분이라면 더욱 잘 맞는 환경입니다. 팀에서는 실습생의 의견도 존중해주기 때문에 아이디어를 제안하고 직접 실행해볼 기회가 충분히 열려 있습니다. 또한 팀원분들과 좋은 관계를 쌓으며 자연스럽게 피드백을 구하고 커리어에 대한 고민을 나누는 과정 역시 큰 자산이 되었습니다. 무엇보다 성실함과 자신감을 바탕으로 업무에 임하는 태도가 결국 가장 큰 성장으로 이어진다고 생각합니다. 여기어때 현장실습생을 소개해요 was originally published in 여기어때 기술블로그 on Medium, where people are continuing the conversation by highlighting and responding to this story. | N45: https://cdn-images-1.medium.com/max/1024/1*YeVcDmEj0MOm5d5JiEY5Jw.jpeg | S45: 1 | T45: focus | U45: 2026-04-15 06:31:35 | V45: active | W45: 0 | Z45: 0 | AA45: 0 | AC45: 0 | AE45: 0 | AF45: 0 | AG45: 0 | AH45: 0
A46: 미확인 | B46: =IFERROR(INDEX('Source Check'!$A:$A, MATCH(C46, 'Source Check'!$B:$B, 0)), "미등록") | C46: 61 | D46: techblog.gccompany.co.kr | E46: https://techblog.gccompany.co.kr/ | F46: =IFERROR(INDEX('Source Check'!$E:$E, MATCH(C46, 'Source Check'!$B:$B, 0)), "") | G46: 418 | H46: https://techblog.gccompany.co.kr/%ED%99%94%EB%A9%B4-%EB%8B%A8%EC%9C%84-%EB%B3%B5%EC%9E%A1%EC%84%B1%EC%9D%84-%ED%9D%A1%EC%88%98%ED%95%98%EB%8B%A4-%EC%97%AC%EA%B8%B0%EC%96%B4%EB%95%8C-bff%EC%9D%98-%EA%B8%B0%EB%A1%9D-74612e7d2986?source=rss----18356045d353---4 | J46: 화면 단위 복잡성을 흡수하다 여기어때 bff의 기록 | L46: 안녕하세요. 여기어때컴퍼니 항공연동개발팀(전 BFF개발팀) 리나입니다. 이번 글은 올해 2월까지 BFF개발팀으로서 근무하며 경험했던 내용을 바탕으로, "왜 BFF가 필요했는지" 그리고 "BFF팀이 어떤 역할을 수행했는지"를 정리한 기록입니다. 여기어때는 주문, 검색, 쿠폰, 리뷰, 항공, 결제 등 각 도메인 팀이 독립적으로 운영되는 MSA 구조를 기반으로 서비스되고 있습니다. 도메인 단위로 분리된 구조는 확장성과 자율성을 보장하지만, 화면 단위로 보면 또 다른 문제가 발생합니다. "한 화면을 구성하기 위해 왜 이렇게 많은 API를 호출해야 할까?" 이 질문에서 BFF 도입이 시작되었습니다. 1. 잘 나뉜 도메인, 그러나 무거워진 화면 현재 여기어때의 백엔드는 거대한 시스템을 도메인 단위로 나눈 MSA(Microservices Architecture) 구조로 이루어져 있습니다. 2025년 12월 기준으로 B2C Gateway(GW)에 등록되어 사용 중인 서비스는 약 50여개 에 달합니다. 주문결제, 유저혜택, 숙소, 검색, 전시, 패키지, 항공 등 수많은 도메인 팀이 각자의 Bounded Context 내에서 전문성 있게 API를 제공하고 있습니다. 하지만 데이터를 소비해야 하는 클라이언트(iOS, Android, Web) 입장에서는 어떨까요? 앞서 말씀드린 MSA 환경에서는 도메인이 세분화된 만큼 프론트엔드의 고충이 커지게 됩니다. 예를 들어, 새롭게 기획된 화면에서 아래 정보가 동시에 필요하다고 가정해보겠습니다. 검색 결과 리뷰 정보 쿠폰 및 혜택 포인트 잔액 주문 상태 이 경우 클라이언트는 5개 팀의 API를 모두 호출하여 조합하는 무거운 복잡한 연산을 수행해야합니다. 이러한 방식에는 다음과 같은 문제가 발생합니다. 네트워크 오버헤드: 5개의 API를 순차 또는 병렬로 호출하면 응답 시간이 크게 지연됩니다. 클라이언트 복잡도 증가: 각기 다른 API의 데이터를 화면에 맞게 맵핑하는 무거운 연산 로직을 앱과 웹에 구현해야 합니다. 중복 개발 및 유지보수 난이도: iOS, Android, Web 각각에서 동일한 데이터 조합 로직을 반복 구현해야 하며, API 변경 시 모든 플랫폼을 수정해야 합니다. 에러 처리의 어려움: 5개 API 중 1개만 실패해도 전체 화면을 에러 처리할지, 부분만 렌더링할지 클라이언트 단에서 복잡하게 처리해야 합니다. 즉, 도메인은 잘 나뉘어 있었지만 화면 단위 복잡성은 클라이언트에 남아 있었습니다. 2. BFF란 무엇인가 BFF(Backend For Frontend)는 단어 뜻 그대로 '프론트엔드를 위한 백엔드'를 의미합니다. 도메인 API가 기능 단위라면, BFF API는 화면 단위입니다. BFF는 단순 라우팅 레이어가 아닌, 특정 클라이언트의 화면(UI)이 요구하는 데이터 구조에 맞춰 여러 도메인 API를 조합하고 가공하는 UI-Driven 서버 계층 입니다. BFF의 핵심 역할은 다음과 같습니다. 여러 도메인 API 결과를 Aggregate 도메인 모델을 클라이언트 ViewModel로 변환 화면 단위 비즈니스 분기 로직 처리 내부 병렬 호출 및 성능 최적화 즉, 클라이언트가 하던 데이터 조합 책임을 서버로 이전하는 것. 이것이 BFF 도입의 본질이었습니다. 3. 구조의 변화 일반적인 API 구조 클라이언트 → Gateway → 각 도메인 API 기존의 여기어때 B2B/B2C Gateway는 단순한 트래픽 라우팅 역할에 가까웠습니다. 메쉬업, 데이터 조합, 비즈니스 분기 처리는 오롯이 클라이언트의 책임 으로 남아있었고, 앱이 점점 무거워지는 원인이 되었습니다. BFF 도입 구조 클라이언트 → BFF → (내부망) → 각 도메인 API 이제 클라이언트는 화면을 그리기 위해 단 하나의 BFF API만 호출 합니다. BFF는 내부 Private Zone 망에서 여러 도메인 API를 빠르게 호출하고, 클라이언트가 화면을 그리기 편한 View Model 형태로 가공해 내려줍니다. 클라이언트는 복잡한 메쉬업 로직을 알 필요가 없어졌습니다. 4. 실제 적용 사례 현재 파트너센터 와 광고센터 에는 BFF가 중간 레이어로써 역할을 하고 있습니다. 아래 예시는 광고센터의 주문 내역 상세 페이지입니다. 화면을 온전히 구성하려면 다음과 같이 총 7~8개의 API를 호출해야만 주문 내역 정보를 온전히 표기할 수 있습니다. public OrderDetailContext loadOrderDetailContext(long orderId, List affiliateIds) { // 주문 정보 조회 OrderDetailResponse orderDetailExt = serviceAdvertisementComponent.getOrderDetail(orderId); // 주문과 엮인 결제 정보 조회 PaymentDetailResponseExt paymentDetailExt = serviceAdvertisementComponent.getPaymentDetail(paymentId); // 주문과 엮인 제휴점 정보 조회 AffiliateDetailResponseExt affiliateDetailResponseExt = serviceAdvertisementComponent.getAffiliateDetail(affiliateId); // 잔여금 내역 조회 WalletResponseExt walletResponseExt = serviceAdvertisementComponent.getAffiliateWalletDetail(affiliateId); // 신용카드 내역 조회 List creditCardDeposits = getDepositsByPaymentMethod(affiliateId, PaymentMethodTypeExt.CARD_BIZ); // 가상계좌 내역 조회 List virtualAccountDeposits = getDepositsByPaymentMethod(affiliateId, PaymentMethodTypeExt.VBANK); if (plpOrderLineOpt.isPresent()) { ... // 추가 주문 정보 조회 List orderLines = serviceAdvertisementComponent.getOrderLines(request); ... } ... } 여기서 복잡성은 단순히 여러 API를 호출하는 것에 그치지 않습니다. 주문 상세 화면은 상태 조합에 따라 비즈니스 로직이 달라지는 구조이기 때문입니다. 예를 들어 CTA 버튼 노출 여부는 결제 상태, 계약 동의 상태, 결제 수단, 중지 여부 등 여러 조건을 종합적으로 판단해 결정됩니다. 이러한 분기 로직을 클라이언트가 직접 처리할 경우 각 플랫폼마다 동일한 조건식을 반복 구현해야 하므로 복잡도가 급격히 증가합니다. 또한 결제 수단이 자동이체인 경우에는 일반 결제와 달리 출금 요청 정보를 추가로 조회해야 하므로, 응답 모델 자체가 달라집니다. 이에 따라 자동이체 전용 응답 생성 로직을 별도로 분리하여 처리하고, 그 외의 경우에는 표준 응답 모델을 사용하도록 설계했습니다. 즉, 결제 유형과 상태 조합에 따른 UI 분기 로직을 서버 단에서 흡수함으로써, 클라이언트는 단일 API 응답만으로 화면을 안정적으로 구성할 수 있도록 구조를 정리했습니다. 결과적으로 클라이언트는 복잡한 조합 로직을 알 필요 없이, BFF에서 제공하는 '주문 상세 조회 API'라는 단건의 API만 호출하면 화면 구성에 필요한 모든 정보가 정제된 형태로 내려옵니다. 결과적으로, 다중 API 호출 제거 클라이언트 로직 단순화 상태 분기 로직 중앙화 변경 대응 속도 향상 이라는 효과를 얻을 수 있었습니다. BFF는 단순 중계 계층이 아니라, 화면 단위 복잡성을 흡수하는 조합 및 분기 레이어 로 동작했습니다. 5. BFF 구조에서 발생할 수 있는 문제점 및 실제 사례 하지만 모든 아키텍처가 그렇듯 BFF 역시 만병통치약은 아닙니다. 중간에 계층이 하나 추가되면서 저희가 겪었던 문제와 주의사항도 함께 공유해 드립니다. ⚠️ 장애 전파 (Cascading Failures) BFF는 기본적으로 여러 하위 도메인 API를 의존합니다. 만약 6개 중 1개의 API 응답이 계속 지연된다면, BFF 서버의 스레드는 해당 응답을 기다리느라(Block) 점차 고갈됩니다. 결국 해당 API와 무관한 다른 정상적인 요청들까지 처리하지 못하게 되는 '장애 전파' 현상이 발생하게 됩니다. 저희는 Spring Retry 기반의 지수 백오프(Exponential Backoff) 재시도 전략 을 적용해 일시적 네트워크 오류나 순간적인 외부 API 불안정에 대해 방어했습니다. 재시도 후에도 실패할 경우에는 빠른 실패(Fast Fail) 또는 대체 응답(Fallback) 으로 전환해 화면 전체가 멈추는 최악의 상황을 피하도록 설계했습니다. 추가로, 특정 외부 API가 실패율/지연 시간이 임계치를 넘는 상태가 일정 시간 이상 지속 된다면, 재시도만으로는 리소스 소모가 커질 수 있습니다. 이런 경우에는 실패 임계치를 기준으로 호출 자체를 차단하는 서킷 브레이커(Circuit Breaker) 도입 도 고려하였습니다. @Retryable( retryFor = {RetryableException.class}, noRetryFor = {NonRetryableException.class}, maxAttempts = 4, backoff = @Backoff(delay = 1000, multiplier = 2, maxDelay = 10000), listeners = {"retryListener"} ) ⚠️ 메모리 및 힙(Heap) 과부하 여러 마이크로서비스에서 대량의 데이터를 가져와 애플리케이션 메모리 위에서 조합(Join)하고 정렬하는 과정은 서버의 메모리를 크게 소모합니다. 하위 API에서 생각보다 큰 볼륨의 리스트를 반환하거나 병렬 스트림(Parallel Stream)을 남용할 경우, 잦은 GC(Garbage Collection)가 발생하거나 심하면 OOM(Out Of Memory)으로 서버가 다운될 위험이 있습니다. 저희는 이를 예방하기 위해 도메인 팀과 협의하여 하위 API 호출 시 반드시 페이징 처리를 강제하고, 반복 호출이 많은 데이터에는 Caffeine cache를 도입하여 불필요한 외부 호출과 객체 생성을 줄임으로써 메모리 부담을 줄여나갔습니다. BFF는 화면 단위 편의성을 제공하는 레이어이지만 동시에 데이터가 집중되는 지점이기도 합니다. 따라서 기능 구현뿐 아니라 메모리 사용 패턴을 고려한 설계 역시 중요한 운영 과제로 다루었습니다. @Cacheable( cacheNames = "priceCompetitionFilterCache", keyGenerator = "dashboardFilterKeyGen", sync = true ) public CommonResponse getFilters( @Configuration @EnableCaching public class CacheConfig { @Bean public List caffeineConfig() { return Arrays.stream(CacheType.values()) .map(cache -> new CaffeineCache(cache.getCacheName(), Caffeine.newBuilder() .recordStats() .expireAfterWrite(cache.getExpireAfterWrite(), TimeUnit.SECONDS) .maximumSize(cache.getMaximumSize()) .build() ) ) .toList(); } @Bean public CacheManager cacheManager(List caffeineCaches) { final SimpleCacheManager cacheManager = new SimpleCacheManager(); cacheManager.setCaches(caffeineCaches); return cacheManager; } } 6. 마치며 MSA는 도메인을 세분화합니다. 하지만 사용자는 도메인을 경험하지 않습니다. 사용자가 마주하는 것은 결국 하나의 화면입니다. BFF는 그 화면을 중심에 두고 설계된 레이어였습니다. 도메인 간의 복잡성을 흡수하고, 상태 조합과 분기 로직을 정리해 화면이 온전히 동작하도록 만드는 역할을 담당했습니다. 지금도 여기어때의 많은 화면 뒤에서는 BFF가 여러 도메인의 데이터를 조합하고 재구성하는 중간 레이어로 동작하고 있습니다. 이 글이 BFF의 역할과 필요성을 이해하는데 도움이 되었기를 바랍니다. 긴 글 읽어주셔서 감사합니다. 화면 단위 복잡성을 흡수하다: 여기어때 BFF의 기록 was originally published in 여기어때 기술블로그 on Medium, where people are continuing the conversation by highlighting and responding to this story. | N46: https://cdn-images-1.medium.com/max/1024/1*fT8qEXR6KKvpaRtjSoLXeQ.png | S46: 1 | T46: focus | U46: 2026-04-15 06:31:35 | V46: active | W46: 0 | Z46: 0 | AA46: 0 | AC46: 0 | AE46: 0 | AF46: 0 | AG46: 0 | AH46: 0
A47: 미확인 | B47: =IFERROR(INDEX('Source Check'!$A:$A, MATCH(C47, 'Source Check'!$B:$B, 0)), "미등록") | C47: 61 | D47: techblog.gccompany.co.kr | E47: https://techblog.gccompany.co.kr/ | F47: =IFERROR(INDEX('Source Check'!$E:$E, MATCH(C47, 'Source Check'!$B:$B, 0)), "") | G47: 416 | H47: https://techblog.gccompany.co.kr/%EA%B8%B0%ED%9A%8D%EC%84%9C%EC%97%90%EC%84%9C%EB%B6%80%ED%84%B0-jira-%ED%83%9C%EC%8A%A4%ED%81%AC-%EC%97%85%EB%A1%9C%EB%93%9C%EA%B9%8C%EC%A7%80-tasky-ee7c0ef72be7?source=rss----18356045d353---4 | J47: 기획서에서부터 jira 태스크 업로드까지 tasky | L47: 안녕하세요 여기어때컴퍼니 프론트엔드 개발자 동글입니다. 개발을 하다 보면 기능 구현보다 더 많은 시간을 잡아먹는 일이 있습니다. 바로 기획 문서를 읽고, 이해하고, 태스크로 쪼개는 과정입니다. Confluence에 정리된 기획서를 읽고, 각 작업자들과 태스크를 나누고, 직접 Jira에서 티켓을 만드는 일은 굉장히 중요하지만 또 반복적이고, 사람에 따라 결과물의 편차도 큽니다. 이 과정을 자동화할 수 있다면 어떨까? 라는 질문에서 Tasky는 시작했습니다. Tasky는 Confluence 기획 문서를 기반으로 Jira 티켓을 자동 생성하는 AI 기반 워크플로우 자동화 시스템입니다. Tasky의 목표는 단순히 "AI로 티켓을 만들어준다"가 아니라, 팀의 생산성 향상을 위해 팀이 일하는 방식 그대로, 표준화된 태스크를 보다 빠르게 준비하는 것입니다. Tasky를 만들며 가장 중요하게 본 가치는 세 가지 였습니다. 첫 번째는, 개발자의 생산성 향상입니다. 기획서를 읽고 태스크를 쪼개는 일은 필수적이지만, 매번 처음부터 사람이 하기에는 반복적인 작업입니다. Tasky는 이 과정을 자동화해 개발자가 비즈니스 문제 해결과 구현에 보다 더 집중할 수 있도록 돕습니다. 두 번째는, 빠른 프로젝트 준비입니다. Confluence 문서를 Jira 티켓으로 옮기는 데에 많게는 수십분까지 걸리던 시간을 수 분 단위로 줄이는 것이 목표였습니다. 기획이 끝나면 곧바로 개발이 시작될 수 있는 상태를 만들 수 있다면 좋겠다는 생각이었습니다. 세 번째는, 일관된 태스크 품질과 표준화 입니다. 사람이 태스크를 만들면 누군가는 크게 범위를 잡아 태스크를 만들고, 누군가는 디테일하게 모든 태스크를 쪼갭니다. 또 종종 중복이 생기거나 누락이 생기기도 합니다. Tasky를 통해 정해진 패턴과 규칙을 기반으로 태스크가 생성된다면, 모든 프로젝트에서 일관된 태스크 구조를 유지할 수 있습니다. 이런 Tasky는 문서를 읽는 단계부터 Jira 등록까지 여러단계를 거치는 파이프라인으로 구성되어 있습니다. 첫 번째 단계는 문서 읽기 단계입니다. 가장 먼저 Tasky는 Confluence API를 통해 기획 문서를 읽어옵니다. 문서의 내용을 조회하고, HTML 태그를 제거해 순수 텍스트로 변환하고, 문서 제목과 본문, Space 정보를 추출해옵니다. 여러 페이지를 누적해서 한 번에 처리할 수도 있습니다. 두 번째 단계는 PRD 생성 단계입니다. 이미 사람이 만든 PRD가 있는데 다시 이 단계가 필요한 이유는, 사람이 작성한 정형화되지 않은 문서를 그대로 AI에게 전달하지 않고, 한번의 워싱을 거쳐 표준화된 형태의 PRD로 만들어 AI에게 전달하기 위함입니다. 이때 AI에게는 역할이 주어지는데요, "당신은 경험 많은 프로덕트 매니저입니다. 문서의 표현은 그대로 유지하면서 구조적인 PRD를 작성해주세요."와 같은 프롬프트를 통해 역할을 부여합니다. (실제 프롬프트는 조금 더 복잡하지만, 기본적인 의도는 같습니다.ㅎ) 역할이 부여된 AI는 문서를 분석해 프로젝트 개요, 핵심 기능, 사용자 경험, 기술 구조, 개발 로드맵, 기능 간 의존성, 리스크와 대응 방안 등의 내용을 포함한 JSON 형태의 PRD를 생성합니다. 이 결과를 검증한 뒤 표준 PRD 텍스트로 변환해 파일로 저장합니다. 그 다음 단계는 태스크 추출 단계입니다. 표준화된 PRD를 기반으로 AI는 기능별 개발 태스크를 추출하고, 태스크 간 의존성을 설정하며, 우선순위와 예상 소요 시간을 계산합니다. 이 단계에서 만들어지는 태스크는 범위가 다소 넓은 상위 레벨의 태스크입니다. 각 팀 별로 사용하기에는 아직 추상적인 부분이 많고, 실제 개발 단위로 사용하기에는 한번 더 다듬는 과정이 필요합니다. 그래서 Tasky는 한 단계 더 나아가 프론트엔드 태스크를 별도로 생성합니다. (추후 각 팀 별 태스크를 뽑아낼 수 있도록 고도화 할 예정입니다.) 단순히 키워드 매칭만으로 판단하지 않고, 2단계에서 만들어진 태스크의 제목과 설명, 상세 내용을 종합적으로 분석해 UI 개발, 사용자 인터페이스 구현, API 연동, 사용자 인터랙션 등 실제 프론트엔드 개발자가 작업해야 하는 요소들이 포함되어 있는지를 기준으로 프론트엔드 관련 태스크를 추려냅니다. 프론트엔드 관련 태스크를 선별한 이후에는, 기존 태스크를 그대로 사용하는 대신 다시 한 번 분석하고 개선하는 단계를 거칩니다. 이때 참고하는 것이 PRD 파일과 metadata.json 파일인데요, 앞서 생성한 PRD에는 기능의 의도와 배경이 담겨있고, metadata.json에는 실제 프로젝트에서 사용 중인 컴포넌트 구조, API 연동 패턴, UI 패턴 정보들이 정리되어 있습니다. 이 과정은 AI가 우리 프로젝트의 맥락을 이해하면서 태스크를 뽑아내는 데 중요한 역할을 합니다. ( 우리 팀 코드 스타일을 아는 AI 만들기: RAG와 Vector DB 활용기 ) 이제 상위 태스크를 뽑았으니, 더 디테일한 상세 태스크를 뽑아낼 단계입니다. 실제로 개발을 시작하려면, 하나의 태스크를 다시 여러 개의 실행 가능한 작업 단위로 쪼개는 과정이 필요합니다. 개발자들은 이 상세 태스크를 보고 개발을 하기 때문에, 이 단계를 가장 중요하게 다뤘습니다. 개발자가 티켓을 열었을 때, 바로 작업을 시작할 수 있는 수준까지 내려가면 좋겠다고 생각했기 때문입니다. 그렇기에 서브태스크 생성 시에는 작업마다 상세 설명에 메타데이터를 바탕으로 만들어진 설명을 함께 넣습니다. 서브태스크를 단순히 해야할 일로만 사용하지 않고, 프로젝트의 맥락이 포함된 설명을 넣어 개발자가 개발을 시작할 때 "어떻게 개발하지?" 라는 고민을 최대한 하지 않고, 바로 개발에 들어갈 수 있게 하는 역할을 하게 하기 위함입니다. 이 과정에서 예상 작업 소요시간이나 중요도도 함께 생성됩니다. 마지막으로, 이렇게 생성된 태스크와 서브태스크는 Jira REST API를 통해 선택된 Epic에 자동으로 등록됩니다. 태스크와 서브태스크의 계층 구조를 유지하면서 우선순위와 예상 소요 시간까지 함께 반영합니다. 이 과정을 마무리하고 나면, 개발자는 Jira에 들어가자마자 바로 일을 시작할 수 있는 상태가 됩니다. Tasky를 도입한 이후, 가장 크게 달라진 점은 태스크의 품질이 팀 전반에서 표준화되었다는 것입니다. 이제는 티켓만 보고도 전체 맥락을 빠르게 파악할 수 있고, 중복되거나 누락되는 태스크가 거의 사라졌습니다. 무엇보다 기획에서 개발 준비까지 걸리는 시간이 크게 단축되었습니다. 물론 중복 태스크 탐지 고도화나 시작일, 마감일 자동 업데이트, 디자인(Figma) 컨텍스트 연동 등 앞으로 개선하고 싶은 점도 여전히 남아 있습니다. Tasky는, AI가 모든 것을 대신 결정하는 어떤 도구가 아니라, 우리가 일하는 방식을 안전하게 자동화한 워크플로우라고 할 수 있습니다. 사람이 정한 맥락과 규칙 안에서 정해진 역할만 수행합니다. 문서를 티켓으로 바꾸는 이 단순한 자동화가 팀 전체의 생산성과 일관성을 얼마나 크게 바꿀 수 있는지 그 조그마한 가능성을 Tasky가 보여주고 있다고 생각합니다. 기획서에서부터 Jira 태스크 업로드까지, Tasky was originally published in 여기어때 기술블로그 on Medium, where people are continuing the conversation by highlighting and responding to this story. | N47: https://cdn-images-1.medium.com/max/1024/1*sFG7SjilM6ISpBAf4XT6-w.jpeg | S47: 1 | T47: focus | U47: 2026-04-15 06:31:35 | V47: active | W47: 0 | Z47: 0 | AA47: 0 | AC47: 0 | AE47: 0 | AF47: 0 | AG47: 0 | AH47: 0
A48: 미확인 | B48: =IFERROR(INDEX('Source Check'!$A:$A, MATCH(C48, 'Source Check'!$B:$B, 0)), "미등록") | C48: 61 | D48: techblog.gccompany.co.kr | E48: https://techblog.gccompany.co.kr/ | F48: =IFERROR(INDEX('Source Check'!$E:$E, MATCH(C48, 'Source Check'!$B:$B, 0)), "") | G48: 414 | H48: https://techblog.gccompany.co.kr/%EB%A9%80%ED%8B%B0-%ED%94%84%EB%A0%88%EC%9E%84%EC%9B%8C%ED%81%AC-%EB%94%94%EC%9E%90%EC%9D%B8-%EC%8B%9C%EC%8A%A4%ED%85%9C-%EA%B2%B0%EA%B5%AD-%EC%9A%B4%EC%98%81-%EA%B0%80%EB%8A%A5%ED%95%9C-%EA%B5%AC%EC%A1%B0%EB%A5%BC-%EC%84%A0%ED%83%9D%ED%95%9C-%EC%9D%B4%EC%9C%A0-de6cf9f8cbbc?source=rss----18356045d353---4 | J48: 멀티 프레임워크 디자인 시스템 결국 운영 가능한 구조를 선택한 이유 | L48: 안녕하세요. 서비스웹개발팀의 헨비입니다. 이번 글에서는 React와 Vue를 함께 지원하는 디자인 시스템을 직접 만들고 배포/운영하면서, 왜 결국 "모든 것을 동일하게 지원"하는 전략에서 "운영 가능한 범위를 선택하는 전략"으로 전환했는지 정리해보려고 합니다. 처음에는 core + react + vue 구조로 컴포넌트까지 일관되게 제공하는 것을 목표로 했지만, 실제 운영에서는 기능 추가, QA, 배포, 회귀 검증 비용이 빠르게 커졌습니다. 현재는 React 컴포넌트를 운영 축으로 두고, Vue에서는 토큰/스타일/유틸리티 같은 디자인 파운데이션을 중심으로 소비하고 있습니다. 이 전환 과정에서 무엇을 얻고 무엇을 포기했는지, 그리고 비슷한 상황에서 어떤 기준으로 선택해야 하는지 공유하겠습니다. 왜 멀티 프레임워크 디자인 시스템을 시작했나? 서비스웹개발팀은 레거시 Vue 프로젝트와 신규 React/Next.js 프로젝트를 동시에 운영하고 있습니다. 문제는 기술 스택 자체보다, YDS 업데이트를 프로젝트별로 반복 반영하는 운영 비용이 매우 컸습니다. 그래서 특정 당장 프레임워크 통일보다는 프레임워크가 달라도 공통 규칙을 재사용할 수 있는 구조를 먼저 찾았습니다. 검토 기준은 SSR, SEO, 복잡도, 런타임 의존성, 운영 유지비였습니다. 결론적으로 우리 팀 조건에서는 Headless Core + Framework Adapter가 가장 운영 가능한 선택이었습니다. 2. 초기 설계: core + adapter(react/vue) 구조 멀티 프레임워크 환경에서 중복 구현을 줄이기 위해 packages/core, packages/react, packages/vue로 구조를 분리했습니다. core는 디자인 토큰/스타일 유틸리티/headless 로직의 단일 출처로 두었습니다. react, vue는 프레임워크별 렌더링/이벤트/컴포넌트 표면만 담당하는 adapter로 설계했습니다. // core (headless) export function createBoxButton(props) { return { state, bindings } } // React adapter (요약) import { createBoxButton } from "@yeogiforge/core"; export function BoxButton(props) { const { state, bindings } = createBoxButton(props); return ( {props.children} ); } // Vue adapter (요약) import { createBoxButton } from "@yeogiforge/core"; const props = defineProps (); const { state, bindings } = createBoxButton(props); 두 adapter는 같은 core 로직을 공유하고, 프레임워크별 렌더링 표면만 다르게 가져갑니다. 즉, 상태/의미 체계는 core에서 통일하고 UI 연결 지점만 React/Vue에서 분리했습니다. 핵심 의도는 "규칙은 한 곳에서 관리하고, 프레임워크별 연결만 분리"하는 것이었습니다. 초기에는 이 구조가 일관성과 확장성을 동시에 잡는 가장 현실적인 방법이라고 판단했습니다. 문제는 아키텍처 선택 자체보다, 이 구조를 실제 운영하면서 발생한 이중 구현과 동기화 비용에서 본격적으로 드러났습니다. 구축보다 어려웠던 운영: 이중 구현과 동기화 비용 초기에는 core + adapter 구조로 중복을 줄일 수 있다고 판단했습니다. 하지만 실제 운영에서는 컴포넌트 레이어의 비용이 크게 남아 있었습니다. 새 컴포넌트를 추가하거나 기존 컴포넌트를 수정할 때마다 React/Vue 양쪽 구현, 스토리, 검증 포인트가 함께 늘어났습니다. 공통 로직이 core에 있어도, 프레임워크별 렌더링/상태 연결/엣지 케이스 대응은 각 adapter에서 별도로 처리해야 했습니다. 결과적으로 변경 1건이 "코어 수정 + React 반영 + Vue 반영 + 각각 확인"으로 이어지며 릴리즈 리드타임이 길어졌습니다. 팀 입장에서는 기능 확장보다 동기화 유지에 더 많은 시간을 쓰게 되었고, 이 지점이 운영 모델 전환의 계기가 되었습니다. 대응 해야 할 파운데이션과 컴포넌트의 목록 운영 모델 전환: React 컴포넌트 집중, Vue는 파운데이션 중심 운영 데이터를 기준으로 지원 범위를 다시 정의했습니다. 컴포넌트 레이어는 React를 단일 운영축으로 집중하고, Vue는 토큰/스타일/유틸리티 같은 디자인 파운데이션 소비에 집중하도록 전환했습니다. 이 결정은 "두 프레임워크를 모두 동일 수준으로 유지" 하는 목표보다, "지속 가능한 속도로 품질을 유지" 하는 목표를 우선한 결과였습니다. 이후 컴포넌트 변경 흐름이 단순해졌고, 신규 요구사항 반영 속도와 릴리즈 예측 가능성이 함께 개선되었습니다. 반면 Vue에서 컴포넌트 레벨의 즉시 확장성은 일부 포기했습니다. 대신 파운데이션 정합성을 유지해 시각/토큰 레벨의 일관성은 계속 보장했습니다. 결국 저희가 선택한 방향은 '모든 레이어를 동일하게 지원' 하는 전략이 아니라, 레이어별로 지원 수준을 다르게 설계해 운영 가능성을 확보하는 전략이었습니다. 파운데이션 공통화 범위와 개발자 사용성 저희는 컴포넌트 공통화 범위를 줄이는 대신, 파운데이션 레이어의 재사용성과 사용성을 높이는 데 집중했습니다. Typography : 폰트는 CSS 변수(` - forge-font-sans`)로 노출해 프로젝트별 오버라이드가 가능하도록 했습니다. Color Palette + Semantic Color : 원색 팔레트와 시멘틱 컬러를 분리해, 브랜드 변경과 UI 의미 변경을 독립적으로 다룰 수 있게 했습니다. SVG Icon : 아이콘 fill을 `currentColor`로 정규화해 React/Vue 어디서든 동일한 방식으로 색상을 제어하도록 했습니다. Shadow : 그림자 값을 토큰화해 컴포넌트와 화면 레벨 모두에서 같은 시각 기준을 재사용하도록 했습니다. 중요했던 기준은 "모든 것을 강제 공통화" 가 아니라 "필요한 파운데이션만 가져다 쓸 수 있는 유연성" 이었습니다. 덕분에 팀 내부 공통 자산으로도 활용하고, 프로젝트별 선택적 도입도 가능하게 설계했습니다. 멀티 프레임워크에서 '지원 범위'를 설계하는 법 이번 경험을 통해 멀티 프레임워크 디자인 시스템의 핵심은 기술 선택 자체보다, 지원 범위를 어떻게 설계하고 운영할지에 있다는 점을 확인했습니다. 처음에는 React/Vue를 동일 수준으로 지원하려고 했지만, 실제 운영에서는 구현·검증·배포 비용이 빠르게 증가했습니다. 그래서 현재는 React 컴포넌트를 운영축으로 두고, Vue는 파운데이션 공통화에 집중하는 방식으로 운영 모델을 재정의했습니다. 이 전환은 "더 많은 지원" 보다 "지속 가능한 품질과 속도" 를 우선한 선택이었습니다. 비슷한 상황에 있는 팀이라면, 아키텍처의 이상형보다 팀이 장기적으로 감당할 수 있는 지원 범위를 먼저 정의해보시길 권장드립니다. 디자인 시스템은 한 번의 구축으로 완성되는 결과물이 아니라, 운영 가능한 범위를 계속 조정해 나가는 제품이라고 생각합니다. 멀티 프레임워크 디자인 시스템, 결국 운영 가능한 구조를 선택한 이유 was originally published in 여기어때 기술블로그 on Medium, where people are continuing the conversation by highlighting and responding to this story. | N48: https://cdn-images-1.medium.com/max/1024/1*16PXSbf-WZdtDMRIH7sDvw.png | S48: 1 | T48: focus | U48: 2026-04-15 06:31:35 | V48: active | W48: 0 | Z48: 0 | AA48: 0 | AC48: 0 | AE48: 0 | AF48: 0 | AG48: 0 | AH48: 0
A49: 미확인 | B49: =IFERROR(INDEX('Source Check'!$A:$A, MATCH(C49, 'Source Check'!$B:$B, 0)), "미등록") | C49: 61 | D49: techblog.gccompany.co.kr | E49: https://techblog.gccompany.co.kr/ | F49: =IFERROR(INDEX('Source Check'!$E:$E, MATCH(C49, 'Source Check'!$B:$B, 0)), "") | G49: 412 | H49: https://techblog.gccompany.co.kr/%EB%96%A8%EB%A6%AC%EB%8A%94-%EC%9D%B8%ED%84%B0%EB%B7%B0-%EB%8B%B9%EC%9D%BC-%EC%96%B4%EB%96%A4-%ED%95%98%EB%A3%A8%EB%A5%BC-%EB%B3%B4%EB%82%B4%EA%B2%8C-%EB%90%A0%EA%B9%8C%EC%9A%94-5f5ab1807b14?source=rss----18356045d353---4 | J49: 떨리는 인터뷰 당일 어떤 하루를 보내게 될까요 | L49: 여기어때 Interview Journey Ep.12- 인터뷰 당일 편 안녕하세요. 여기어때의 합류 여정을 담은 기획 시리즈 Interview Journey 두번째 에피소드 입니다. 지난 1편에서는 서류 합격 후 인터뷰를 준비하는 과정과 유용한 꿀팁들을 전해드렸는데요. 준비 과정의 막막함이 조금은 해소되셨나요? 🙂 이번 에피소드에서는 인터뷰 당일, 여러분이 겪게 될 생생한 여정을 따라가 보려 해요. 이 날은 누구에게나 긴장될 수 밖에 없죠. 여러분이 가진 역량을 100% 편안하게 발휘하실 수 있도록, 공간과 안내 과정 곳곳에 세심한 배려를 담아두었으니, 편하게 따라오시면 돼요. 자, 그럼 인터뷰 당일로 함께 떠나볼까요? 🏢 11층 리셉션 도착 환영합니다! 긴장하지 말고 들어오세요. 본사에 도착해 11층 엘리베이터에서 내리면, 'Welcome' 메시지와 귀여운 키오스크가 여러분을 가장 먼저 맞이합니다. 오른쪽을 보시면, 유리문과 그 너머에 리셉션 데스크가 보이실텐데요. 두리번거리고 계신다면, 인재영입팀에서 빠르게 알아채고 먼저 문을 활짝 열어 반갑게 인사드릴 거예요. 👀 혹시라도 문이 닫혀 있다면 당황하지 마시고 문 앞의 벨을 꾹 눌러주세요! 마치 원래 알던 사이처럼 따뜻하게 맞이해 드릴 테니, 편하게 리셉션 데스크로 오시면 돼요. 간단히 성함을 확인한 뒤에는 오늘 인터뷰에 대한 브리핑을 해드려요. 오늘 만날 면접관 : 어떤 분들과 이야기를 나눌지 한 번 더 짚어드려요. 진행 방식 : 예상 소요 시간과 인터뷰 형태(1:1 또는 다대일)를 안내해 드립니다. 기타 : 주차 정산 및 1차 인터뷰 종료 후 지급되는 여기어때 쿠폰에 대해서 미리 귀띔해 드려요. 본격적인 인터뷰에 앞서 가벼운 스몰톡을 나누며 굳어있는 긴장을 사르르 풀어드릴게요. ☕ 인터뷰 대기실 카페 들를 필요 없이, 편안하게 준비하세요. 지각할까 봐 일찍 출발했다가 시간이 너무 많이 남아버린 경험, 다들 있으시죠? 시간을 때우기 위해 굳이 근처 카페를 찾지 않으셔도 된답니다. 11층 리셉션에 도착하시면 후보자분들만을 위해 마련된 아늑한 인터뷰 대기실이 마련되어 있으니까요. [예비 젊은이들을 위해 준비했어요❤️] 시원한 생수와 커피머신 : 냉장고에는 시원한 생수가, 그 옆에는 작은 커피머신이 준비되어 있으니, 자유롭게 마시면 돼요. 배터리 걱정 NO : 인터뷰 직전까지 노트북으로 포트폴리오나 자료를 점검하시는 분들을 위해, 각 자리마다 플러그가 설치해두었어요. 와이파이 & 안내문 : 책상 위 팻말에는 와이파이 연결 방법과 마음을 편안하게 해주는 따뜻한 안내 문구가 적혀 있어요. 여유가 되신다면 천천히 읽어보며 호흡을 가다듬어 보세요. 🛋️ 인터뷰룸 입장 대화에만 온전히 집중할 수 있도록 준비했어요. 약속된 시간이 되면, 안내에 따라 인터뷰룸으로 이동하게 됩니다. 여기어때의 인터뷰룸은 진행 방식이나 참석 인원에 따라 알맞은 공간으로 배정되는데요. 아늑하고 따뜻한 분위기의 룸도 있고, 널찍한 테이블과 편안한 허먼밀러 의자가 세팅된 룸도 준비되어 있습니다. 인터뷰룸 안에도 마실 물이 세팅되어 있으니, 인터뷰 도중 목이 마를까 걱정하지 않으셔도 돼요. (인터뷰 종료 이후에는 별도 절차 없이 편하게 귀가하시면 됩니다. 주차권이 필요한 경우엔 리셉션을 들러주세요!) 💌 인터뷰 그 후 인터뷰를 마치고 나면, 고생하신 여러분을 위한 작은 선물과 인터뷰 만족도 서베이가 발송됩니다. 여기어때 쿠폰 & 서베이 발송 : 1차 인터뷰를 마치신 모든 분들께는 꿀맛 같은 휴식을 응원하며 여기어때 앱에서 사용할 수 있는 쿠폰 을 보내드려요! (카카오톡 알림으로도 꼼꼼히 챙겨드립니다.) 또한, 더 나은 채용 경험을 만들기 위한 인터뷰 만족도 서베이도 함께 발송됩니다. 투명한 결과 안내 : 가장 기다려지실 인터뷰 결과는 최대 2주 이내 로 안내해 드려요. 만약 내부 사정으로 결과 안내가 지연된다면, 기다리시지 않도록 상황을 미리 메일로 공유해 드립니다. 인터뷰 결과가 아쉽게 불합격인 경우에도, 소중한 시간을 내어주신 모든 분들께 빠짐없이 결과를 안내해 드리고 있습니다. 오늘 준비한 두 번째 이야기는 여기까지인데, 어떠셨나요? 인터뷰 당일 낯선 리셉션 문을 열고 들어오는 순간부터, 인터뷰를 진행하는 과정까지 머릿속으로 생생하게 그려지셨나요? 여기어때는 여러분과 만나는 모든 순간이 '좋은 경험'으로 남을 수 있도록 늘 지원자의 입장에서 고민하고 있어요. 이 글이 인터뷰를 앞둔 여러분의 긴장을 조금이나마 덜어주었기를 바라요. 다음 편은 마지막 에피소드로, 여기어때가 입사 첫날 신규 입사자를 어떻게 환영하고 적응을 돕는지 담아보려고 해요. 마지막 편도 많은 기대 부탁 드려요😊 떨리는 인터뷰 당일, 어떤 하루를 보내게 될까요? was originally published in 여기어때 기술블로그 on Medium, where people are continuing the conversation by highlighting and responding to this story. | N49: https://cdn-images-1.medium.com/max/1024/1*3_SLaVKSr1e-hmnDkQvlfQ.jpeg | S49: 1 | T49: focus | U49: 2026-04-15 06:31:35 | V49: active | W49: 0 | Z49: 0 | AA49: 0 | AC49: 0 | AE49: 0 | AF49: 0 | AG49: 0 | AH49: 0
A50: 미확인 | B50: =IFERROR(INDEX('Source Check'!$A:$A, MATCH(C50, 'Source Check'!$B:$B, 0)), "미등록") | C50: 61 | D50: techblog.gccompany.co.kr | E50: https://techblog.gccompany.co.kr/ | F50: =IFERROR(INDEX('Source Check'!$E:$E, MATCH(C50, 'Source Check'!$B:$B, 0)), "") | G50: 410 | H50: https://techblog.gccompany.co.kr/%EC%97%AC%EA%B8%B0%EC%96%B4%EB%95%8C-%EC%9D%B4%EB%B2%A4%ED%8A%B8-%EA%B8%B0%EB%B0%98-%ED%86%B5%ED%95%A9-%EC%95%8C%EB%A6%BC-%ED%94%8C%EB%9E%AB%ED%8F%BC-%EA%B5%AC%EC%B6%95%EA%B8%B0-part-1-why-3d2961d1e849?source=rss----18356045d353---4 | J50: 여기어때 이벤트 기반 통합 알림 플랫폼 구축기 part 1 why | L50: 안녕하세요. DevOps팀 아리입니다. 이번 글에서는 여기어때의 이벤트 기반의 통합 알림 플랫폼인 Notification Hub를 왜 구축했는지, 그 과정에서 어떤 어려움이 있었고 어떻게 풀어나갔는지를 공유해보려고 합니다. Notification Hub를 어떻게 구축했는지, 기술적으로 어떤 고민이 있었는지가 궁금하다면 Part 2 를 읽어주시길 바랍니다! 1. 좋은 알림이란 무엇인가 서비스의 규모가 커질수록 우리가 가장 경계해야 했던 것은 알림에 무뎌지는 것이었습니다. 봐도 그만, 안 봐도 그만인 메시지들이 쌓이면서 정작 즉시 대응이 필요한 크리티컬한 신호들이 그 속에 묻히기 시작했기 때문입니다. 기존의 개별적인 알림 전송 방식은 각 서비스의 자유도를 보장해 주었지만, 조직 전체 관점 에서는 알림의 질을 일정하게 유지하거나 체계적으로 관리하기 어려운 구조적 한계가 있었습니다. 그래서 NotiHub는 단순히 '알림을 보내는 기능'을 넘어, 누구나 목적에 부합하고 인지하기 쉬운 알림을 설계할 수 있는 전사적 토대 를 만들고자 했습니다. 목적에 맞게: 정보 전달용인지, 즉각 대응용인지에 따라 수신자와 채널이 명확히 구분될 것 인지하기 쉽게: 메시지를 읽는 즉시 상황을 파악하고 다음 행동(Action)으로 이어질 수 있을 것 2. 우리의 현실 채널을 가득 채운 알림들, 정작 중요한 건 묻혔습니다 기존에는 각 시스템(ArgoCD, GitLab 등)에서 제공하는 기본 슬랙 인테그레이션(Slack Integration)을 활용하고 있었습니다. 설정이 간편하고 슬랙이 제공하는 표준 포맷을 즉시 사용할 수 있다는 장점이 있었지만, 서비스 규모가 커지면서 자연스럽게 한계가 드러나기 시작했습니다. 첫째, 제공되는 포맷에 갇힌 낮은 자유도였습니다. 기본 인테그레이션은 정해진 포맷과 규칙 안에서만 작동합니다. 예를 들어 ArgoCD 알림 채널에는 하루 수백 건의 메시지가 쏟아졌지만, Healthy 상태의 성공 알림과 즉각 대응이 필요한 Degraded, Sync Failed 알림이 한데 뒤섞여 있었습니다. 멘션 기능조차 설정하기 어려워, 중요한 장애 신호를 찾으려면 수백 개의 메시지를 직접 스크롤해야 했습니다. 둘째, 정보의 파편화와 인지 부하입니다. GitLab도 마찬가지였습니다. MR과 Pipeline 알림이 구분 없이 섞여 올라왔고, 단순히 "실패했다"는 결과만 통보할 뿐이었습니다. 원인을 파악하려면 반드시 GitLab에 직접 접속해야만 했습니다. 결국 이러한 '경직된 알림 구조'는 누군가의 부주의가 아닌, 시스템이 정보를 제때 제대로 전달하지 못하는 구조적 한계로 이어졌습니다. 우리는 편리하지만 제약이 많은 기존 연동 방식에서 벗어나, 우리가 원하는 정보를, 우리가 원하는 포맷으로, 원하는 곳에 보낼 수 있는 완전한 통제권이 필요했습니다. 개인 계정 웹훅 94.48% 초기 기획 단계에서 사내 슬랙 웹훅 현황을 분석했습니다. 결과는 예상보다 좋지 않았습니다. 공용 계정 발급 프로세스가 이미 존재했음에도 불구하고, 이후 생성된 웹훅의 약 90%가 여전히 개인 계정으로 만들어졌습니다. 사실 사내에는 이미 공용 계정 발급 프로세스가 잘 갖춰져 있었습니다. 운영상의 문제를 해결하기 위해 만들어둔 소중한 장치였죠. 하지만 서비스와 조직이 급격히 성장하다 보니, 모든 정보가 온보딩 과정에서 완벽히 전달되기에 현실적인 어려움이 있었습니다. 이런 상황에서 개발자들은 당장 알림을 띄우기 위해 가장 익숙한 '개인 계정 생성'이라는 선택지를 택할 수밖에 없었을 거라고 생각합니다. 당시에는 그것이 최선의 해결책이었을지 모르나, 문제는 개인 웹훅이 '특정 개인의 계정'에 완전히 종속된다는 점 이었습니다. 이로 인해 조직 전체 관점에서는 조금씩 운영 부채가 쌓여가고 있었습니다. 히스토리의 증발 (계정 종속성) : 웹훅을 만든 담당자가 퇴사하여 계정이 삭제되면, 그와 연결된 웹훅도 예고 없이 함께 사라집니다. 운영의 악순환 : 코드에 하드코딩된 웹훅 URL이 갑자기 에러를 내며 알림이 끊기면, 원인을 파악하고 수정하여 신규 배포까지 마쳐야 하는 비효율적인 상황이 반복되었습니다. 낮은 효율성 : 단순한 알림 수신 채널 변경이나 포맷 수정조차도 매번 코드 리뷰와 배포 프로세스를 거쳐야만 했습니다. 분산된 정책, 파악할 수 없는 구조 알림 정책은 gitlab-ci.yaml, Jenkinsfile 같은 소스 코드부터 Grafana Alert, 슬랙 웹훅 설정 화면까지 사방에 흩어져 있었습니다. 어느 알림이 어디에 설정되어 있는지 찾는 것 자체가 어려웠습니다. 실제로 알림 설정을 찾지 못한 팀이 기존 채널을 그냥 나가버리고 새 채널을 파는 웃지 못할 상황도 있었습니다. 그 결과, 메시지는 발송되나 수신인은 없는 이른바 '유령 채널'이 무려 638개에 달했습니다. 3. 관리의 한계: 개인에서 조직으로 NotiHub는 문제의 근본 원인인 '개인에게 묶인 오너십'을 해결하고자 했습니다. 전 구성원이 이미 GWS(Google Workspace) 계정을 사용하고 있고 팀 소속 정보도 GWS에서 관리되고 있었기 때문에, 이를 기반으로 팀 단위 워크스페이스를 도입했습니다. 별도의 계정 체계를 새로 만들 필요 없이, GWS 소속 정보를 그대로 활용할 수 있었습니다. 권한 관리는 사내 개발자 플랫폼인 Devhub 내 NotiHub를 통해 이루어집니다. 일부 권한은 GWS 소속 정보와 자동으로 연동되며, 추가적인 접근이 필요한 경우에는 신청 후 검토를 거쳐 반영됩니다. 덕분에 특정 개인의 부재와 상관없이 알림 서비스가 안정적으로 운영될 수 있으며, 팀원 누구나 필요할 때 운영의 오너십을 함께 나눌 수 있는 구조가 되었습니다. 4. NotiHub 가 추구한 것들 문제를 정의했다면, 어떻게 풀 것인지가 중요합니다. NotiHub를 설계하면서 몇 가지 방향을 세웠습니다. 슬랙처럼 편하게: 러닝커브를 낮추되, 더 하려면 더 할 수 있게 새로운 도구를 도입할 때 가장 큰 장벽은 학습 비용입니다. 그래서 NotiHub는 기존 슬랙 웹훅과 동일한 인터페이스를 유지했습니다. 웹훅 URL만 NotiHub URL로 교체하면 즉시 동작합니다. 추가 설정 없이도 바로 사용할 수 있고, 더 세밀한 제어가 필요하다면 라우팅 규칙이나 템플릿 기능을 활용하면 됩니다. 왜 '직접 호출'이 아닌 '이벤트'여야 했는가: 관심사의 분리 NotiHub는 기존 슬랙 웹훅과 동일한 방식도 그대로 지원합니다. 알림 메시지를 직접 구성해서 보내는 기존 방식은 웹훅 URL만 교체하면 즉시 동작합니다. 이벤트 방식은 그보다 더 많은 것을 하고 싶은 팀을 위한 선택지입니다. 실제로 개발팀들과 이야기해보면 이런 니즈가 꽤 있었습니다. "배포 성공/실패 상태에 따라 다른 채널로 보내고 싶다", "특정 이벤트가 발생했을 때 외부 API를 자동으로 호출하고 싶다". 하지만 이런 로직을 구현하려면 결국 슬랙봇 서버가 필요했고, 서버 발급 자체가 허들이 되어 아예 포기하는 경우도 있었습니다. NotiHub의 이벤트 방식은 바로 이 지점을 해결하고자 했습니다. 각 시스템은 "이런 이벤트가 발생했다"는 사실만 전달하고, 이벤트 상태에 따른 라우팅, 채널 분기, Actions(API 호출 등)는 모두 NotiHub가 처리합니다. 별도의 슬랙봇 서버 없이도 NotiHub가 그 중간 레이어 역할을 대신할 수 있습니다. 덕분에 단순한 알림 채널 변경을 위해 코드를 수정하고 재배포하던 과정도 사라졌습니다. 비즈니스 로직과 알림 로직이 분리되면서, 정책 변경은 UI 설정만으로 즉시 반영됩니다. 목적에 맞는 알림, 인지하기 쉬운 알림 앞서 언급했던 ArgoCD와 GitLab 알림이 NotiHub를 통해 어떻게 바뀌었는지 소개합니다. Before After ArgoCD는 배포 상태에 따라 채널을 분리했습니다. #{env}-eks-deploy-info: 정상 배포 완료 및 리비전 정보. 히스토리 추적 용도. #{env}-eks-deploy: Degraded, Sync Failed 등 즉각 대응이 필요한 알림만. 채널을 나누고 나서 변화가 생겼습니다. 기존에는 실패 알림을 인지조차 못했던 개발팀에서 갑자기 "👀" 이모지가 붙기 시작하고, "왜 Degraded 상태로 알림이 오는 건지"를 직접 질문해오기 시작했습니다. 알림이 제 역할을 하기 시작한 것입니다. 포맷도 함께 개선했습니다. 단순히 "실패했다"는 통보에서 벗어나, 실패 원인(ComparisonError, RPC error 등)을 메시지 본문에 직접 포함시켜 ArgoCD UI에 접속하지 않아도 즉시 원인을 파악할 수 있게 했습니다. ArgoCD 애플리케이션과 Git Manifest로 바로 이동할 수 있는 딥링크도 추가했습니다. Before After GitLab은 MR 알림과 Pipeline 알림을 목적에 따라 채널로 분리하고, 코드 리뷰 댓글 내용을 슬랙 메시지 본문에 바로 포함시켜 GitLab에 접속하지 않아도 내용을 확인할 수 있게 개선했습니다. 알림의 범위도 MR 위주에서 CI/CD 전체 생명주기로 확장했습니다. 초기에는 단일 프로젝트에 시범적으로 도입했으나, 해당 팀 내부에서 긍정적인 피드백을 받은 덕분에 해당 부서 내 모든 프로젝트로 확대 적용된 케이스도 있었습니다. 강제적인 지침 없이 필요에 의해 자발적으로 확산 되었다는 점에서 뜻깊은 성과였다고 생각합니다. 좋은 알림을 만드는 가이드와 템플릿 "좋은 알림을 만들자"는 말은 쉽지만, 실제로 어떻게 만들어야 하는지는 막막한 경우가 많습니다. NotiHub는 모범 사례를 템플릿으로 제공합니다. 현재 제공 중인 GitLab 템플릿을 시작으로, 장애 대응용/모니터링용/상호작용형 알림 등 다양한 케이스를 순차적으로 확대할 예정입니다. 5. 마치며 지금까지 여기어때가 왜 Notification Hub(NotiHub)를 구축하게 되었는지, 그리고 우리가 정의한 '좋은 알림'이 조직에 어떤 변화를 가져왔는지 살펴보았습니다. 단순히 메시지를 전달하는 기능을 넘어, 개인에게 파편화되어 있던 운영 권한을 조직의 자산으로 내재화 하고, 개발자가 비즈니스 로직에만 집중할 수 있는 환경을 만드는 것이 NotiHub의 목표였습니다. 다음 Part 2에서는 고가용성을 보장하기 위한 아키텍처 설계와, 쏟아지는 이벤트를 안정적으로 처리하기 위해 사용한 기술 스택(Kafka, Redis 등)에 대해 깊이 있게 다뤄보겠습니다. 여기어때 이벤트 기반 통합 알림 플랫폼 구축기 Part 1. Why? was originally published in 여기어때 기술블로그 on Medium, where people are continuing the conversation by highlighting and responding to this story. | N50: https://cdn-images-1.medium.com/max/1024/1*yPpvAbUahFgqpC-nfuyBVw.png | S50: 1 | T50: focus | U50: 2026-04-15 06:31:35 | V50: active | W50: 0 | Z50: 0 | AA50: 0 | AC50: 0 | AE50: 0 | AF50: 0 | AG50: 0 | AH50: 0
A51: 미확인 | B51: =IFERROR(INDEX('Source Check'!$A:$A, MATCH(C51, 'Source Check'!$B:$B, 0)), "미등록") | C51: 61 | D51: techblog.gccompany.co.kr | E51: https://techblog.gccompany.co.kr/ | F51: =IFERROR(INDEX('Source Check'!$E:$E, MATCH(C51, 'Source Check'!$B:$B, 0)), "") | G51: 407 | H51: https://techblog.gccompany.co.kr/%EC%97%AC%EA%B8%B0%EC%96%B4%EB%95%8C-%EC%9D%B4%EB%B2%A4%ED%8A%B8-%EA%B8%B0%EB%B0%98-%ED%86%B5%ED%95%A9-%EC%95%8C%EB%A6%BC-%ED%94%8C%EB%9E%AB%ED%8F%BC-%EA%B5%AC%EC%B6%95%EA%B8%B0-part-2-how-11f41bb2b5f2?source=rss----18356045d353---4 | J51: 여기어때 이벤트 기반 통합 알림 플랫폼 구축기 part 2 how | L51: 안녕하세요. DevOps팀 아리입니다. 지난 1편에서는 시스템의 탄생 배경을 다뤘다면, 이번 글에서는 NotiHub의 기술적 설계와 그 과정에서 내린 주요 의사결정들을 깊이 있게 공유하고자 합니다. 1. 왜 만들었는가 인터널 툴에는 두 가지 측면이 있습니다. 조직적 측면과 개인적 측면입니다. NotiHub는 조직적 효율성에 무게를 둔 프로젝트라고 생각합니다. 슬랙은 보편적으로 어느 회사에서나 사용하고 있지만, NotiHub는 우리 조직만의 커스텀 도구입니다. 사용자에게는 새로운 학습 비용이 발생하게 됩니다. 그럼에도 '중앙 집중형 구조'를 선택한 이유는 명확한 관리의 한계 때문이었습니다. 웹훅의 종속성 문제 : 특정 개인이 생성한 웹훅은 퇴사 시 계정 삭제와 함께 사라집니다. 이는 애플리케이션 에러와 긴급 배포로 이어지는 악순환을 만들었습니다. 모니터링의 부재 : 어떤 팀이 어떤 채널로 알림을 보내는지 파악이 불가능해 전사적인 알림 정책을 수립하기 어려웠습니다. 또한 대부분의 SaaS 서비스는 자체적인 슬랙 연동 기능을 제공합니다. 하지만 실제 운영 환경에서 이를 그대로 사용하기에는 몇 가지 한계가 있었습니다. 제한된 포맷 : SaaS가 제공하는 알림은 포맷이 고정되어 있어, 우리 팀에게 필요한 핵심 정보를 강조하거나 불필요한 노이즈를 제거하기 어려웠습니다. 라우팅의 경직성 : 특정 이벤트가 발생했을 때 내용에 따라 수신 채널을 동적으로 분리하고 싶어도, SaaS 설정만으로는 세밀한 조건별 분기가 불가능한 경우가 많았습니다. 이 외에도 자세한 탄생 배경이 궁금하다면 1편을 참고해주시길 바랍니다. 트레이드오프: 편의성 vs 안정성 중앙화의 가장 큰 숙제는 단일 장애점(SPOF) 문제입니다. NotiHub가 멈추면 전사의 알림이 멈춥니다. 저희는 이를 해결하기 위해 HPA(Horizontal Pod Autoscaler) 기반의 Scale-out과 무중단 배포, 그리고 다중 레이어 캐싱을 통해 가용성을 확보했습니다. 완벽한 정답은 없겠지만 관제 효율화로 얻는 이득이 운영 리스크보다 크다고 판단하여, 아키텍처 차원의 방어 기제를 두터이 설계했습니다. 2. 전체 아키텍처 개요 NotiHub는 확장성과 독립성을 위해 세 개의 레이어로 분리되어 있습니다. 아래 시퀀스 다이어그램을 통해 이벤트가 수신되어 슬랙으로 전달되기까지의 흐름을 확인할 수 있습니다. 이 구조의 핵심은 이중화된 확장 전략에 있습니다. 급격한 트래픽 증가 시 물리적인 Pod 확장은 HPA(Horizontal Pod Autoscaler)가 담당하여 컴퓨팅 자원을 확보하고, 논리적인 작업 분배는 Kafka의 Consumer Group과 내부 샤딩 로직이 담당하여 데이터 처리의 일관성과 분산 처리를 동시에 보장합니다. 각 컴포넌트는 Kafka와 Redis를 매개체로 연결되어 있어, 특정 구간에 부하가 걸려도 전체 시스템으로 전이되지 않는 구조를 가집니다. 3. 외부와의 접점: 보안과 확장성 내부망과 외부망의 분리 설계 기존 슬랙 웹훅의 사용자 경험을 유지하는 것이 핵심이었습니다. 내부망 : 인증 토큰 없이 URL 교체만으로 즉시 마이그레이션이 가능합니다. 외부망 (Jira, Slack API 등) : 보안을 위해 B2B Gateway를 통한 이중 검증 구조를 도입했습니다. 엔드포인트를 분리하여 '가벼운 Receiver'라는 원칙을 지키면서도 보안 요구사항을 충족했습니다. 단일 키 노출 시의 위험을 방지하기 위해, 시스템 전역에서 사용하는 Static Key 와 각 엔드포인트 별로 발급된 Dynamic Key 를 동시에 검증하는 구조를 택했습니다. 모든 검증을 외부 저장소(Redis)에 의존하면 네트워크 레이턴시가 발생합니다. 따라서, 변경 빈도가 낮은 Static Key 는 애플리케이션 기동 시 Secret Store에서 조회하여 인메모리에 캐싱 함으로써 1차 검증 속도를 극대화했습니다. 4. 유실 없는 수신을 위한 전략 Receiver는 의도적으로 최소한의 역할만 수행합니다. JSON 스키마 검증과 키 확인만 마치면 즉시 이벤트를 Kafka로 발행하여, 급격한 트래픽 증가(Burst) 상황에서 안정적인 버퍼 역할을 수행하고 Receiver와 Processor 간의 결합도를 낮춥니다. 이벤트 브로커로 Kafka를 선택한 배경에는 사내에서 이미 운영 중인 공용 Kafka 클러스터 가 있었다는 점도 크게 작용했습니다. 덕분에 인프라 구축이나 운영 리소스 부담 없이 즉시 메시징 구조를 도입할 수 있었습니다. 구체적으로는 Kafka의 Consumer Group 메커니즘을 통해 다수의 Processor Pod가 이벤트를 균등하게 나누어 처리하며, 특정 Pod에 장애가 발생하더라도 리밸런싱을 통해 유실 없이 작업을 이어받도록 설계했습니다. 동시에 CPU 점유율(80%) 기준의 HPA를 설정하여 트래픽 폭증 시 물리적 자원을 확장하도록 구성했습니다. 물론 설계 단계에서 Kafka Lag 기반 HPA나 Graceful Shutdown 같은 고도화된 장치들도 검토했으나, 현재는 Receiver 인입량과 Processor 처리 지표를 실시간 모니터링 하며 가용성을 확인하는 방식만으로도 충분하다고 판단했습니다. 인프라 복잡도를 낮게 유지하되, 지표상 유의미한 지연이 감지되는 시점에 맞춰 해당 기능들을 단계적으로 도입할 계획입니다. 5. 실시간 설정 반영: 3중 캐시 구조 사용자가 관리 페이지에서 알림 규칙(Rule)이나 템플릿을 수정하면 즉시 반영되어야 합니다. 성능과 최신 데이터 사이의 균형을 위해 계층형 캐시 전략 을 사용합니다. 캐시 계층: Local Cache (In-memory) → Redis → API/DB 전략: 현재는 로컬 캐시의 TTL을 짧게 유지하여 별도의 무효화(Invalidation) 로직 없이도 데이터 정합성을 확보하고 있습니다. 특히 Redis 장애가 서비스 전체의 중단으로 이어지지 않도록 다음과 같은 방어 기제(Failsafe)를 구축했습니다. Fallback 구조: Redis 조회가 실패할 경우 각 인스턴스의 로컬 캐시를 우선 활용하며, 최악의 상황에는 API 서버를 직접 호출하도록 설계했습니다. API 서버 또한 HPA 설정이 되어 있어 일시적인 직접 호출 부하 증가에 유연하게 대응합니다. 재연결 및 업데이트 제어: Redis 연결 이슈 발생 시 Exponential Backoff 전략을 적용해 재시도 간격을 점진적으로 늘림으로써 시스템 부하를 방지합니다. 설정 업데이트 실패 시에도 최대 3회까지만 재시도하여 프로세스 점유를 차단합니다. 결과적으로 각 인스턴스가 독립적인 로컬 캐시를 보유하고 있어, 단기간의 Redis 장애 상황에서도 알림 서비스의 연속성을 보장할 수 있습니다. 향후 이벤트 수가 늘어나고 API 서버의 부하가 가중될 경우, Redis의 Pub/Sub 기능을 도입하여 설정 변경 시점에만 로컬 캐시를 갱신하는 '이벤트 기반 무효화' 방식으로 전환할 예정입니다. 6. 슬랙 API의 한계 극복 (Rate Limit 핸들링) 베타 테스트 중 수천 건의 알림이 쏟아질 때 슬랙의 429 Too Many Requests 오류가 빈번했습니다. 이를 해결하기 위해 두 가지 전략을 도입했습니다. 슬랙봇 샤딩 (Slack Bot Sharding) 동일한 봇이 너무 많은 메시지를 보내지 않도록 봇 풀(Pool)을 구성했습니다. 일관성 유지 : bot_index = hash(channel_id) % bot_pool_size. 동일 채널의 메시지는 항상 동일한 봇이 담당합니다. 그래야만 메시지 업데이트(Update)나 스레드(Thread) 연결 시 권한 문제가 발생하지 않습니다. Main Bot vs Shard Bots : Private 채널이나 인터랙션(Button 클릭 등)이 필요한 경우, 모든 샤딩 봇을 채널에 초대하는 번거로움을 피하기 위해 권한을 가진 'Main Bot'이 예외적으로 처리하도록 이원화했습니다. 샤딩 도입 후 초당 수천 건의 메시지 전송도 안정적으로 처리됨을 확인했습니다. 채널별 큐 격리 특정 채널에서 Rate Limit이 발생해도 다른 채널에 영향이 가지 않도록 채널별 독립 큐를 운영합니다. 큐는 슬랙봇 샤딩과 동일한 모듈러 연산으로 관리되며, release 환경 기준으로 10개의 큐를 운영합니다. 지연이 발생하는 큐는 잠시 멈추지만, 다른 큐들은 정상적으로 메시지를 처리합니다. 이 과정에서 앞서 언급한 물리적 확장(HPA)과 논리적 분배(Sharding)가 시너지를 냅니다. Pod가 아무리 늘어나도(HPA), 특정 채널의 메시지는 일관된 해시 결과에 따라 지정된 큐와 봇을 통해 처리되므로 메시지 업데이트나 스레드 연산의 무결성이 깨지지 않습니다. Slack API 오류 대응 및 복원 전략 단순 실패 처리 대신 Processor 레벨에서 자동 복원을 시도합니다. no_text, msg_too_long, blocks_too_many 등의 오류가 감지되면 메시지를 분할하거나 blocks/attachments를 나눠 재전송하도록 처리됩니다. 7. Processor의 핵심 로직 Kafka를 통해 전달된 이벤트는 다음과 같은 핵심 과정을 거쳐 슬랙으로 전송됩니다. (1) 일대다 채널 라우팅 (Multi-channel Routing) 하나의 이벤트는 설정에 따라 여러 채널로 동시에 전송될 수 있습니다. 각 채널마다 별도의 템플릿과 전송 규칙(Rule)을 가질 수 있으며, 특정 조건에 따라 메시지를 분기하여 전달합니다. (2) 조건 엔진 및 템플릿 렌더링 (Handlebars) Condition Engine : 페이로드의 특정 필드 값이 error, critical 인지 등 조건(eq, neq, contains)을 판단하여 전송 여부를 결정합니다. 공휴일이나 시간 조건도 함께 설정할 수 있어 업무 시간 외 알림 등을 유연하게 제어할 수 있습니다. Handlebars : JSON 형태의 raw payload를 사용자 친화적인 슬랙 메시지로 변환합니다. {{#each errors}}...{{/each}}와 같이 복잡한 리스트 구조도 유연하게 표현할 수 있습니다. 렌더링 실패 시 raw payload를 텍스트로 전송하여 메시지 유실을 방지하고 있습니다. (3) 스레드 관리와 에스컬레이션 동일한 컨텍스트(예: incident_id)를 가진 이벤트는 하나의 스레드로 묶어 채널의 가독성을 높입니다. 스레드 키의 만료 시간은 기본 24시간이며 최대 7일까지 설정할 수 있습니다. 특정 시간 내에 확인 이모지 반응이 없는 경우 담당자를 멘션하거나 상위 채널로 재전송하는 에스컬레이션 정책을 최대 3단계까지 설정할 수 있습니다. 에스컬레이션은 1분 주기의 배치로 처리됩니다. 8. 마치며 개인 프로젝트나 단일 서비스에서 알림 시스템을 구축하는 것이 기술적 구현의 영역이라면, 전사 구성원이 함께 사용하는 플랫폼을 만드는 과정은 그와는 전혀 다른 고민을 안겨주었습니다. 특히 '단일 장애점(SPOF)'에 대한 우려와 시스템 안정성에 대한 동료들의 날카로운 피드백은 NotiHub가 더 견고한 아키텍처를 갖추는 데 가장 큰 동력이 되었습니다. 전사 플랫폼을 구축한다는 것은 결국 기술을 통해 조직의 신뢰를 쌓아가는 여정이라고 생각합니다. 앞으로도 사용자의 목소리에 귀 기울이며, NotiHub가 우리 조직에서 누구나 믿고 사용할 수 있는 플랫폼이 될 수 있도록 다듬어 가겠습니다. 감사합니다. 여기어때 이벤트 기반 통합 알림 플랫폼 구축기 Part 2. How? was originally published in 여기어때 기술블로그 on Medium, where people are continuing the conversation by highlighting and responding to this story. | N51: https://cdn-images-1.medium.com/max/1024/1*_ZLFEaTnVm5z0u6HQXdRVg.png | S51: 1 | T51: focus | U51: 2026-04-15 06:31:35 | V51: active | W51: 0 | Z51: 0 | AA51: 0 | AC51: 0 | AE51: 0 | AF51: 0 | AG51: 0 | AH51: 0
A52: 미확인 | B52: =IFERROR(INDEX('Source Check'!$A:$A, MATCH(C52, 'Source Check'!$B:$B, 0)), "미등록") | C52: 61 | D52: techblog.gccompany.co.kr | E52: https://techblog.gccompany.co.kr/ | F52: =IFERROR(INDEX('Source Check'!$E:$E, MATCH(C52, 'Source Check'!$B:$B, 0)), "") | G52: 405 | H52: https://techblog.gccompany.co.kr/%EC%BF%A0%ED%8F%B0%EC%9D%80-%EB%A7%8E%EC%9D%80%EB%8D%B0-%EC%99%9C-%ED%98%9C%ED%83%9D%EC%9D%80-%EB%8A%90%EA%BB%B4%EC%A7%80%EC%A7%80-%EC%95%8A%EC%95%98%EC%9D%84%EA%B9%8C-f5bd6e86d021?source=rss----18356045d353---4 | J52: 쿠폰은 많은데 왜 혜택은 느껴지지 않았을까 | L52: 글. 최서연(Effie) / UX Designer 여행을 준비하며 숙소를 고를 때, "이 숙소에 쿠폰이 적용될까?", "지금 받는 혜택이 최대 혜택이 맞을까?" "지금 예약 안하면 쿠폰 할인이 바뀌지 않을까?" 같은 고민을 해본 적 있으실 거예요. 저 역시 고객이 체감하는 쿠폰 혜택 경험을 어떻게 더 명확하게 만들 수 있을지, 그리고 동시에 다양한 비즈니스 요구 사항을 어떻게 충족할 수 있을지에 대한 고민을 안고 있었어요. 커머스의 핵심 영역 중 하나인 만큼 카테고리 운영, 전략, 파트너 협업 등 다양한 요구를 충족하면서 쿠폰의 구조는 계속 정교해지고, 고객 경험은 오히려 복잡해져갔죠. 이번 글에서는 쿠폰 UX 개선 프로젝트를 통해 복잡한 쿠폰 구조를 어떻게 정리했고 고객이 '지금 내가 가장 좋은 혜택을 받고 있다'고 느낄 수 있도록 어떤 UX적 솔루션을 시도했는지 그리고 그 결과 비즈니스적으로 어떤 변화가 있었는지를 공유해보려고 해요. 배경: 다양한 요구가 교차하는 쿠폰 영역 쿠폰은 성장 전략, 카테고리 운영 전략, 파트너와의 협업 구조 등 여러 비즈니스 맥락이 동시에 작동하는 영역이에요. 특정 카테고리를 강화해야 할 때도 있고, 인기 숙소에 혜택을 더 명확히 보여줘야 할 때도 있고 시즌이나 상황에 따라 전략적으로 운영되어야 할 때도 있어요. 이처럼 쿠폰은 하나의 목적만을 위해 존재하지 않아요. 각기 다른 요구가 교차하면서, 자연스럽게 구조도 복잡해졌죠. 하지만 여기서 중요한 질문이 생겼어요. "이렇게 설계된 쿠폰 구조는 고객에게도 같은 방식으로 이해되고 있을까?" 고객 관점에서 다시 본 쿠폰 경험 비즈니스 요구를 충족하기 위해 정교하게 설계된 쿠폰 시스템은 운영 측면에서는 합리적이었어요. 하지만 고객에게 지금의 쿠폰 모듈은 사용 할 수 있는 쿠폰이 여러 군데 흩어져 보이고, 어떤 쿠폰이 적용되는지 명확하지 않고 지금 받는 혜택이 최적인지 확신하기 어려운 상태였어요. 결국 문제는 구조 자체가 아니라, 그 구조가 고객의 언어로 번역되지 않았다는 점이었어요. 그래서 자연스럽게 또 하나의 질문이 생겼어요. "지금의 쿠폰 UX는 고객이 혜택을 제대로 이해하고 선택하도록 돕고 있을까?" 이 질문에 답을 얻기 위해 실제 고객을 대상으로 UT(Usability Test)를 진행했어요. 현재 제공되는 쿠폰의 혜택을 고객이 얼마나 잘 활용하고 체감하는지, 숙소 탐색부터 구매 직전까지의 과정을 관찰하며 검증했어요. UT 결과: 쿠폰은 많았지만, 확신은 없었다 문제 1. 쿠폰 구조의 복잡성 다운로드 쿠폰 자동 적용 쿠폰 특정 카테고리 전용 쿠폰 쿠폰의 종류도 다양했고, 쿠폰을 받는 퍼널도 분산돼 있었어요. 운영 측면에서는 유연했지만, 고객은 한눈에 이해하기 어려웠어요. 어떤 쿠폰을 언제 받아야 하는지 지금 이 숙소에 어떤 쿠폰이 최대 혜택인지 명확하게 보이지 않았어요. 문제 2. 혜택에 대한 낮은 체감 UT에서 반복적으로 나온 질문은 이거였어요. "이게 제일 할인 많이 되는 거죠?" 여러 쿠폰이 보이지만 내가 더 좋은 쿠폰을 놓치고 있는 건 아닌지, 지금 보이는 가격이 최종 가격이 맞는지 확신이 부족했어요. 이런 불확실성이 남아 있었고, 이는 곧 혜택에 대한 신뢰도 저하로 이어질 수 있는 문제였어요. 문제 3. 직관적이지 않은 쿠폰명과 종류 쿠폰명을 살펴보면 내부 정책이나 조건을 반영한 이름들이 많았어요. 운영과 기획 관점에서는 익숙했지만, 고객에게는 의미를 직관적으로 전달하기 어려웠죠. 특히 같은 특성의 쿠폰도 카테고리별로 다른 이름으로 소통되고 있었죠. 발견된 문제를 바탕으로 빠른 개선을 위해 기존 쿠폰 구조는 유지하되, 고객이 혜택을 더 직관적으로 이해할 수 있는 방법을 고민하게 되었어요. 그 과정에서 PLP-PDP-ILP-주문서까지 이어지는 전체 퍼널 안에서 쿠폰이 반영된 최대 혜택가를 일관되게 보여준다면 , 고객이 별도의 비교나 계산 없이도 최적의 혜택으로 예약할 수 있을 것이라는 가설을 수립 했어요. 이를 바탕으로 세 가지 솔루션을 제안했어요. 솔루션1. 전 카테고리 쿠폰 시스템을 UX 기준으로 재정비 먼저, 카테고리별로 흩어져 있던 쿠폰 구조를 정리했어요. 숙소 디테일 페이지에 앱과 웹 동일한 기준으로 노출하고, 쿠폰 역할과 노출 위치를 통일한 뒤, "지금 적용 가능한 쿠폰'이 무엇인지 구조화했어요. 따라서 어디에서 보더라도 같은 기준으로 이해할 수 있도록 만들었죠. 쿠폰의 역할과 노출 위치를 통일 고객이 '지금 적용 가능한 쿠폰'을 바로 인지할 수 있도록 구조화 솔루션 2. 퍼널 전반에서 '최대 혜택'을 일관되게 인지하도록 설계 기존에는 PLP, PDP, 주문서가 각각 독립적으로 설계되어 있었어요. 쿠폰은 화면마다 다르게 보였고, 고객은 단계마다 다시 이해해야 했죠. 그래서 쿠폰을 개별 기능이 아니라 하나의 '경험 흐름'으로 재정의했어요. 리스트(PLP)에서 혜택 존재를 인지하고 상세(PDP/ILP)에서 최대 혜택을 이해하며 주문서에서 적용 결과를 명확히 확인하도록 설계했어요. 특히 주문서에서는 쿠폰명과 쿠폰 종류를 함께 노출하고, 적용 전·후 금액 차이를 명확히 보여주도록 개선했어요. 이를 통해 고객은 여러 쿠폰을 비교하거나 계산하지 않아도, 현재 조건에서 받을 수 있는 최대 혜택이 무엇인지 자연스럽게 이해할 수 있게 되었어요. 결과적으로 쿠폰은 '선택해야 할 옵션'이 아니라, "이게 제일 좋은 선택이구나 "라고 납득할 수 있는 구조로 바뀌었어요. 솔루션 3. 쿠폰명과 종류의 재정의 기존의 복잡한 쿠폰명을 정리하고, 고객 입장에서 바로 이해할 수 있는 언어 로 통합하고, 주문/결제 단계 에서도 쿠폰 종류와 적용 결과를 명확히 확인하도록 통일했어요. UX Writing Evangelist로서의 역할은 여기서 끝이 아니었어요. 이 기준을 일회성으로 끝내지 않고, '앞으로 쿠폰 이름은 이렇게 만든다'는 공통 원칙 으로 정리해 팀 내에 공유하고 전파했어요. 이해되는 순간이 구매 전환을 만든다 이번 실험을 통해 한 가지를 분명하게 확인할 수 있었어요 . 쿠폰 경험에서 중요한 건 '얼마나 더 할인했는가'가 아니라, '어떻게 보여줬는가'였어요. 기존에는 쿠폰을 확인하고, 비교하고, 적용하는 과정에서 여러 단계를 거쳐야 했고, 그 과정에서 자연스럽게 고민과 계산이 필요했어요. 하지만 퍼널 전반에서 쿠폰이 반영된 가격과 혜택을 일관되게 보여주도록 구조를 정리하자, 고객은 더 이상 고민하거나 계산하지 않아도 되었어요. 그 결과 리드타임이 줄어들고, 쿠폰 사용률은 44% 증가하는 변화를 확인할 수 있었어요. 이 성과는 할인율을 더 정교하게 설계한 결과라기보다, 적절한 순간에 고민 없이 혜택을 이해할 수 있도록 만든 UX가 만들어낸 결과에 가까웠어요. AS-IS에서는 혜택이 많아 보이기만 했지만, TO-BE에서는 혜택이 이해되기 시작했어요. 이번 프로젝트를 통해 배운 점은 명확했어요. 전 카테고리를 아우르는 쿠폰 시스템은 정책이 아니라 경험 기준으로 정렬되어야 하고, 고객이 체감하는 혜택은 단순한 숫자가 아니라 '이해되는 순간'에서 만들어진다는 점 이에요. 결국 쿠폰은 숫자의 문제가 아니라 이해의 문제였어요 . 앞으로도 우리는 유저와 비즈니스 사이에서, 두 관점을 모두 납득시킬 수 있는 균형을 계속 고민해보려 해요. ✔️ 글쓴이를 더 알고 싶다면?: 링크드인 편집: 이소연 (Jetty) UX Writer 그래픽: 김제린 (Riny) Visual Interaction Designer **해당 글과 이미지를 인용 또는 재가공 시 출처를 꼭 밝혀주세요. 추천글 ・ 탐색을 돕는 광고 UX를 만들 수 있을까? ・ 작은 카드에 담긴 큰 문제를 풀다 ・ 더 잘 팔고, 잘 살 수 있는 방법 쿠폰은 많은데, 왜 혜택은 느껴지지 않았을까? was originally published in 여기어때 기술블로그 on Medium, where people are continuing the conversation by highlighting and responding to this story. | N52: https://cdn-images-1.medium.com/max/1024/1*PhO1EAci50SWKwbGk9KPvg.png | S52: 1 | T52: focus | U52: 2026-04-15 06:31:35 | V52: active | W52: 0 | Z52: 0 | AA52: 0 | AC52: 0 | AE52: 0 | AF52: 0 | AG52: 0 | AH52: 0
A53: 미확인 | B53: =IFERROR(INDEX('Source Check'!$A:$A, MATCH(C53, 'Source Check'!$B:$B, 0)), "미등록") | C53: 59 | D53: intercom.com | E53: https://www.intercom.com/blog/ | F53: =IFERROR(INDEX('Source Check'!$E:$E, MATCH(C53, 'Source Check'!$B:$B, 0)), "") | G53: 7738 | H53: https://www.intercom.com/blog/ | J53: intercom.com | S53: 1 | T53: focus | U53: 2026-04-15 06:31:34 | V53: active | W53: 0 | Z53: 0 | AA53: 0 | AC53: 0 | AE53: 0 | AF53: 1 | AG53: 1 | AH53: 1
A54: 미확인 | B54: =IFERROR(INDEX('Source Check'!$A:$A, MATCH(C54, 'Source Check'!$B:$B, 0)), "미등록") | C54: 59 | D54: intercom.com | E54: https://www.intercom.com/blog/ | F54: =IFERROR(INDEX('Source Check'!$E:$E, MATCH(C54, 'Source Check'!$B:$B, 0)), "") | G54: 5240 | H54: http://intercom.com/customers | J54: customers | S54: 1 | T54: focus | U54: 2026-04-15 06:31:34 | V54: active | W54: 0 | Z54: 0 | AA54: 0 | AC54: 0 | AE54: 0 | AF54: 1 | AG54: 0 | AH54: 1
A55: 미확인 | B55: =IFERROR(INDEX('Source Check'!$A:$A, MATCH(C55, 'Source Check'!$B:$B, 0)), "미등록") | C55: 59 | D55: intercom.com | E55: https://www.intercom.com/blog/ | F55: =IFERROR(INDEX('Source Check'!$E:$E, MATCH(C55, 'Source Check'!$B:$B, 0)), "") | G55: 5239 | H55: http://intercom.com/support-for-agents | J55: support for agents | S55: 1 | T55: focus | U55: 2026-04-15 06:31:34 | V55: active | W55: 0 | Z55: 0 | AA55: 0 | AC55: 0 | AE55: 0 | AF55: 1 | AG55: 0 | AH55: 1
A56: 미확인 | B56: =IFERROR(INDEX('Source Check'!$A:$A, MATCH(C56, 'Source Check'!$B:$B, 0)), "미등록") | C56: 59 | D56: intercom.com | E56: https://www.intercom.com/blog/ | F56: =IFERROR(INDEX('Source Check'!$E:$E, MATCH(C56, 'Source Check'!$B:$B, 0)), "") | G56: 5238 | H56: http://intercom.com/support-for-customers? | J56: support for customers | S56: 1 | T56: focus | U56: 2026-04-15 06:31:34 | V56: active | W56: 0 | Z56: 0 | AA56: 0 | AC56: 0 | AE56: 0 | AF56: 1 | AG56: 0 | AH56: 1
A57: 미확인 | B57: =IFERROR(INDEX('Source Check'!$A:$A, MATCH(C57, 'Source Check'!$B:$B, 0)), "미등록") | C57: 59 | D57: intercom.com | E57: https://www.intercom.com/blog/ | F57: =IFERROR(INDEX('Source Check'!$E:$E, MATCH(C57, 'Source Check'!$B:$B, 0)), "") | G57: 3957 | H57: https://www.intercom.com/blog/from-swarms-to-product-turning-customer-signals-into-scalable-features/ | J57: From swarms to product: Turning customer signals into scalable features | L57: The best product signal often comes from the least scalable work. Here's how Intercom's swarm model turns individual customer insights into features that reach everyone. | N57: https://blog.intercomassets.com/blog/wp-content/uploads/2026/04/image2.png | S57: 1 | T57: focus | U57: 2026-04-15 06:31:34 | V57: active | W57: 0 | Z57: 0 | AA57: 0 | AC57: 0 | AE57: 0 | AF57: 0 | AG57: 0 | AH57: 0
A58: 미확인 | B58: =IFERROR(INDEX('Source Check'!$A:$A, MATCH(C58, 'Source Check'!$B:$B, 0)), "미등록") | C58: 59 | D58: intercom.com | E58: https://www.intercom.com/blog/ | F58: =IFERROR(INDEX('Source Check'!$E:$E, MATCH(C58, 'Source Check'!$B:$B, 0)), "") | G58: 3956 | H58: https://www.intercom.com/blog/the-hardest-percentages/ | J58: The hardest percentages | L58: Solving your customers' most challenging problems is what your support team exists for. With Procedures, Fin can do this too. | N58: https://blog.intercomassets.com/blog/wp-content/uploads/2026/04/Time-spent-across-different-query-types.png | S58: 1 | T58: focus | U58: 2026-04-15 06:31:34 | V58: active | W58: 0 | Z58: 0 | AA58: 0 | AC58: 0 | AE58: 0 | AF58: 0 | AG58: 0 | AH58: 0
A59: 미확인 | B59: =IFERROR(INDEX('Source Check'!$A:$A, MATCH(C59, 'Source Check'!$B:$B, 0)), "미등록") | C59: 59 | D59: intercom.com | E59: https://www.intercom.com/blog/ | F59: =IFERROR(INDEX('Source Check'!$E:$E, MATCH(C59, 'Source Check'!$B:$B, 0)), "") | G59: 512 | H59: https://www.intercom.com/blog/procedures-simulations-updates/ | J59: Announcing major updates to Procedures and Simulations: Enabling Fin to handle complex queries | L59: See the latest updates to Procedures and Simulations, the foundation of how Fin handles complex work. | N59: https://blog.intercomassets.com/blog/wp-content/uploads/2056/02/V2_T1AnnouncementProcedures_Blog_Hero_3600x1680-1-scaled.png | S59: 1 | T59: focus | U59: 2026-04-15 06:31:34 | V59: active | W59: 0 | Z59: 0 | AA59: 0 | AC59: 0 | AE59: 0 | AF59: 0 | AG59: 0 | AH59: 0
A60: 미확인 | B60: =IFERROR(INDEX('Source Check'!$A:$A, MATCH(C60, 'Source Check'!$B:$B, 0)), "미등록") | C60: 59 | D60: intercom.com | E60: https://www.intercom.com/blog/ | F60: =IFERROR(INDEX('Source Check'!$E:$E, MATCH(C60, 'Source Check'!$B:$B, 0)), "") | G60: 511 | H60: https://www.intercom.com/blog/how-ai-is-evolving-support-careers/ | J60: Transformation in action: How AI is evolving support careers | L60: AI is changing what it means to work in support. Here's what this looks like in practice. | N60: https://blog.intercomassets.com/blog/wp-content/uploads/2026/02/Screenshot-2026-02-27-at-14.11.09.png | S60: 1 | T60: focus | U60: 2026-04-15 06:31:34 | V60: active | W60: 0 | Z60: 0 | AA60: 0 | AC60: 0 | AE60: 0 | AF60: 0 | AG60: 0 | AH60: 0
A61: 미확인 | B61: =IFERROR(INDEX('Source Check'!$A:$A, MATCH(C61, 'Source Check'!$B:$B, 0)), "미등록") | C61: 59 | D61: intercom.com | E61: https://www.intercom.com/blog/ | F61: =IFERROR(INDEX('Source Check'!$E:$E, MATCH(C61, 'Source Check'!$B:$B, 0)), "") | G61: 510 | H61: https://www.intercom.com/blog/support-is-the-blueprint-for-company-wide-ai/ | J61: Transformation in action: When support becomes the blueprint for company-wide AI | L61: As AI spreads beyond support, the teams who pioneered it are becoming the blueprint for company-wide transformation. | N61: https://blog.intercomassets.com/blog/wp-content/uploads/2026/03/Screenshot-2026-03-02-at-14.43.37.png | S61: 1 | T61: focus | U61: 2026-04-15 06:31:34 | V61: active | W61: 0 | Z61: 0 | AA61: 0 | AC61: 0 | AE61: 0 | AF61: 0 | AG61: 0 | AH61: 0
A62: 미확인 | B62: =IFERROR(INDEX('Source Check'!$A:$A, MATCH(C62, 'Source Check'!$B:$B, 0)), "미등록") | C62: 59 | D62: intercom.com | E62: https://www.intercom.com/blog/ | F62: =IFERROR(INDEX('Source Check'!$E:$E, MATCH(C62, 'Source Check'!$B:$B, 0)), "") | G62: 509 | H62: https://www.intercom.com/blog/fin-product-updates-february-recap/ | J62: Fin Product Updates: February recap | L62: Over the past four weeks, we've shipped major improvements to Procedures and Simulations, enhanced the Fin Voice experience, and made it significantly easier to set Fin up as a personalized shopping assistant. | N62: https://blog.intercomassets.com/blog/wp-content/uploads/2056/03/Screenshot-2026-03-09-at-8.20.10-PM.png | S62: 1 | T62: focus | U62: 2026-04-15 06:31:34 | V62: active | W62: 0 | Z62: 0 | AA62: 0 | AC62: 0 | AE62: 0 | AF62: 0 | AG62: 0 | AH62: 0
A63: 미확인 | B63: =IFERROR(INDEX('Source Check'!$A:$A, MATCH(C63, 'Source Check'!$B:$B, 0)), "미등록") | C63: 59 | D63: intercom.com | E63: https://www.intercom.com/blog/ | F63: =IFERROR(INDEX('Source Check'!$E:$E, MATCH(C63, 'Source Check'!$B:$B, 0)), "") | G63: 508 | H63: https://www.intercom.com/blog/from-resolutions-to-outcomes-evolving-how-fin-delivers-value/ | J63: From resolutions to outcomes: Evolving how Fin delivers value | L63: Resolutions were the right place to start. But as Fin got more powerful, success stopped being binary. | N63: https://blog.intercomassets.com/blog/wp-content/uploads/2026/03/Fin-resolution-rates.png | S63: 1 | T63: focus | U63: 2026-04-15 06:31:34 | V63: active | W63: 0 | Z63: 0 | AA63: 0 | AC63: 0 | AE63: 0 | AF63: 0 | AG63: 0 | AH63: 0
A64: 미확인 | B64: =IFERROR(INDEX('Source Check'!$A:$A, MATCH(C64, 'Source Check'!$B:$B, 0)), "미등록") | C64: 59 | D64: intercom.com | E64: https://www.intercom.com/blog/ | F64: =IFERROR(INDEX('Source Check'!$E:$E, MATCH(C64, 'Source Check'!$B:$B, 0)), "") | G64: 507 | H64: https://www.intercom.com/blog/automate-customer-service-while-improving-customer-experience/ | J64: Transformation in action: What it takes to automate 81% of your customer service while improving CX | L64: We build Fin. We also run our support on it. Here's what three years of committing fully to AI-first transformation has produced. | N64: https://blog.intercomassets.com/blog/wp-content/uploads/2056/03/Fin-Flywheel-scaled.png | S64: 1 | T64: focus | U64: 2026-04-15 06:31:34 | V64: active | W64: 0 | Z64: 0 | AA64: 0 | AC64: 0 | AE64: 0 | AF64: 0 | AG64: 0 | AH64: 0
A65: 미확인 | B65: =IFERROR(INDEX('Source Check'!$A:$A, MATCH(C65, 'Source Check'!$B:$B, 0)), "미등록") | C65: 59 | D65: intercom.com | E65: https://www.intercom.com/blog/ | F65: =IFERROR(INDEX('Source Check'!$E:$E, MATCH(C65, 'Source Check'!$B:$B, 0)), "") | G65: 506 | H65: https://www.intercom.com/blog/kaizen-for-the-ai-era-how-small-improvements-build-smarter-support/ | J65: Kaizen for the AI era: How small improvements build smarter support | L65: Small changes, compounding results. Here's how we build continuous improvement into how we deliver AI-powered support. | N65: https://blog.intercomassets.com/blog/wp-content/uploads/2056/03/Fin-Flywheel-scaled.png | S65: 1 | T65: focus | U65: 2026-04-15 06:31:34 | V65: active | W65: 0 | Z65: 0 | AA65: 0 | AC65: 0 | AE65: 0 | AF65: 0 | AG65: 0 | AH65: 0
A66: 미확인 | B66: =IFERROR(INDEX('Source Check'!$A:$A, MATCH(C66, 'Source Check'!$B:$B, 0)), "미등록") | C66: 59 | D66: intercom.com | E66: https://www.intercom.com/blog/ | F66: =IFERROR(INDEX('Source Check'!$E:$E, MATCH(C66, 'Source Check'!$B:$B, 0)), "") | G66: 505 | H66: https://www.intercom.com/blog/announcing-monitors-opening-the-ai-black-box/ | J66: Announcing Monitors: Opening the AI black box | L66: Learn about Monitors, a new product area for Fin that sits alongside Insights and Recommendations to give you a full observability suite. | N66: https://blog.intercomassets.com/blog/wp-content/uploads/2026/03/image1.png | S66: 1 | T66: focus | U66: 2026-04-15 06:31:34 | V66: active | W66: 0 | Z66: 0 | AA66: 0 | AC66: 0 | AE66: 0 | AF66: 0 | AG66: 0 | AH66: 0
A67: 미확인 | B67: =IFERROR(INDEX('Source Check'!$A:$A, MATCH(C67, 'Source Check'!$B:$B, 0)), "미등록") | C67: 59 | D67: intercom.com | E67: https://www.intercom.com/blog/ | F67: =IFERROR(INDEX('Source Check'!$E:$E, MATCH(C67, 'Source Check'!$B:$B, 0)), "") | G67: 504 | H67: https://www.intercom.com/blog/announcing-fin-apex-the-age-of-vertical-models-is-here/ | J67: Announcing Fin Apex: The age of vertical models is here | L67: We've just shipped the most significant new technology in the customer service agent category: Apex, a brand new model for Fin. | N67: https://blog.intercomassets.com/blog/wp-content/uploads/2026/03/apex-1.png | S67: 1 | T67: focus | U67: 2026-04-15 06:31:34 | V67: active | W67: 0 | Z67: 0 | AA67: 0 | AC67: 0 | AE67: 0 | AF67: 0 | AG67: 0 | AH67: 0
A68: 미확인 | B68: =IFERROR(INDEX('Source Check'!$A:$A, MATCH(C68, 'Source Check'!$B:$B, 0)), "미등록") | C68: 59 | D68: intercom.com | E68: https://www.intercom.com/blog/ | F68: =IFERROR(INDEX('Source Check'!$E:$E, MATCH(C68, 'Source Check'!$B:$B, 0)), "") | G68: 503 | H68: https://www.intercom.com/blog/introducing-the-fin-api-platform/ | J68: Never stop disrupting yourself; introducing the Fin API platform | L68: Last week, we announced Apex, the world's first specialized customer service LLM. We're now going to allow you to access all of this power and all of our core models directly via API. | N68: https://blog.intercomassets.com/blog/wp-content/uploads/2056/04/1775236158481.png | S68: 1 | T68: focus | U68: 2026-04-15 06:31:34 | V68: active | W68: 0 | Z68: 0 | AA68: 0 | AC68: 0 | AE68: 0 | AF68: 0 | AG68: 0 | AH68: 0
A69: 미확인 | B69: =IFERROR(INDEX('Source Check'!$A:$A, MATCH(C69, 'Source Check'!$B:$B, 0)), "미등록") | C69: 58 | D69: uxdesign.cc | E69: https://uxdesign.cc/ | F69: =IFERROR(INDEX('Source Check'!$E:$E, MATCH(C69, 'Source Check'!$B:$B, 0)), "") | G69: 6777 | H69: https://uxdesign.cc/ | J69: uxdesign.cc | S69: 1 | T69: focus | U69: 2026-04-15 06:31:33 | V69: active | W69: 0 | Z69: 0 | AA69: 0 | AC69: 0 | AE69: 0 | AF69: 1 | AG69: 1 | AH69: 1
A70: 미확인 | B70: =IFERROR(INDEX('Source Check'!$A:$A, MATCH(C70, 'Source Check'!$B:$B, 0)), "미등록") | C70: 58 | D70: uxdesign.cc | E70: https://uxdesign.cc/ | F70: =IFERROR(INDEX('Source Check'!$E:$E, MATCH(C70, 'Source Check'!$B:$B, 0)), "") | G70: 409 | H70: https://uxdesign.cc/data-models-the-shared-language-your-ai-and-team-are-both-missing-e36807c7f665?source=rss----138adf9c44c---4 | J70: data models the shared language your ai and team are both missing e36807c7f665 | L70: The one thing your team needs to agree on before prompting any AI tool Have you seen that meme with the guy pointing at a wall covered in papers, pictures, and strings and conspiracy theories? That was me when ChatGPT came out, pointing at a screen saying "it's just clusters and vectors, it's not magic." Nobody cared. Yet. This is what it looks like when you understand something before everyone else does. Or at least that's what it feels like. Charlie Kelly from It's Always Sunny in Philadelphia, FX Networks. Used for editorial and illustrative purposes. Back in 2020 I was working at a startup that collected, processed, augmented and delivered insights about points of interest, physical locations and all the data you can attach to them. My role at that point was somewhere between designer, PM, analyst, and person trying to survive a pandemic at a small but successful startup. Our CTO knew we had to get more technical to stay competitive, so he brought in a data scientist and pushed us all to engage with the work seriously. There was a lot of math, a Python library called pandas that I still can't fully explain, and diagrams I stared at longer than I'd like to admit. Then he sent us a paper. I still think about that abstract, which is corny but true. It was called "Attention Is All You Need," published in 2017 by a team of researchers at Google, and I'd argue it's one of the most consequential things written in the last decade. The architecture it introduced, the transformer, is the foundation underneath every large language model you've used. What made it click for me wasn't the math. It was the concept. Before this, AI processed information sequentially, word by word, often losing the thread by the time it reached the end of a sentence. The attention mechanism changed that. It let the model look at everything at once and learn what to focus on, what to weight heavily, what to set aside. The model developed something that looks a lot like judgment about relevance. The transformer architecture from "Attention Is All You Need". Vaswani et al., Video: youtube.com/watch?v=iDulhoQ2pro So if attention is how the model decides what matters, vectors and clusters are where it actually puts that attention. Think of it this way: instead of storing words as definitions, the model represents them as points in space. Words with related meanings end up close together. Clusters form. "Invoice," "payment," and "receipt" live near each other. "Dashboard," "metric," and "report" form their own neighborhood. Meaning lives in the relationships, not in the words themselves. Which means if your team calls the same thing three different names, the model isn't confused because it's dumb. It's confused because you are. This is how words clustering would look like, each word being a vector. Visualization generated by the author. The real reason your AI keeps getting it wrong As designers we wear a lot of hats. The one that matters most right now isn't UI, or systems, or even UX. It's language. We use words to make sense of things. Without shared definitions, even a simple diagram like this becomes ambiguous This past week I was presenting analytics to a client and he stopped me mid-sentence: "what does intent mean, what does it mean to you and your team, because I'm understanding it differently and I'm not sure the client even meant that." Intent was the output of the LLM . Not necessarily wrong. We had just all been naming the same thing differently, and nobody had caught it until that moment. When it was just humans in the room, that was an awkward meeting. Now that AI is in the room too, it's the kind of misalignment that ships. The moment AI is in the loop, language gaps stop being a coordination issue and start being a product issue. The model doesn't ask for clarification. It doesn't flag ambiguity. It just acts on whatever definition it inferred, confidently, at scale. So what does it take to make sure the model is working from the same definitions as your team? That's what a data model is for. The following is a practical guide to building one with your team, for whatever AI product you're working on, so it makes sense to you, the AI, and ultimately the people you're building for. Before you build anything, name the things: entities For the sake of this exercise, let's start fresh. We're building a food delivery app. Such an innovation, I know. FYI entity is any thing in your system that has a name, a definition, and attributes that describe it. The noun your whole team needs to agree on before anyone builds anything. Before we list a single entity, we need to know what we're trying to make someone feel. In this case: a hungry person orders food and it shows up. Fast, correct, no friction. That experience is the constraint. Everything we define has to serve it. Eight entities. Named, defined, one sentence each. This is where the data model starts. So let's list what we actually need for that to work: User: the person ordering food, they have a location, preferences, and an order history. Restaurant: the place preparing the food, they have a menu, hours, and a location. Menu item: a specific dish or product a restaurant offers, it has a name, a price, and it belongs to a restaurant. Order: the transaction connecting a user to a restaurant, it has a status, a list of items, a total, and a timestamp. Driver: the person delivering the order, they have a location, availability, and an assigned order. Delivery: the physical act of getting the order from restaurant to user, it has a route, a status, and an estimated time. Payment: the financial record of the transaction, it belongs to an order and has a status. Review: feedback left by the user after the delivery, it references the order, the restaurant, and sometimes the driver. Those are entities. Defined, named, one sentence each. That's step one. You probably already work with a version of this and don't call it that. Designers will recognize it as an entity relationship diagram, a tool for mapping how concepts connect. PMs have fragments of it scattered across acceptance criteria and data requirements in tickets. This isn't a new idea. Engineers have been doing this for decades, and have been asking for this shared language for a while. Three versions of the same map, rarely shared. What's changed is that AI made it everyone's problem. When a model has to reason over your product, vague definitions don't just slow down a sprint. They become the product. Your entities have something in common. Find it. A list is not a model. A list is just words. To make it useful we need to do what the transformer did with language: cluster things that belong together. he same eight entities, now grouped by what they have in common. A list becomes a model the moment things belong somewhere. Our eight entities don't all live in the same neighborhood. Let's group them: People and identity: User, Driver. These are the humans in the system, each with their own context, permissions, and goals. The offer: Restaurant, Menu Item. This is what's available, what can be ordered, what belongs to whom. The transaction: Order, Payment. This is the moment something happens, money moves, a commitment is made. The experience: Delivery, Review. This is what the user actually feels, the wait, the arrival, the reflection after. You could take this clustering and sketch wireframes right now, but it's still not enough. Because we haven't told the system how these clusters relate to each other. This is where most teams stop too early. The relationships your AI can't guess It might feel obvious that an Order belongs to a User, or that a Delivery references a Driver. But obvious to a human and explicit to a system are very different things. The model can't infer relationships the way we do. It needs them stated. When working with AI tools, giving them more stuff doesn't always give you better results. I learned this the hard way while trying to spin up a proof of concept. I had Figma Make, a PRD, a design system, a list of requirements. I thought it would take an afternoon. It did not. The outputs were generic, misaligned, and confidently wrong in ways that were hard to even explain. The tool just didn't know where to put its attention. That's when I dove into data models seriously. The entity relationship diagram with connectors labeled. Every arrow is a decision the model no longer has to guess. Let's make the relationships explicit, using three questions: What does it produce? One thing creates another as a direct result. A Restaurant produces Menu Items. An Order produces a Payment. A completed Delivery produces a Review. What does it reference? One thing points to another that exists independently. An Order references a User, a Restaurant, and one or more Menu Items. A Delivery references an Order and a Driver. Neither owns the other, they just know about each other. What does it influence? One thing shapes how another behaves or is prioritized, without creating it directly. User preferences influence which Restaurants surface first. Order history influences delivery time estimates. This is the relationship type that matters most to AI, because it's how context shapes decisions without being explicitly stated every time. Those three questions are your connectors. And if you've ever drawn a user flow where one screen leads to another, or mapped ticket dependencies in a sprint, you've already done this kind of thinking. The diagram just makes it explicit and shared. Additionally every end of every arrow can be a rule. Define it clearly and your AI, your engineer, and your PM are all reading the same map. This is also where the parallel to the attention mechanism closes. The entities are the clusters. The connectors are the attention. You're defining the relationships that give those things meaning. Now step back. Look at what you have. A set of named, defined entities. Grouped into clusters that make intuitive sense. Connected by relationships that are explicit enough for a model, a designer, a PM, and an engineer to all read the same way. This is an example of a diagram I built for one of my teams. This was before we implemented some AI agents. Entity names have been anonymized. Build it together When I first presented this to my team I wasn't sure how it would land. Data models sound technical. The word alone can make a designer's eyes glaze over or make a PM reach for their phone. So I showed it instead of explaining it. Here's the model, here's the prompt I built from it, here's what Figma Make produced. The prompt wasn't long. It looked something like: "Using this data model… create a … for a user who… and wants to complete…." One prompt, took 5 minutes, put it into Figma Make and you get something you can concept test, not a generic card layout, but a screen that knew what to surface and what to hold back. The output from a single prompt, built on the data model. The Driver surfaces first because the Delivery relationship made movement the priority. The Restaurant drops to the map because the offer cluster is reference, not focus. The progress tracker reflects Order status. None of that was designed manually. It was inferred from structure. Prototype generated with Figma Make by the author. PROMPT EXAMPLE: Design the order tracking screen for a hungry person who has just placed an order on a food delivery app. Use the following data model as the underlying logic for every decision you make about what to show, what to hide, and what to prioritize. **Entities and their attributes:** User: has a location, preferences, and an order history. Restaurant: has a name, a menu, hours, and a location. Menu item: has a name, a price, and belongs to a Restaurant. Order: has a status, a list of items, a total, and a timestamp. References a User, a Restaurant, and one or more Menu Items. Driver: has a name, a location, and an availability status. Delivery: has a route, a status, and an estimated time. References an Order and a Driver. Payment: has a status and belongs to an Order. Review: references the Order, the Restaurant, and sometimes the Driver. **Cluster priorities for this screen:** The experience cluster (Delivery, Review) is the primary focus. The user is waiting. That feeling is the design constraint. The transaction cluster (Order, Payment) is secondary. Show confirmation, not complexity. The offer cluster (Restaurant, Menu Item) is reference only. It already happened. The people and identity cluster (User, Driver) surfaces the Driver prominently because movement is what the user cares about right now. **Relationships to reflect in the UI:** Delivery references a Driver: show the Driver's name and live location as the primary element. Order references a Restaurant and Menu Items: show these as a collapsible summary, not the focus. User preferences influence what surfaces first: if the user has ordered from this restaurant before, surface a familiar detail that builds trust. Order history influences tone: returning users get a lighter, more confident experience. First-time users get more guidance. A completed Delivery produces a Review: when status changes to delivered, transition immediately into a review prompt anchored to the Order and the Restaurant. **UI states to include:** Order confirmed, preparing, out for delivery, delivered. Driver location updating in real time. Estimated time prominent and updating. Review prompt on delivery completion. **Tone:** Calm, clear, reassuring. The user is hungry and waiting. Every element should reduce anxiety, not add to it. The engineer looked at the diagram and said "this is what we do." Not exactly the same format, not the same vocabulary, but the same idea. A shared map of what exists, what connects, and what it all means. A designer can facilitate it, and should. The designer's job is to translate everyone's input into a coherent shared structure. The PM brings requirements and context. The engineer brings technical judgment: what's feasible, what's fragile. The designer listens, organizes, and maps. By the time you're done you have something the engineer can build from, the PM can write tickets against, and the AI tool can actually reason over. The two logical next steps that AI came up with based on the information it had, such as the goal and the data model: where to save menu items for future orders, and give and adjust tip for the driver after a delivery was completed. Results are no longer random or disconnected from the experience. Prototypes generated with Figma Make by the author. This connects directly to the first principle in my previous piece on Agentic UX: think systematically. Agents rely on structured systems to act consistently. If the product's flows, labels, and hierarchies are messy, agent actions will feel random or confusing. The data model is where that systematic thinking starts, before the wireframes, before the tickets, before the prompts. It's the foundation everything else builds on. Where your product sits on this spectrum determines how ready it is for agents to act within it reliably. Framework from the author's work on agentic UX. Before your next sprint When an AI tool doesn't deliver, it's rarely the model's fault. And it's rarely the prompt, at least not in isolation. A prompt can only reason over what it's been given. If the definitions are vague, the relationships undefined, the language inconsistent across your team, no amount of prompt craft will close that gap. The data model is the cheapest investment you can make before building anything with AI. Three steps. In that order. The data model lives in step two, but nothing works without step one, and step three is the whole point. A data model saves you from the meeting where everyone argues about what "intent" means. Clarity upfront is the most efficient thing you can do. For your team, for your tools, and for the AI that will eventually try to reason over everything you're building. Also worth knowing: 51% of Figma users working on AI products are now building agents, up from 21% the year before. The teams moving fastest are the ones who figured out the foundations first. And if you want to take this one step further, the next piece in this series goes deeper into how to turn this map into a task diagram your whole team can build together, and how to use it to test a concept before a single ticket gets written. Because a shared language is only the beginning. What you do with it is where it gets interesting. The task diagram is an artifact that teams and AI use to quickly create deliverables. More on this in the next piece. References "Attention Is All You Need," Vaswani et al., Google, 2017 "I Finally Understood 'Attention Is All You Need' After So Long. Here's How I Did It," Olubusolami Sogunle , 2025 Attention Is All You Need [Video] , Yannic Kilcher, 2017 What is an entity relationship diagram, Figma Resource Library Speaking the Same Language: Engineering and Design in Product Teams, SafetyCulture Engineering, Medium, 2024 Agentic UX: 7 principles for designing systems with agents, Alexandra Vasquez, Medium Bootcamp, 2026 Figma 2025 AI Report, Figma Blog, 2025 Data models: the shared language your AI and team are both missing was originally published in UX Collective on Medium, where people are continuing the conversation by highlighting and responding to this story. | S70: 1 | T70: focus | U70: 2026-04-15 06:31:33 | V70: active | W70: 0 | Z70: 0 | AA70: 0 | AC70: 0 | AE70: 0 | AF70: 1 | AG70: 0 | AH70: 0
A71: 미확인 | B71: =IFERROR(INDEX('Source Check'!$A:$A, MATCH(C71, 'Source Check'!$B:$B, 0)), "미등록") | C71: 58 | D71: uxdesign.cc | E71: https://uxdesign.cc/ | F71: =IFERROR(INDEX('Source Check'!$E:$E, MATCH(C71, 'Source Check'!$B:$B, 0)), "") | G71: 406 | H71: https://uxdesign.cc/the-ux-ground-is-shaking-synthetic-users-building-perspective-38635c3677e1?source=rss----138adf9c44c---4 | J71: the ux ground is shaking synthetic users building perspective 38635c3677e1 | L71: Weekly curated resources for designers - thinkers and makers. "To have a perspective is to say 'no' to things that are technically possible but strategically wrong. Most products fail not because they lack features, but because they lack a clear stance on what they are not. Every feature added without a clear perspective dilutes the ones that actually matter. Design is an editorial act: the more you leave out, the more weight you give to what remains." Perspective → 5 design links a day, curated by the folks from UX Collective → For people who still believe in the web as a platform for knowledge sharing, long-form writing, and community. Editor picks The ground is shaking → Why designers must flip the script on AI. By Peter (Zak) Zakrzewski Designers finally have a say in the product they design → AI gave desugbers back the decisions that were always theirs. By Daniel Mitev Rethinking design awards in an AI world → Why design awards are still relevant and what needs to change. By Darren Yeo The UX Collective is an independent design publication that elevates unheard design voices and helps designers think more critically about their work. Ban Ray: Your face is not inventory → Make me think Your ticket is a prompt → "The agents are behaving like the tickets they learned from. The scope-narrowing, the deference to small pieces over whole outcomes, the instinct to fragment before thinking." Why are executives enamored with AI but ICs aren't? → "Here's my current posit for why there's such a big divide: executives have always had to deal with non-determinism and focus on nondeterministic system design, while individual contributors are evaluated by their execution on deterministic tasks." Take my job, AI! → "On the personal side, I've become more and more disillusioned with product design. It can be a shit role where you're stuck between product managers on one side, engineers on the other, "the business" above you, and your actual users below you. What remains is an increasingly cramped space for decisions we actually "own", which is basically which color lip stick to put on the pig." Little gems this week Every designer on my team ships the same quality now → By Hoang Nguyen AI is rewriting the rules; Language is following → By Dora Czerna The long and short of telephone progress → By Neel Dozome Tools and resources Context matters… A lot → Building intuitive AI products requires designing for context management. By Connor Joyce The many paths in the life of a designer → Way-finding in the work/life journey. By Filip Mishevski The rise of synthetic users → The future of consumer research? By Melek Akan Support the newsletter If you find our content helpful, here's how you can support us: Check out Sidebar.io and subscribe Forward this email to a friend and invite them to subscribe Sponsor an edition The UX ground is shaking, synthetic users, building perspective was originally published in UX Collective on Medium, where people are continuing the conversation by highlighting and responding to this story. | S71: 1 | T71: focus | U71: 2026-04-15 06:31:33 | V71: active | W71: 0 | Z71: 0 | AA71: 0 | AC71: 0 | AE71: 0 | AF71: 1 | AG71: 0 | AH71: 0
A72: 미확인 | B72: =IFERROR(INDEX('Source Check'!$A:$A, MATCH(C72, 'Source Check'!$B:$B, 0)), "미등록") | C72: 58 | D72: uxdesign.cc | E72: https://uxdesign.cc/ | F72: =IFERROR(INDEX('Source Check'!$E:$E, MATCH(C72, 'Source Check'!$B:$B, 0)), "") | G72: 404 | H72: https://uxdesign.cc/designing-for-the-invisible-customer-1e1bbeba56ae?source=rss----138adf9c44c---4 | J72: designing for the invisible customer 1e1bbeba56ae | L72: Are consumers' Openclaw agents becoming the real consumers? Continue reading on UX Collective | N72: https://cdn-images-1.medium.com/max/2600/1*X7m2rKd9Evfqy43no_6ACg.png | S72: 1 | T72: focus | U72: 2026-04-15 06:31:33 | V72: active | W72: 0 | Z72: 0 | AA72: 0 | AC72: 0 | AE72: 0 | AF72: 0 | AG72: 0 | AH72: 0
A73: 미확인 | B73: =IFERROR(INDEX('Source Check'!$A:$A, MATCH(C73, 'Source Check'!$B:$B, 0)), "미등록") | C73: 58 | D73: uxdesign.cc | E73: https://uxdesign.cc/ | F73: =IFERROR(INDEX('Source Check'!$E:$E, MATCH(C73, 'Source Check'!$B:$B, 0)), "") | G73: 403 | H73: https://uxdesign.cc/beyond-the-user-why-design-needs-to-widen-its-circle-5d6d6bca783e?source=rss----138adf9c44c---4 | J73: Beyond the user: why design needs to widen its circle | by Dora Czerna | Apr, 2026 | UX Collective | L73: Beyond the user: why design needs to widen its circle Human-centred design changed everything. But optimising for the individual while ignoring the planet may be the field's most expensive blind … | S73: 1 | T73: focus | U73: 2026-04-15 06:31:33 | V73: active | W73: 0 | Z73: 0 | AA73: 0 | AC73: 0 | AE73: 0 | AF73: 1 | AG73: 0 | AH73: 0
A74: 미확인 | B74: =IFERROR(INDEX('Source Check'!$A:$A, MATCH(C74, 'Source Check'!$B:$B, 0)), "미등록") | C74: 58 | D74: uxdesign.cc | E74: https://uxdesign.cc/ | F74: =IFERROR(INDEX('Source Check'!$E:$E, MATCH(C74, 'Source Check'!$B:$B, 0)), "") | G74: 402 | H74: https://uxdesign.cc/careful-liable-ux-is-a-thing-now-ff088a766de8?source=rss----138adf9c44c---4 | J74: careful liable ux is a thing now ff088a766de8 | L74: The recent ruling against Meta signals a shift that's been brewing for a minute. Deceptive or dark patterns are no longer just… Continue reading on UX Collective | N74: https://cdn-images-1.medium.com/max/2160/1*KNqPT56IAfnDLcIrCesRZg.png | S74: 1 | T74: focus | U74: 2026-04-15 06:31:33 | V74: active | W74: 0 | Z74: 0 | AA74: 0 | AC74: 0 | AE74: 0 | AF74: 0 | AG74: 0 | AH74: 0
A75: 미확인 | B75: =IFERROR(INDEX('Source Check'!$A:$A, MATCH(C75, 'Source Check'!$B:$B, 0)), "미등록") | C75: 58 | D75: uxdesign.cc | E75: https://uxdesign.cc/ | F75: =IFERROR(INDEX('Source Check'!$E:$E, MATCH(C75, 'Source Check'!$B:$B, 0)), "") | G75: 401 | H75: https://uxdesign.cc/the-old-design-workshop-is-dead-long-live-design-workshops-98f4ee58d9a7?source=rss----138adf9c44c---4 | J75: The old design workshop is dead. Long live design workshops. | by Kai Wong | Apr, 2026 | UX Collective | L75: How new leaner design workshops are succeeding in 2026 Continue reading on UX Collective | N75: https://cdn-images-1.medium.com/max/2600/1*EX4OMf4D_5yWw4uF8Bhv2A.jpeg | S75: 1 | T75: focus | U75: 2026-04-15 06:31:33 | V75: active | W75: 0 | Z75: 0 | AA75: 0 | AC75: 0 | AE75: 0 | AF75: 0 | AG75: 0 | AH75: 0
A76: 미확인 | B76: =IFERROR(INDEX('Source Check'!$A:$A, MATCH(C76, 'Source Check'!$B:$B, 0)), "미등록") | C76: 58 | D76: uxdesign.cc | E76: https://uxdesign.cc/ | F76: =IFERROR(INDEX('Source Check'!$E:$E, MATCH(C76, 'Source Check'!$B:$B, 0)), "") | G76: 400 | H76: https://uxdesign.cc/social-media-on-trial-32be44a6434e?source=rss----138adf9c44c---4 | J76: social media on trial 32be44a6434e | L76: How design was used to target vulnerable children Continue reading on UX Collective | N76: https://cdn-images-1.medium.com/max/1600/1*3g_rANzM6n-e5CcvZmrI_g.png | S76: 1 | T76: focus | U76: 2026-04-15 06:31:33 | V76: active | W76: 0 | Z76: 0 | AA76: 0 | AC76: 0 | AE76: 0 | AF76: 0 | AG76: 0 | AH76: 0
A77: 미확인 | B77: =IFERROR(INDEX('Source Check'!$A:$A, MATCH(C77, 'Source Check'!$B:$B, 0)), "미등록") | C77: 58 | D77: uxdesign.cc | E77: https://uxdesign.cc/ | F77: =IFERROR(INDEX('Source Check'!$E:$E, MATCH(C77, 'Source Check'!$B:$B, 0)), "") | G77: 399 | H77: https://uxdesign.cc/taste-md-e4fb75d9096f?source=rss----138adf9c44c---4 | J77: taste md e4fb75d9096f | L77: the new tech buzzword Continue reading on UX Collective | N77: https://cdn-images-1.medium.com/max/2550/1*VVhJBoOK4jFGmVa0vcq9kA.png | S77: 1 | T77: focus | U77: 2026-04-15 06:31:33 | V77: active | W77: 0 | Z77: 0 | AA77: 0 | AC77: 0 | AE77: 0 | AF77: 0 | AG77: 0 | AH77: 0
